Workbook

Sheet Dashboard
A1: Bank of Baroda Statement Analysis
A3: Period Covered | B3: Apr 2026 to Apr 2026 | I3: Period | J3: Receipts | K3: Payments | L3: Net | M3: Closing Balance | N3: Checks
A4: Statements Reviewed | B4: 1 | I4: ='Monthly Summary'!D2 | J4: ='Monthly Summary'!J2 | K4: ='Monthly Summary'!I2 | L4: =ROUND(J4-K4,2) | M4: ='Monthly Summary'!K2 | N4: ='Monthly Summary'!N2&"/"&'Monthly Summary'!O2
A5: Transactions Parsed | B5: 398
A7: Total Receipts | B7: ='Category Summary'!D2
A8: Total Payments | B8: ='Category Summary'!F2
A9: Net Movement | B9: =ROUND('Category Summary'!G2,2)
A10: Cash Receipts | B10: ='Category Summary'!D3
A11: High Transaction Value | B11: =ROUND('Category Summary'!D7-'Category Summary'!F7,2)
A12: Recurring Transaction Value | B12: =ROUND('Category Summary'!D4-'Category Summary'!F4,2)
A13: UPI / LIC / EMI / Salary | B13: =ROUND('Category Summary'!G8+'Category Summary'!G9+'Category Summary'!G5+'Category Summary'!G6,2)
A15: Category | B15: Receipt Count | C15: Receipts | D15: Payment Count | E15: Payments | F15: Net | G15: Action / View Detail
A16: ='Category Summary'!A2 | B16: ='Category Summary'!C2 | C16: ='Category Summary'!D2 | D16: ='Category Summary'!E2 | E16: ='Category Summary'!F2 | F16: ='Category Summary'!G2
A17: ='Category Summary'!A3 | B17: ='Category Summary'!C3 | C17: ='Category Summary'!D3 | D17: ='Category Summary'!E3 | E17: ='Category Summary'!F3 | F17: ='Category Summary'!G3
A18: ='Category Summary'!A4 | B18: ='Category Summary'!C4 | C18: ='Category Summary'!D4 | D18: ='Category Summary'!E4 | E18: ='Category Summary'!F4 | F18: ='Category Summary'!G4
A19: ='Category Summary'!A5 | B19: ='Category Summary'!C5 | C19: ='Category Summary'!D5 | D19: ='Category Summary'!E5 | E19: ='Category Summary'!F5 | F19: ='Category Summary'!G5
A20: ='Category Summary'!A6 | B20: ='Category Summary'!C6 | C20: ='Category Summary'!D6 | D20: ='Category Summary'!E6 | E20: ='Category Summary'!F6 | F20: ='Category Summary'!G6
A21: ='Category Summary'!A7 | B21: ='Category Summary'!C7 | C21: ='Category Summary'!D7 | D21: ='Category Summary'!E7 | E21: ='Category Summary'!F7 | F21: ='Category Summary'!G7
A22: ='Category Summary'!A8 | B22: ='Category Summary'!C8 | C22: ='Category Summary'!D8 | D22: ='Category Summary'!E8 | E22: ='Category Summary'!F8 | F22: ='Category Summary'!G8
A23: ='Category Summary'!A9 | B23: ='Category Summary'!C9 | C23: ='Category Summary'!D9 | D23: ='Category Summary'!E9 | E23: ='Category Summary'!F9 | F23: ='Category Summary'!G9
A24: ='Category Summary'!A10 | B24: ='Category Summary'!C10 | C24: ='Category Summary'!D10 | D24: ='Category Summary'!E10 | E24: ='Category Summary'!F10 | F24: ='Category Summary'!G10
A25: ='Category Summary'!A11 | B25: ='Category Summary'!C11 | C25: ='Category Summary'!D11 | D25: ='Category Summary'!E11 | E25: ='Category Summary'!F11 | F25: ='Category Summary'!G11
A26: ='Category Summary'!A12 | B26: ='Category Summary'!C12 | C26: ='Category Summary'!D12 | D26: ='Category Summary'!E12 | E26: ='Category Summary'!F12 | F26: ='Category Summary'!G12

Sheet Category Summary
A1: Requested Category | B1: Match Term | C1: Receipt Count | D1: Receipts | E1: Payment Count | F1: Payments | G1: Net | H1: Notes
A2: Total | C2: =COUNTIF(Transactions!$I$2:$I$399,"Receipt") | D2: =SUM(Transactions!$K$2:$K$399) | E2: =COUNTIF(Transactions!$I$2:$I$399,"Payment") | F2: =SUM(Transactions!$J$2:$J$399) | G2: =ROUND(D2-F2,2) | H2: All parsed receipts and payments.
A3: Cash | B3: Cash | C3: =COUNTIFS(Transactions!$Q$2:$Q$399,1,Transactions!$I$2:$I$399,"Receipt") | D3: =SUMIFS(Transactions!$K$2:$K$399,Transactions!$Q$2:$Q$399,1) | E3: =COUNTIFS(Transactions!$Q$2:$Q$399,1,Transactions!$I$2:$I$399,"Payment") | F3: =SUMIFS(Transactions!$J$2:$J$399,Transactions!$Q$2:$Q$399,1) | G3: =ROUND(D3-F3,2) | H3: Cash detected from CASH DEPOSIT BY narration.
A4: Recurring Transaction | B4: Recurring Transaction | C4: =COUNTIFS(Transactions!$R$2:$R$399,1,Transactions!$I$2:$I$399,"Receipt") | D4: =SUMIFS(Transactions!$K$2:$K$399,Transactions!$R$2:$R$399,1) | E4: =COUNTIFS(Transactions!$R$2:$R$399,1,Transactions!$I$2:$I$399,"Payment") | F4: =SUMIFS(Transactions!$J$2:$J$399,Transactions!$R$2:$R$399,1) | G4: =ROUND(D4-F4,2) | H4: Repeated counterpart/pattern appearing at least twice.
A5: EMI | B5: EMI | C5: =COUNTIFS(Transactions!$S$2:$S$399,1,Transactions!$I$2:$I$399,"Receipt") | D5: =SUMIFS(Transactions!$K$2:$K$399,Transactions!$S$2:$S$399,1) | E5: =COUNTIFS(Transactions!$S$2:$S$399,1,Transactions!$I$2:$I$399,"Payment") | F5: =SUMIFS(Transactions!$J$2:$J$399,Transactions!$S$2:$S$399,1) | G5: =ROUND(D5-F5,2) | H5: Keyword based: EMI/ECS/ACH/loan/installment.
A6: Salary | B6: Salary | C6: =COUNTIFS(Transactions!$T$2:$T$399,1,Transactions!$I$2:$I$399,"Receipt") | D6: =SUMIFS(Transactions!$K$2:$K$399,Transactions!$T$2:$T$399,1) | E6: =COUNTIFS(Transactions!$T$2:$T$399,1,Transactions!$I$2:$I$399,"Payment") | F6: =SUMIFS(Transactions!$J$2:$J$399,Transactions!$T$2:$T$399,1) | G6: =ROUND(D6-F6,2) | H6: Keyword based: salary.
A7: High Transaction | B7: High Transaction | C7: =COUNTIFS(Transactions!$U$2:$U$399,1,Transactions!$I$2:$I$399,"Receipt") | D7: =SUMIFS(Transactions!$K$2:$K$399,Transactions!$U$2:$U$399,1) | E7: =COUNTIFS(Transactions!$U$2:$U$399,1,Transactions!$I$2:$I$399,"Payment") | F7: =SUMIFS(Transactions!$J$2:$J$399,Transactions!$U$2:$U$399,1) | G7: =ROUND(D7-F7,2) | H7: Transactions with absolute amount at or above Rs 100,000.
A8: UPI | B8: UPI | C8: =COUNTIFS(Transactions!$V$2:$V$399,1,Transactions!$I$2:$I$399,"Receipt") | D8: =SUMIFS(Transactions!$K$2:$K$399,Transactions!$V$2:$V$399,1) | E8: =COUNTIFS(Transactions!$V$2:$V$399,1,Transactions!$I$2:$I$399,"Payment") | F8: =SUMIFS(Transactions!$J$2:$J$399,Transactions!$V$2:$V$399,1) | G8: =ROUND(D8-F8,2) | H8: Keyword based: UPI.
A9: LIC | B9: LIC | C9: =COUNTIFS(Transactions!$W$2:$W$399,1,Transactions!$I$2:$I$399,"Receipt") | D9: =SUMIFS(Transactions!$K$2:$K$399,Transactions!$W$2:$W$399,1) | E9: =COUNTIFS(Transactions!$W$2:$W$399,1,Transactions!$I$2:$I$399,"Payment") | F9: =SUMIFS(Transactions!$J$2:$J$399,Transactions!$W$2:$W$399,1) | G9: =ROUND(D9-F9,2) | H9: Keyword based: LIC.
A10: FD interest | B10: FD interest | C10: =COUNTIFS(Transactions!$X$2:$X$399,1,Transactions!$I$2:$I$399,"Receipt") | D10: =SUMIFS(Transactions!$K$2:$K$399,Transactions!$X$2:$X$399,1) | E10: =COUNTIFS(Transactions!$X$2:$X$399,1,Transactions!$I$2:$I$399,"Payment") | F10: =SUMIFS(Transactions!$J$2:$J$399,Transactions!$X$2:$X$399,1) | G10: =ROUND(D10-F10,2) | H10: Keyword based: FD plus interest/int.
A11: FD Deposit and withdrawals | B11: FD Deposit/Withdrawal | C11: =COUNTIFS(Transactions!$Y$2:$Y$399,1,Transactions!$I$2:$I$399,"Receipt") | D11: =SUMIFS(Transactions!$K$2:$K$399,Transactions!$Y$2:$Y$399,1) | E11: =COUNTIFS(Transactions!$Y$2:$Y$399,1,Transactions!$I$2:$I$399,"Payment") | F11: =SUMIFS(Transactions!$J$2:$J$399,Transactions!$Y$2:$Y$399,1) | G11: =ROUND(D11-F11,2) | H11: Keyword based: FD/fixed deposit/TDR/term deposit.
A12: PPF/PF interest and contribution | B12: PPF/PF interest/contribution | C12: =COUNTIFS(Transactions!$Z$2:$Z$399,1,Transactions!$I$2:$I$399,"Receipt") | D12: =SUMIFS(Transactions!$K$2:$K$399,Transactions!$Z$2:$Z$399,1) | E12: =COUNTIFS(Transactions!$Z$2:$Z$399,1,Transactions!$I$2:$I$399,"Payment") | F12: =SUMIFS(Transactions!$J$2:$J$399,Transactions!$Z$2:$Z$399,1) | G12: =ROUND(D12-F12,2) | H12: Keyword based: PPF/PF/EPF/provident fund.

Sheet Category Details
A1: Category Details
A3: Category | B3: Detail Sheet | C3: Rows | D3: Receipt Count | E3: Receipts | F3: Payment Count | G3: Payments | H3: Net
A4: Total | B4: Detail Total | C4: 398 | D4: 283 | E4: 17768567 | F4: 115 | G4: 18129258 | H4: -360691
A5: Cash | B5: Detail Cash | C5: 2 | D5: 1 | E5: 114500 | F5: 1 | G5: 24 | H5: 114476
A6: Recurring Transaction | B6: Detail Recurring Transaction | C6: 346 | D6: 250 | E6: 15926651 | F6: 96 | G6: 17904826 | H6: -1978174.6
A7: EMI | B7: Detail EMI | C7: 2 | D7: 2 | E7: 55541 | F7: 0 | G7: 0 | H7: 55541
A8: Salary | B8: Detail Salary | C8: 0 | D8: 0 | E8: 0 | F8: 0 | G8: 0 | H8: 0
A9: High Transaction | B9: Detail High Transaction | C9: 112 | D9: 59 | E9: 10963794 | F9: 53 | G9: 17146556 | H9: -6182762.4
A10: Total Receipts and Payments | B10: Detail Total Receipts and Payme | C10: 398 | D10: 283 | E10: 17768567 | F10: 115 | G10: 18129258 | H10: -360691
A11: UPI | B11: Detail UPI | C11: 36 | D11: 24 | E11: 416085 | F11: 12 | G11: 71816.63 | H11: 344268.37
A12: LIC | B12: Detail LIC | C12: 0 | D12: 0 | E12: 0 | F12: 0 | G12: 0 | H12: 0
A13: FD interest | B13: Detail FD interest | C13: 0 | D13: 0 | E13: 0 | F13: 0 | G13: 0 | H13: 0
A14: FD Deposit and withdrawals | B14: Detail FD Deposit and withdrawa | C14: 0 | D14: 0 | E14: 0 | F14: 0 | G14: 0 | H14: 0
A15: PPF/PF interest and contribution | B15: Detail PPF PF interest and cont | C15: 0 | D15: 0 | E15: 0 | F15: 0 | G15: 0 | H15: 0

Sheet Monthly Summary
A1: Month Key | B1: From | C1: To | D1: Period | E1: Transactions | F1: Opening Balance | G1: Dr Count | H1: Cr Count | I1: Payments | J1: Receipts | K1: Closing Balance | L1: Parsed Payments | M1: Parsed Receipts | N1: Payment Check | O1: Receipt Check
A2: 2026-04 | B2: 46113 | C2: 46143 | D2: Apr 2026 | E2: 398 | F2: 363191 | G2: 115 | H2: 283 | I2: 18129258 | J2: 17768567 | K2: 2500 | L2: =SUMIFS(Transactions!$J$2:$J$399,Transactions!$AA$2:$AA$399,">="&B2,Transactions!$AA$2:$AA$399,"<"&C2) | M2: =SUMIFS(Transactions!$K$2:$K$399,Transactions!$AA$2:$AA$399,">="&B2,Transactions!$AA$2:$AA$399,"<"&C2) | N2: =IF(ABS(I2-L2)<0.01,"OK","Check") | O2: =IF(ABS(J2-M2)<0.01,"OK","Check")

Sheet Transactions
A1: Seq | B1: Source File | C1: Statement From | D1: Statement To | E1: Date | F1: Value Date | G1: Narration | H1: Reference | I1: Direction | J1: Withdrawal | K1: Deposit | L1: Amount | M1: Closing Balance | N1: Categories | O1: Recurring? | P1: Recurring Key | Q1: Flag - Cash | R1: Flag - Recurring Transaction | S1: Flag - EMI | T1: Flag - Salary | U1: Flag - High Transaction | V1: Flag - UPI | W1: Flag - LIC | X1: Flag - FD interest | Y1: Flag - FD Deposit and withdrawals | Z1: Flag - PPF/PF interest and contribution | AA1: Month Date
A2: 1 | B2: 502 input.pdf | C2: 46113 | D2: 46142 | E2: 46114 | F2: 46114 | G2: DIGITA-MUMBAI/ IMPS/P2A/609147096215/HONEPELIMITEDPA/F09Hpcljige | I2: Receipt | J2: 0 | K2: 53200 | L2: 53200 | M2: 416391 | N2: Other | O2: No | P2: HONEPELIMITEDPA | Q2: 0 | R2: 0 | S2: 0 | T2: 0 | U2: 0 | V2: 0 | W2: 0 | X2: 0 | Y2: 0 | Z2: 0 | AA2: 46114
A3: 2 | B3: 502 input.pdf | C3: 46113 | D3: 46142 | E3: 46114 | F3: 46114 | G3: DIGITA-MUMBAI/ NEFT-YESAP60912594024-PhonePe Limited | I3: Receipt | J3: 0 | K3: 165179 | L3: 165179 | M3: 581570 | N3: High Transaction; Recurring Transaction | O3: Yes | P3: PHONEPE LIMITED | Q3: 0 | R3: 1 | S3: 0 | T3: 0 | U3: 1 | V3: 0 | W3: 0 | X3: 0 | Y3: 0 | Z3: 0 | AA3: 46114
A4: 3 | B4: 502 input.pdf | C4: 46113 | D4: 46142 | E4: 46114 | F4: 46114 | G4: UPI/6091426275 42627513 UPI/609142627513/04:54:21/UPI/dineshjogle086-5@ok | I4: Payment | J4: 2356 | K4: 0 | L4: 2356 | M4: 579214 | N4: UPI | O4: No | P4: DINESHJOGLE | Q4: 0 | R4: 0 | S4: 0 | T4: 0 | U4: 0 | V4: 1 | W4: 0 | X4: 0 | Y4: 0 | Z4: 0 | AA4: 46114
A5: 4 | B5: 502 input.pdf | C5: 46113 | D5: 46142 | E5: 46114 | F5: 46114 | G5: DIGITA-MUMBAI/ IMPS/P2A/609149979773/ONEMOBIKWIKSYST/IMPSAXB9100 | I5: Receipt | J5: 0 | K5: 35167.6 | L5: 35167.6 | M5: 614381.6 | N5: Other | O5: No | P5: ONEMOBIKWIKSYST | Q5: 0 | R5: 0 | S5: 0 | T5: 0 | U5: 0 | V5: 0 | W5: 0 | X5: 0 | Y5: 0 | Z5: 0 | AA5: 46114
A6: 5 | B6: 502 input.pdf | C6: 46113 | D6: 46142 | E6: 46114 | F6: 46114 | G6: UPI/6091243743 24374374 UPI/609124374374/11:47:28/UPI/prasadconstruction2 | I6: Receipt | J6: 0 | K6: 70000 | L6: 70000 | M6: 684381.6 | N6: UPI | O6: No | P6: PRASADCONSTRUCTION | Q6: 0 | R6: 0 | S6: 0 | T6: 0 | U6: 0 | V6: 1 | W6: 0 | X6: 0 | Y6: 0 | Z6: 0 | AA6: 46114
A7: 6 | B7: 502 input.pdf | C7: 46113 | D7: 46142 | E7: 46114 | F7: 46114 | G7: EBANK:WIB/1502 EBANK:WIB/1502021829/Edfs | I7: Payment | J7: 681881.6 | K7: 0 | L7: 681881.6 | M7: 2500 | N7: High Transaction; Recurring Transaction | O7: Yes | P7: EBANKWIB | Q7: 0 | R7: 1 | S7: 0 | T7: 0 | U7: 1 | V7: 0 | W7: 0 | X7: 0 | Y7: 0 | Z7: 0 | AA7: 46114
A8: 7 | B8: 502 input.pdf | C8: 46113 | D8: 46142 | E8: 46114 | F8: 46114 | G8: DIGITA-MUMBAI/ NEFT-FBPT260916108327-PREMIER CONVEYORS PRIVATE LI | I8: Receipt | J8: 0 | K8: 18409 | L8: 18409 | M8: 20909 | N8: EMI; Recurring Transaction | O8: Yes | P8: PREMIER CONVEYORS PRIVATE LI | Q8: 0 | R8: 1 | S8: 1 | T8: 0 | U8: 0 | V8: 0 | W8: 0 | X8: 0 | Y8: 0 | Z8: 0 | AA8: 46114
A9: 8 | B9: 502 input.pdf | C9: 46113 | D9: 46142 | E9: 46114 | F9: 46114 | G9: DIGITA-MUMBAI/ NEFT-CNRBH00121803213-QUALITY PLAST INDUSTRIES LIM | I9: Receipt | J9: 0 | K9: 121431 | L9: 121431 | M9: 142340 | N9: High Transaction; Recurring Transaction | O9: Yes | P9: QUALITY PLAST INDUSTRIES LIM | Q9: 0 | R9: 1 | S9: 0 | T9: 0 | U9: 1 | V9: 0 | W9: 0 | X9: 0 | Y9: 0 | Z9: 0 | AA9: 46114
A10: 9 | B10: 502 input.pdf | C10: 46113 | D10: 46142 | E10: 46114 | F10: 46114 | G10: UPI/6091779614 77961475 UPI/609177961475/16:34:33/UPI/q297956037@ybl/food | I10: Payment | J10: 1500 | K10: 0 | L10: 1500 | M10: 140840 | N10: UPI | O10: No | P10: UPI/# # UPI/#/#:#:#/UPI/Q#@YBL/FOOD | Q10: 0 | R10: 0 | S10: 0 | T10: 0 | U10: 0 | V10: 1 | W10: 0 | X10: 0 | Y10: 0 | Z10: 0 | AA10: 46114
A11: 10 | B11: 502 input.pdf | C11: 46113 | D11: 46142 | E11: 46114 | F11: 46114 | G11: DIGITA-MUMBAI/ IMPS/P2A/609116466512/AFZALSIRAJUDDIN/IMPSUOB9191 | I11: Receipt | J11: 0 | K11: 100000 | L11: 100000 | M11: 240840 | N11: High Transaction; Recurring Transaction | O11: Yes | P11: AFZALSIRAJUDDIN | Q11: 0 | R11: 1 | S11: 0 | T11: 0 | U11: 1 | V11: 0 | W11: 0 | X11: 0 | Y11: 0 | Z11: 0 | AA11: 46114
A12: 11 | B12: 502 input.pdf | C12: 46113 | D12: 46142 | E12: 46114 | F12: 46114 | G12: DIGITA-MUMBAI/ NEFT-KKBKH26091970510-VENKTESHWAR INDUSTRIAL CORPO | I12: Receipt | J12: 0 | K12: 10000 | L12: 10000 | M12: 250840 | N12: Recurring Transaction | O12: Yes | P12: VENKTESHWAR INDUSTRIAL CORPO | Q12: 0 | R12: 1 | S12: 0 | T12: 0 | U12: 0 | V12: 0 | W12: 0 | X12: 0 | Y12: 0 | Z12: 0 | AA12: 46114
A13: 12 | B13: 502 input.pdf | C13: 46113 | D13: 46142 | E13: 46114 | F13: 46114 | G13: EBANK:WIB/1502 ---------------------------------------------------------------------------------------------------------------------------------- Page Total: 9,34,077.60 5,73,386.60 2,500.00Cr ---------------------------------------------------------------------------------------------------------------------------------- Note: Cheques received in inward clearing will be considered for debiting/ returning on the basis opening balance in account Unless the constituent notifies the bank of any dis | I13: Payment | J13: 248340 | K13: 0 | L13: 248340 | M13: 2500 | N13: High Transaction; Recurring Transaction | O13: Yes | P13: EBANKWIB | Q13: 0 | R13: 1 | S13: 0 | T13: 0 | U13: 1 | V13: 0 | W13: 0 | X13: 0 | Y13: 0 | Z13: 0 | AA13: 46114
... A399: 398 | B399: 502 input.pdf | C399: 46113 | D399: 46142 | E399: 46142 | F399: 46142 | G399: EBANK:WIB/1506 EBANK:WIB/1506303993/Edfs ---------------------------------------------------------------------------------------------------------------------------------- Page Total: 4,73,075.05 2,64,697.00 2,500.00Cr ---------------------------------------------------------------------------------------------------------------------------------- Grand Total: 1,81,29,258.19 1,77,68,567.19 2,500.00Cr* ----------------------------------------------------------------------------------------------- | I399: Payment | J399: 128623.2 | K399: 0 | L399: 128623.2 | M399: 2500 | N399: High Transaction; Recurring Transaction | O399: Yes | P399: EBANKWIB | Q399: 0 | R399: 1 | S399: 0 | T399: 0 | U399: 1 | V399: 0 | W399: 0 | X399: 0 | Y399: 0 | Z399: 0 | AA399: 46142

Sheet Detail Total
A1: =HYPERLINK("#'Dashboard'!A1", "← Return to Dashboard") | B1: Total Transactions
A2: Rows | B2: 398 | C2: Match | D2: All transactions
A4: Seq | B4: Source File | C4: Statement From | D4: Statement To | E4: Date | F4: Value Date | G4: Narration | H4: Reference | I4: Direction | J4: Withdrawal | K4: Deposit | L4: Amount | M4: Closing Balance | N4: Categories | O4: Recurring? | P4: Recurring Key | Q4: Flag - Cash | R4: Flag - Recurring Transaction | S4: Flag - EMI | T4: Flag - Salary | U4: Flag - High Transaction | V4: Flag - UPI | W4: Flag - LIC | X4: Flag - FD interest | Y4: Flag - FD Deposit and withdrawals | Z4: Flag - PPF/PF interest and contribution | AA4: Month Date | AB4: View Source Row
A5: 1 | B5: 502 input.pdf | C5: 46113 | D5: 46142 | E5: 46114 | F5: 46114 | G5: DIGITA-MUMBAI/ IMPS/P2A/609147096215/HONEPELIMITEDPA/F09Hpcljige | I5: Receipt | J5: 0 | K5: 53200 | L5: 53200 | M5: 416391 | N5: Other | O5: No | P5: HONEPELIMITEDPA | Q5: 0 | R5: 0 | S5: 0 | T5: 0 | U5: 0 | V5: 0 | W5: 0 | X5: 0 | Y5: 0 | Z5: 0 | AA5: 46114 | AB5: =HYPERLINK("#'Transactions'!A2", "View Source Row")
A6: 2 | B6: 502 input.pdf | C6: 46113 | D6: 46142 | E6: 46114 | F6: 46114 | G6: DIGITA-MUMBAI/ NEFT-YESAP60912594024-PhonePe Limited | I6: Receipt | J6: 0 | K6: 165179 | L6: 165179 | M6: 581570 | N6: High Transaction; Recurring Transaction | O6: Yes | P6: PHONEPE LIMITED | Q6: 0 | R6: 1 | S6: 0 | T6: 0 | U6: 1 | V6: 0 | W6: 0 | X6: 0 | Y6: 0 | Z6: 0 | AA6: 46114 | AB6: =HYPERLINK("#'Transactions'!A3", "View Source Row")
A7: 3 | B7: 502 input.pdf | C7: 46113 | D7: 46142 | E7: 46114 | F7: 46114 | G7: UPI/6091426275 42627513 UPI/609142627513/04:54:21/UPI/dineshjogle086-5@ok | I7: Payment | J7: 2356 | K7: 0 | L7: 2356 | M7: 579214 | N7: UPI | O7: No | P7: DINESHJOGLE | Q7: 0 | R7: 0 | S7: 0 | T7: 0 | U7: 0 | V7: 1 | W7: 0 | X7: 0 | Y7: 0 | Z7: 0 | AA7: 46114 | AB7: =HYPERLINK("#'Transactions'!A4", "View Source Row")
A8: 4 | B8: 502 input.pdf | C8: 46113 | D8: 46142 | E8: 46114 | F8: 46114 | G8: DIGITA-MUMBAI/ IMPS/P2A/609149979773/ONEMOBIKWIKSYST/IMPSAXB9100 | I8: Receipt | J8: 0 | K8: 35167.6 | L8: 35167.6 | M8: 614381.6 | N8: Other | O8: No | P8: ONEMOBIKWIKSYST | Q8: 0 | R8: 0 | S8: 0 | T8: 0 | U8: 0 | V8: 0 | W8: 0 | X8: 0 | Y8: 0 | Z8: 0 | AA8: 46114 | AB8: =HYPERLINK("#'Transactions'!A5", "View Source Row")
A9: 5 | B9: 502 input.pdf | C9: 46113 | D9: 46142 | E9: 46114 | F9: 46114 | G9: UPI/6091243743 24374374 UPI/609124374374/11:47:28/UPI/prasadconstruction2 | I9: Receipt | J9: 0 | K9: 70000 | L9: 70000 | M9: 684381.6 | N9: UPI | O9: No | P9: PRASADCONSTRUCTION | Q9: 0 | R9: 0 | S9: 0 | T9: 0 | U9: 0 | V9: 1 | W9: 0 | X9: 0 | Y9: 0 | Z9: 0 | AA9: 46114 | AB9: =HYPERLINK("#'Transactions'!A6", "View Source Row")
A10: 6 | B10: 502 input.pdf | C10: 46113 | D10: 46142 | E10: 46114 | F10: 46114 | G10: EBANK:WIB/1502 EBANK:WIB/1502021829/Edfs | I10: Payment | J10: 681881.6 | K10: 0 | L10: 681881.6 | M10: 2500 | N10: High Transaction; Recurring Transaction | O10: Yes | P10: EBANKWIB | Q10: 0 | R10: 1 | S10: 0 | T10: 0 | U10: 1 | V10: 0 | W10: 0 | X10: 0 | Y10: 0 | Z10: 0 | AA10: 46114 | AB10: =HYPERLINK("#'Transactions'!A7", "View Source Row")
A11: 7 | B11: 502 input.pdf | C11: 46113 | D11: 46142 | E11: 46114 | F11: 46114 | G11: DIGITA-MUMBAI/ NEFT-FBPT260916108327-PREMIER CONVEYORS PRIVATE LI | I11: Receipt | J11: 0 | K11: 18409 | L11: 18409 | M11: 20909 | N11: EMI; Recurring Transaction | O11: Yes | P11: PREMIER CONVEYORS PRIVATE LI | Q11: 0 | R11: 1 | S11: 1 | T11: 0 | U11: 0 | V11: 0 | W11: 0 | X11: 0 | Y11: 0 | Z11: 0 | AA11: 46114 | AB11: =HYPERLINK("#'Transactions'!A8", "View Source Row")
A12: 8 | B12: 502 input.pdf | C12: 46113 | D12: 46142 | E12: 46114 | F12: 46114 | G12: DIGITA-MUMBAI/ NEFT-CNRBH00121803213-QUALITY PLAST INDUSTRIES LIM | I12: Receipt | J12: 0 | K12: 121431 | L12: 121431 | M12: 142340 | N12: High Transaction; Recurring Transaction | O12: Yes | P12: QUALITY PLAST INDUSTRIES LIM | Q12: 0 | R12: 1 | S12: 0 | T12: 0 | U12: 1 | V12: 0 | W12: 0 | X12: 0 | Y12: 0 | Z12: 0 | AA12: 46114 | AB12: =HYPERLINK("#'Transactions'!A9", "View Source Row")
A13: 9 | B13: 502 input.pdf | C13: 46113 | D13: 46142 | E13: 46114 | F13: 46114 | G13: UPI/6091779614 77961475 UPI/609177961475/16:34:33/UPI/q297956037@ybl/food | I13: Payment | J13: 1500 | K13: 0 | L13: 1500 | M13: 140840 | N13: UPI | O13: No | P13: UPI/# # UPI/#/#:#:#/UPI/Q#@YBL/FOOD | Q13: 0 | R13: 0 | S13: 0 | T13: 0 | U13: 0 | V13: 1 | W13: 0 | X13: 0 | Y13: 0 | Z13: 0 | AA13: 46114 | AB13: =HYPERLINK("#'Transactions'!A10", "View Source Row")
A14: 10 | B14: 502 input.pdf | C14: 46113 | D14: 46142 | E14: 46114 | F14: 46114 | G14: DIGITA-MUMBAI/ IMPS/P2A/609116466512/AFZALSIRAJUDDIN/IMPSUOB9191 | I14: Receipt | J14: 0 | K14: 100000 | L14: 100000 | M14: 240840 | N14: High Transaction; Recurring Transaction | O14: Yes | P14: AFZALSIRAJUDDIN | Q14: 0 | R14: 1 | S14: 0 | T14: 0 | U14: 1 | V14: 0 | W14: 0 | X14: 0 | Y14: 0 | Z14: 0 | AA14: 46114 | AB14: =HYPERLINK("#'Transactions'!A11", "View Source Row")
A15: 11 | B15: 502 input.pdf | C15: 46113 | D15: 46142 | E15: 46114 | F15: 46114 | G15: DIGITA-MUMBAI/ NEFT-KKBKH26091970510-VENKTESHWAR INDUSTRIAL CORPO | I15: Receipt | J15: 0 | K15: 10000 | L15: 10000 | M15: 250840 | N15: Recurring Transaction | O15: Yes | P15: VENKTESHWAR INDUSTRIAL CORPO | Q15: 0 | R15: 1 | S15: 0 | T15: 0 | U15: 0 | V15: 0 | W15: 0 | X15: 0 | Y15: 0 | Z15: 0 | AA15: 46114 | AB15: =HYPERLINK("#'Transactions'!A12", "View Source Row")
A16: 12 | B16: 502 input.pdf | C16: 46113 | D16: 46142 | E16: 46114 | F16: 46114 | G16: EBANK:WIB/1502 ---------------------------------------------------------------------------------------------------------------------------------- Page Total: 9,34,077.60 5,73,386.60 2,500.00Cr ---------------------------------------------------------------------------------------------------------------------------------- Note: Cheques received in inward clearing will be considered for debiting/ returning on the basis opening balance in account Unless the constituent notifies the bank of any dis | I16: Payment | J16: 248340 | K16: 0 | L16: 248340 | M16: 2500 | N16: High Transaction; Recurring Transaction | O16: Yes | P16: EBANKWIB | Q16: 0 | R16: 1 | S16: 0 | T16: 0 | U16: 1 | V16: 0 | W16: 0 | X16: 0 | Y16: 0 | Z16: 0 | AA16: 46114 | AB16: =HYPERLINK("#'Transactions'!A13", "View Source Row")
A17: 13 | B17: 502 input.pdf | C17: 46113 | D17: 46142 | E17: 46114 | F17: 46114 | G17: DIGITA-MUMBAI/ NEFT-YESAP60924833309-PhonePe Limited | I17: Receipt | J17: 0 | K17: 188588.4 | L17: 188588.4 | M17: 191088.4 | N17: High Transaction; Recurring Transaction | O17: Yes | P17: PHONEPE LIMITED | Q17: 0 | R17: 1 | S17: 0 | T17: 0 | U17: 1 | V17: 0 | W17: 0 | X17: 0 | Y17: 0 | Z17: 0 | AA17: 46114 | AB17: =HYPERLINK("#'Transactions'!A14", "View Source Row")
A18: 14 | B18: 502 input.pdf | C18: 46113 | D18: 46142 | E18: 46114 | F18: 46114 | G18: DIGITA-MUMBAI/ NEFT-AXNPN09202196281-PHONEPE LIMITED-PAYMENT AGGR | I18: Receipt | J18: 0 | K18: 50884.1 | L18: 50884.1 | M18: 241972.5 | N18: Recurring Transaction | O18: Yes | P18: PHONEPE LIMITED | Q18: 0 | R18: 1 | S18: 0 | T18: 0 | U18: 0 | V18: 0 | W18: 0 | X18: 0 | Y18: 0 | Z18: 0 | AA18: 46114 | AB18: =HYPERLINK("#'Transactions'!A15", "View Source Row")
A19: 15 | B19: 502 input.pdf | C19: 46113 | D19: 46142 | E19: 46114 | F19: 46114 | G19: DIGITA-MUMBAI/ NEFT-AXISCN1298773772-ONE MOBIKWIK SYSTEMS LIMITED https://cbdrpt101.bankofbaroda.co.in:22000/finbranch/arjspmorph/INFENG/tran_rpt.jsp?... 04-05-2026 | I19: Receipt | J19: 0 | K19: 26312 | L19: 26312 | M19: 268284.5 | N19: Recurring Transaction | O19: Yes | P19: ONE MOBIKWIK SYSTEMS LIMITED HTTPS | Q19: 0 | R19: 1 | S19: 0 | T19: 0 | U19: 0 | V19: 0 | W19: 0 | X19: 0 | Y19: 0 | Z19: 0 | AA19: 46114 | AB19: =HYPERLINK("#'Transactions'!A16", "View Source Row")
A20: 16 | B20: 502 input.pdf | C20: 46113 | D20: 46142 | E20: 46114 | F20: 46114 | G20: DIGITA-MUMBAI/ IMPS/P2A/609208556385/OMSANITRANSPORT/IMPSUOB9195 | I20: Receipt | J20: 0 | K20: 16450 | L20: 16450 | M20: 284734.5 | N20: Recurring Transaction | O20: Yes | P20: OMSANITRANSPORT | Q20: 0 | R20: 1 | S20: 0 | T20: 0 | U20: 0 | V20: 0 | W20: 0 | X20: 0 | Y20: 0 | Z20: 0 | AA20: 46114 | AB20: =HYPERLINK("#'Transactions'!A17", "View Source Row")
A21: 17 | B21: 502 input.pdf | C21: 46113 | D21: 46142 | E21: 46114 | F21: 46114 | G21: DIGITA-MUMBAI/ NEFT-AXISCN1298906804-PINE LABS PRIVATE LIMITED-NO | I21: Receipt | J21: 0 | K21: 61903 | L21: 61903 | M21: 346637.5 | N21: Recurring Transaction | O21: Yes | P21: PINE LABS PRIVATE LIMITED | Q21: 0 | R21: 1 | S21: 0 | T21: 0 | U21: 0 | V21: 0 | W21: 0 | X21: 0 | Y21: 0 | Z21: 0 | AA21: 46114 | AB21: =HYPERLINK("#'Transactions'!A18", "View Source Row")
A22: 18 | B22: 502 input.pdf | C22: 46113 | D22: 46142 | E22: 46114 | F22: 46114 | G22: DIGITA-MUMBAI/ NEFT-AXISCN1299028324-PINE LABS PRIVATE LIMITED-NO | I22: Receipt | J22: 0 | K22: 166884 | L22: 166884 | M22: 513521.5 | N22: High Transaction; Recurring Transaction | O22: Yes | P22: PINE LABS PRIVATE LIMITED | Q22: 0 | R22: 1 | S22: 0 | T22: 0 | U22: 1 | V22: 0 | W22: 0 | X22: 0 | Y22: 0 | Z22: 0 | AA22: 46114 | AB22: =HYPERLINK("#'Transactions'!A19", "View Source Row")
A23: 19 | B23: 502 input.pdf | C23: 46113 | D23: 46142 | E23: 46114 | F23: 46114 | G23: UPI/6092378308 37830859 UPI/609237830859/11:20:36/UPI/9850754712-3@ybl/st | I23: Payment | J23: 4000 | K23: 0 | L23: 4000 | M23: 509521.5 | N23: UPI | O23: No | P23: UPI/# # UPI/#/#:#:#/UPI/#-#@YBL/ST | Q23: 0 | R23: 0 | S23: 0 | T23: 0 | U23: 0 | V23: 1 | W23: 0 | X23: 0 | Y23: 0 | Z23: 0 | AA23: 46114 | AB23: =HYPERLINK("#'Transactions'!A20", "View Source Row")
A24: 20 | B24: 502 input.pdf | C24: 46113 | D24: 46142 | E24: 46114 | F24: 46114 | G24: DIGITA-MUMBAI/ IMPS/P2A/609211135154/SHREE GANESH EN/dieselVVS91 | I24: Receipt | J24: 0 | K24: 63308 | L24: 63308 | M24: 572829.5 | N24: Recurring Transaction | O24: Yes | P24: SHREE GANESH EN | Q24: 0 | R24: 1 | S24: 0 | T24: 0 | U24: 0 | V24: 0 | W24: 0 | X24: 0 | Y24: 0 | Z24: 0 | AA24: 46114 | AB24: =HYPERLINK("#'Transactions'!A21", "View Source Row")
A25: 21 | B25: 502 input.pdf | C25: 46113 | D25: 46142 | E25: 46114 | F25: 46114 | G25: DIGITA-MUMBAI/ NEFT-KKBKH26092777992-VENKTESHWAR INDUSTRIAL CORPO | I25: Receipt | J25: 0 | K25: 18088 | L25: 18088 | M25: 590917.5 | N25: Recurring Transaction | O25: Yes | P25: VENKTESHWAR INDUSTRIAL CORPO | Q25: 0 | R25: 1 | S25: 0 | T25: 0 | U25: 0 | V25: 0 | W25: 0 | X25: 0 | Y25: 0 | Z25: 0 | AA25: 46114 | AB25: =HYPERLINK("#'Transactions'!A22", "View Source Row")
A26: 22 | B26: 502 input.pdf | C26: 46113 | D26: 46142 | E26: 46114 | F26: 46114 | G26: UPI/6092013389 1338963 UPI/609201338963/12:38:06/UPI/gpay-11193876450@ok | I26: Payment | J26: 2800 | K26: 0 | L26: 2800 | M26: 588117.5 | N26: UPI | O26: No | P26: UPI/# # UPI/#/#:#:#/UPI/GPAY-#@OK | Q26: 0 | R26: 0 | S26: 0 | T26: 0 | U26: 0 | V26: 1 | W26: 0 | X26: 0 | Y26: 0 | Z26: 0 | AA26: 46114 | AB26: =HYPERLINK("#'Transactions'!A23", "View Source Row")
A27: 23 | B27: 502 input.pdf | C27: 46113 | D27: 46142 | E27: 46114 | F27: 46114 | G27: DIGITA-MUMBAI/ NEFT-NKGSH26092846591-GEBI PRODUCTS PRIVATE LIMITE | I27: Receipt | J27: 0 | K27: 12813 | L27: 12813 | M27: 600930.5 | N27: Recurring Transaction | O27: Yes | P27: GEBI PRODUCTS PRIVATE LIMITE | Q27: 0 | R27: 1 | S27: 0 | T27: 0 | U27: 0 | V27: 0 | W27: 0 | X27: 0 | Y27: 0 | Z27: 0 | AA27: 46114 | AB27: =HYPERLINK("#'Transactions'!A24", "View Source Row")
A28: 24 | B28: 502 input.pdf | C28: 46113 | D28: 46142 | E28: 46114 | F28: 46114 | G28: DIGITA-MUMBAI/ NEFT-IDIBH09236262399-JAI AMBE TRANSPORT | I28: Receipt | J28: 0 | K28: 4378 | L28: 4378 | M28: 605308.5 | N28: Recurring Transaction | O28: Yes | P28: JAI AMBE TRANSPORT | Q28: 0 | R28: 1 | S28: 0 | T28: 0 | U28: 0 | V28: 0 | W28: 0 | X28: 0 | Y28: 0 | Z28: 0 | AA28: 46114 | AB28: =HYPERLINK("#'Transactions'!A25", "View Source Row")
A29: 25 | B29: 502 input.pdf | C29: 46113 | D29: 46142 | E29: 46114 | F29: 46114 | G29: DIGITA-MUMBAI/ NEFT-HDFCH00905140576-Adekar enterprises pvt ltd | I29: Receipt | J29: 0 | K29: 138674 | L29: 138674 | M29: 743982.5 | N29: High Transaction; Recurring Transaction | O29: Yes | P29: ADEKAR ENTERPRISES PVT LTD | Q29: 0 | R29: 1 | S29: 0 | T29: 0 | U29: 1 | V29: 0 | W29: 0 | X29: 0 | Y29: 0 | Z29: 0 | AA29: 46114 | AB29: =HYPERLINK("#'Transactions'!A26", "View Source Row")
A30: 26 | B30: 502 input.pdf | C30: 46113 | D30: 46142 | E30: 46114 | F30: 46114 | G30: DIGITA-MUMBAI/ NEFT-TDCBH26092001785-V C ENTERPRISES | I30: Receipt | J30: 0 | K30: 50000 | L30: 50000 | M30: 793982.5 | N30: Recurring Transaction | O30: Yes | P30: V C ENTERPRISES | Q30: 0 | R30: 1 | S30: 0 | T30: 0 | U30: 0 | V30: 0 | W30: 0 | X30: 0 | Y30: 0 | Z30: 0 | AA30: 46114 | AB30: =HYPERLINK("#'Transactions'!A27", "View Source Row")
A31: 27 | B31: 502 input.pdf | C31: 46113 | D31: 46142 | E31: 46114 | F31: 46114 | G31: EBANK:WIB/1502 EBANK:WIB/1502234210/Edfs | I31: Payment | J31: 791482.5 | K31: 0 | L31: 791482.5 | M31: 2500 | N31: High Transaction; Recurring Transaction | O31: Yes | P31: EBANKWIB | Q31: 0 | R31: 1 | S31: 0 | T31: 0 | U31: 1 | V31: 0 | W31: 0 | X31: 0 | Y31: 0 | Z31: 0 | AA31: 46114 | AB31: =HYPERLINK("#'Transactions'!A28", "View Source Row")
A32: 28 | B32: 502 input.pdf | C32: 46113 | D32: 46142 | E32: 46114 | F32: 46114 | G32: DIGITA-MUMBAI/ ---------------------------------------------------------------------------------------------------------------------------------- Page Total: 7,98,282.50 8,34,458.50 38,676.00Cr ---------------------------------------------------------------------------------------------------------------------------------- Note: Cheques received in inward clearing will be considered for debiting/ returning on the basis opening balance in account Unless the constituent notifies the bank of any di | I32: Receipt | J32: 0 | K32: 36176 | L32: 36176 | M32: 38676 | N32: Recurring Transaction | O32: Yes | P32: PAGE TOTAL CR | Q32: 0 | R32: 1 | S32: 0 | T32: 0 | U32: 0 | V32: 0 | W32: 0 | X32: 0 | Y32: 0 | Z32: 0 | AA32: 46114 | AB32: =HYPERLINK("#'Transactions'!A29", "View Source Row")
A33: 29 | B33: 502 input.pdf | C33: 46113 | D33: 46142 | E33: 46114 | F33: 46114 | G33: DIGITA-MUMBAI/ NEFT-KKBKH26092921670-ATLAS COMMODITIES PRIVATE LI | I33: Receipt | J33: 0 | K33: 4353 | L33: 4353 | M33: 43029 | N33: Recurring Transaction | O33: Yes | P33: ATLAS COMMODITIES PRIVATE LI | Q33: 0 | R33: 1 | S33: 0 | T33: 0 | U33: 0 | V33: 0 | W33: 0 | X33: 0 | Y33: 0 | Z33: 0 | AA33: 46114 | AB33: =HYPERLINK("#'Transactions'!A30", "View Source Row")
A34: 30 | B34: 502 input.pdf | C34: 46113 | D34: 46142 | E34: 46115 | F34: 46115 | G34: DIGITA-MUMBAI/ NEFT-YESAP60934071902-PhonePe Limited | I34: Receipt | J34: 0 | K34: 173393.9 | L34: 173393.9 | M34: 216422.9 | N34: High Transaction; Recurring Transaction | O34: Yes | P34: PHONEPE LIMITED | Q34: 0 | R34: 1 | S34: 0 | T34: 0 | U34: 1 | V34: 0 | W34: 0 | X34: 0 | Y34: 0 | Z34: 0 | AA34: 46115 | AB34: =HYPERLINK("#'Transactions'!A31", "View Source Row")
A35: 31 | B35: 502 input.pdf | C35: 46113 | D35: 46142 | E35: 46115 | F35: 46115 | G35: DIGITA-MUMBAI/ NEFT-AXNPN09311160907-PHONEPE LIMITED-PAYMENT AGGR | I35: Receipt | J35: 0 | K35: 53957.68 | L35: 53957.68 | M35: 270380.58 | N35: Recurring Transaction | O35: Yes | P35: PHONEPE LIMITED | Q35: 0 | R35: 1 | S35: 0 | T35: 0 | U35: 0 | V35: 0 | W35: 0 | X35: 0 | Y35: 0 | Z35: 0 | AA35: 46115 | AB35: =HYPERLINK("#'Transactions'!A32", "View Source Row")
A36: 32 | B36: 502 input.pdf | C36: 46113 | D36: 46142 | E36: 46115 | F36: 46115 | G36: DIGITA-MUMBAI/ NEFT-AXISCN1300289999-ONE MOBIKWIK SYSTEMS LIMITED | I36: Receipt | J36: 0 | K36: 21700 | L36: 21700 | M36: 292080.58 | N36: Recurring Transaction | O36: Yes | P36: ONE MOBIKWIK SYSTEMS LIMITED | Q36: 0 | R36: 1 | S36: 0 | T36: 0 | U36: 0 | V36: 0 | W36: 0 | X36: 0 | Y36: 0 | Z36: 0 | AA36: 46115 | AB36: =HYPERLINK("#'Transactions'!A33", "View Source Row")
A37: 33 | B37: 502 input.pdf | C37: 46113 | D37: 46142 | E37: 46115 | F37: 46115 | G37: DIGITA-MUMBAI/ IMPS/P2A/609308206742/S TRANS 14851/Mh04ju3738I | I37: Receipt | J37: 0 | K37: 5750 | L37: 5750 | M37: 297830.58 | N37: Recurring Transaction | O37: Yes | P37: DIGITA-MUMBAI/ IMPS/P#A/#/S TRANS #/MH#JU#I | Q37: 0 | R37: 1 | S37: 0 | T37: 0 | U37: 0 | V37: 0 | W37: 0 | X37: 0 | Y37: 0 | Z37: 0 | AA37: 46115 | AB37: =HYPERLINK("#'Transactions'!A34", "View Source Row")
A38: 34 | B38: 502 input.pdf | C38: 46113 | D38: 46142 | E38: 46115 | F38: 46115 | G38: DIGITA-MUMBAI/ NEFT-AXISCN1300388689-PINE LABS PRIVATE LIMITED-NO | I38: Receipt | J38: 0 | K38: 112894 | L38: 112894 | M38: 410724.58 | N38: High Transaction; Recurring Transaction | O38: Yes | P38: PINE LABS PRIVATE LIMITED | Q38: 0 | R38: 1 | S38: 0 | T38: 0 | U38: 1 | V38: 0 | W38: 0 | X38: 0 | Y38: 0 | Z38: 0 | AA38: 46115 | AB38: =HYPERLINK("#'Transactions'!A35", "View Source Row")
A39: 35 | B39: 502 input.pdf | C39: 46113 | D39: 46142 | E39: 46115 | F39: 46115 | G39: DIGITA-MUMBAI/ IMPS/P2A/609312855509/AFZALSIRAJUDDIN/IMPSUOB9191 | I39: Receipt | J39: 0 | K39: 200000 | L39: 200000 | M39: 610724.58 | N39: High Transaction; Recurring Transaction | O39: Yes | P39: AFZALSIRAJUDDIN | Q39: 0 | R39: 1 | S39: 0 | T39: 0 | U39: 1 | V39: 0 | W39: 0 | X39: 0 | Y39: 0 | Z39: 0 | AA39: 46115 | AB39: =HYPERLINK("#'Transactions'!A36", "View Source Row")
A40: 36 | B40: 502 input.pdf | C40: 46113 | D40: 46142 | E40: 46115 | F40: 46115 | G40: DIGITA-MUMBAI/ NEFT-002663976089-GANGAMAI INDUSTRIES AND CONSTR | I40: Receipt | J40: 0 | K40: 180880 | L40: 180880 | M40: 791604.58 | N40: High Transaction | O40: No | P40: GANGAMAI INDUSTRIES AND CONSTR | Q40: 0 | R40: 0 | S40: 0 | T40: 0 | U40: 1 | V40: 0 | W40: 0 | X40: 0 | Y40: 0 | Z40: 0 | AA40: 46115 | AB40: =HYPERLINK("#'Transactions'!A37", "View Source Row")
A41: 37 | B41: 502 input.pdf | C41: 46113 | D41: 46142 | E41: 46115 | F41: 46115 | G41: EBANK:WIB/1502 EBANK:WIB/1502413595/Edfs | I41: Payment | J41: 790104.58 | K41: 0 | L41: 790104.58 | M41: 1500 | N41: High Transaction; Recurring Transaction | O41: Yes | P41: EBANKWIB | Q41: 0 | R41: 1 | S41: 0 | T41: 0 | U41: 1 | V41: 0 | W41: 0 | X41: 0 | Y41: 0 | Z41: 0 | AA41: 46115 | AB41: =HYPERLINK("#'Transactions'!A38", "View Source Row")
A42: 38 | B42: 502 input.pdf | C42: 46113 | D42: 46142 | E42: 46116 | F42: 46116 | G42: DIGITA-MUMBAI/ NEFT-YESAP60944128518-PhonePe Limited | I42: Receipt | J42: 0 | K42: 171014 | L42: 171014 | M42: 172514 | N42: High Transaction; Recurring Transaction | O42: Yes | P42: PHONEPE LIMITED | Q42: 0 | R42: 1 | S42: 0 | T42: 0 | U42: 1 | V42: 0 | W42: 0 | X42: 0 | Y42: 0 | Z42: 0 | AA42: 46116 | AB42: =HYPERLINK("#'Transactions'!A39", "View Source Row")
A43: 39 | B43: 502 input.pdf | C43: 46113 | D43: 46142 | E43: 46116 | F43: 46116 | G43: DIGITA-MUMBAI/ https://cbdrpt101.bankofbaroda.co.in:22000/finbranch/arjspmorph/INFENG/tran_rpt.jsp?... 04-05-2026 NEFT-AXNPN09418938602-PHONEPE LIMITED-PAYMENT AGGR | I43: Receipt | J43: 0 | K43: 49956 | L43: 49956 | M43: 222470 | N43: Recurring Transaction | O43: Yes | P43: CBDRPTBANKOFBARODACOIN | Q43: 0 | R43: 1 | S43: 0 | T43: 0 | U43: 0 | V43: 0 | W43: 0 | X43: 0 | Y43: 0 | Z43: 0 | AA43: 46116 | AB43: =HYPERLINK("#'Transactions'!A40", "View Source Row")
A44: 40 | B44: 502 input.pdf | C44: 46113 | D44: 46142 | E44: 46116 | F44: 46116 | G44: DIGITA-MUMBAI/ NEFT-AXISCN1301100257-ONE MOBIKWIK SYSTEMS LIMITED | I44: Receipt | J44: 0 | K44: 22121 | L44: 22121 | M44: 244591 | N44: Recurring Transaction | O44: Yes | P44: ONE MOBIKWIK SYSTEMS LIMITED | Q44: 0 | R44: 1 | S44: 0 | T44: 0 | U44: 0 | V44: 0 | W44: 0 | X44: 0 | Y44: 0 | Z44: 0 | AA44: 46116 | AB44: =HYPERLINK("#'Transactions'!A41", "View Source Row")
A45: 41 | B45: 502 input.pdf | C45: 46113 | D45: 46142 | E45: 46116 | F45: 46116 | G45: EBANK:WIB/1502 EBANK:WIB/1502423934/Edfs | I45: Payment | J45: 240091 | K45: 0 | L45: 240091 | M45: 4500 | N45: High Transaction; Recurring Transaction | O45: Yes | P45: EBANKWIB | Q45: 0 | R45: 1 | S45: 0 | T45: 0 | U45: 1 | V45: 0 | W45: 0 | X45: 0 | Y45: 0 | Z45: 0 | AA45: 46116 | AB45: =HYPERLINK("#'Transactions'!A42", "View Source Row")
A46: 42 | B46: 502 input.pdf | C46: 46113 | D46: 46142 | E46: 46116 | F46: 46116 | G46: DIGITA-MUMBAI/ NEFT-AXISCN1301297166-PINE LABS PRIVATE LIMITED-NO | I46: Receipt | J46: 0 | K46: 22400 | L46: 22400 | M46: 26900 | N46: Recurring Transaction | O46: Yes | P46: PINE LABS PRIVATE LIMITED | Q46: 0 | R46: 1 | S46: 0 | T46: 0 | U46: 0 | V46: 0 | W46: 0 | X46: 0 | Y46: 0 | Z46: 0 | AA46: 46116 | AB46: =HYPERLINK("#'Transactions'!A43", "View Source Row")
A47: 43 | B47: 502 input.pdf | C47: 46113 | D47: 46142 | E47: 46116 | F47: 46116 | G47: DIGITA-MUMBAI/ NEFT-HDFCH00909652553-KUNDAN QUARRY ---------------------------------------------------------------------------------------------------------------------------------- Page Total: 10,30,195.58 10,24,219.58 32,700.00Cr ---------------------------------------------------------------------------------------------------------------------------------- Note: Cheques received in inward clearing will be considered for debiting/ returning on the basis opening balance in account Unless the c | I47: Receipt | J47: 0 | K47: 5800 | L47: 5800 | M47: 32700 | N47: Recurring Transaction | O47: Yes | P47: KUNDAN QUARRY | Q47: 0 | R47: 1 | S47: 0 | T47: 0 | U47: 0 | V47: 0 | W47: 0 | X47: 0 | Y47: 0 | Z47: 0 | AA47: 46116 | AB47: =HYPERLINK("#'Transactions'!A44", "View Source Row")
A48: 44 | B48: 502 input.pdf | C48: 46113 | D48: 46142 | E48: 46116 | F48: 46116 | G48: UPI/6094661908 66190812 UPI/609466190812/12:12:08/UPI/starbazaarhyper@ybl | I48: Payment | J48: 150.63 | K48: 0 | L48: 150.63 | M48: 32549.37 | N48: UPI | O48: No | P48: STARBAZAARHYPERYBL | Q48: 0 | R48: 0 | S48: 0 | T48: 0 | U48: 0 | V48: 1 | W48: 0 | X48: 0 | Y48: 0 | Z48: 0 | AA48: 46116 | AB48: =HYPERLINK("#'Transactions'!A45", "View Source Row")
A49: 45 | B49: 502 input.pdf | C49: 46113 | D49: 46142 | E49: 46116 | F49: 46116 | G49: DIGITA-MUMBAI/ NEFT-KKBKH26094919635-ATLAS COMMODITIES PRIVATE LI | I49: Receipt | J49: 0 | K49: 7885 | L49: 7885 | M49: 40434.37 | N49: Recurring Transaction | O49: Yes | P49: ATLAS COMMODITIES PRIVATE LI | Q49: 0 | R49: 1 | S49: 0 | T49: 0 | U49: 0 | V49: 0 | W49: 0 | X49: 0 | Y49: 0 | Z49: 0 | AA49: 46116 | AB49: =HYPERLINK("#'Transactions'!A46", "View Source Row")
A50: 46 | B50: 502 input.pdf | C50: 46113 | D50: 46142 | E50: 46116 | F50: 46116 | G50: DIGITA-MUMBAI/ IMPS/P2A/609418057716/PRASAD ROADS AN/JigeeshaICI | I50: Receipt | J50: 0 | K50: 81396 | L50: 81396 | M50: 121830.37 | N50: Other | O50: No | P50: PRASAD ROADS AN | Q50: 0 | R50: 0 | S50: 0 | T50: 0 | U50: 0 | V50: 0 | W50: 0 | X50: 0 | Y50: 0 | Z50: 0 | AA50: 46116 | AB50: =HYPERLINK("#'Transactions'!A47", "View Source Row")
A51: 47 | B51: 502 input.pdf | C51: 46113 | D51: 46142 | E51: 46116 | F51: 46116 | G51: EBANK:WIB/1502 EBANK:WIB/1502545632/Edfs | I51: Payment | J51: 120330.37 | K51: 0 | L51: 120330.37 | M51: 1500 | N51: High Transaction; Recurring Transaction | O51: Yes | P51: EBANKWIB | Q51: 0 | R51: 1 | S51: 0 | T51: 0 | U51: 1 | V51: 0 | W51: 0 | X51: 0 | Y51: 0 | Z51: 0 | AA51: 46116 | AB51: =HYPERLINK("#'Transactions'!A48", "View Source Row")
A52: 48 | B52: 502 input.pdf | C52: 46113 | D52: 46142 | E52: 46116 | F52: 46116 | G52: DIGITA-MUMBAI/ NEFT-HDFCH00911243518-KAVITA ENTERPRISES | I52: Receipt | J52: 0 | K52: 81396 | L52: 81396 | M52: 82896 | N52: Recurring Transaction | O52: Yes | P52: KAVITA ENTERPRISES | Q52: 0 | R52: 1 | S52: 0 | T52: 0 | U52: 0 | V52: 0 | W52: 0 | X52: 0 | Y52: 0 | Z52: 0 | AA52: 46116 | AB52: =HYPERLINK("#'Transactions'!A49", "View Source Row")
A53: 49 | B53: 502 input.pdf | C53: 46113 | D53: 46142 | E53: 46117 | F53: 46117 | G53: DIGITA-MUMBAI/ NEFT-YESAP60953903247-PhonePe Limited | I53: Receipt | J53: 0 | K53: 167015 | L53: 167015 | M53: 249911 | N53: High Transaction; Recurring Transaction | O53: Yes | P53: PHONEPE LIMITED | Q53: 0 | R53: 1 | S53: 0 | T53: 0 | U53: 1 | V53: 0 | W53: 0 | X53: 0 | Y53: 0 | Z53: 0 | AA53: 46117 | AB53: =HYPERLINK("#'Transactions'!A50", "View Source Row")
A54: 50 | B54: 502 input.pdf | C54: 46113 | D54: 46142 | E54: 46117 | F54: 46117 | G54: DIGITA-MUMBAI/ NEFT-AXNPN09528140899-PHONEPE LIMITED-PAYMENT AGGR | I54: Receipt | J54: 0 | K54: 67868.36 | L54: 67868.36 | M54: 317779.36 | N54: Recurring Transaction | O54: Yes | P54: PHONEPE LIMITED | Q54: 0 | R54: 1 | S54: 0 | T54: 0 | U54: 0 | V54: 0 | W54: 0 | X54: 0 | Y54: 0 | Z54: 0 | AA54: 46117 | AB54: =HYPERLINK("#'Transactions'!A51", "View Source Row")
A55: 51 | B55: 502 input.pdf | C55: 46113 | D55: 46142 | E55: 46117 | F55: 46117 | G55: DIGITA-MUMBAI/ NEFT-AXISCN1301923332-ONE MOBIKWIK SYSTEMS LIMITED | I55: Receipt | J55: 0 | K55: 28124 | L55: 28124 | M55: 345903.36 | N55: Recurring Transaction | O55: Yes | P55: ONE MOBIKWIK SYSTEMS LIMITED | Q55: 0 | R55: 1 | S55: 0 | T55: 0 | U55: 0 | V55: 0 | W55: 0 | X55: 0 | Y55: 0 | Z55: 0 | AA55: 46117 | AB55: =HYPERLINK("#'Transactions'!A52", "View Source Row")
A56: 52 | B56: 502 input.pdf | C56: 46113 | D56: 46142 | E56: 46117 | F56: 46117 | G56: EBANK:WIB/1502 EBANK:WIB/1502577386/Edfs | I56: Payment | J56: 300403.36 | K56: 0 | L56: 300403.36 | M56: 45500 | N56: High Transaction; Recurring Transaction | O56: Yes | P56: EBANKWIB | Q56: 0 | R56: 1 | S56: 0 | T56: 0 | U56: 1 | V56: 0 | W56: 0 | X56: 0 | Y56: 0 | Z56: 0 | AA56: 46117 | AB56: =HYPERLINK("#'Transactions'!A53", "View Source Row")
A57: 53 | B57: 502 input.pdf | C57: 46113 | D57: 46142 | E57: 46117 | F57: 46117 | G57: DIGITA-MUMBAI/ IMPS/P2A/609509137308/SHREE GANESH EN/diselVVS910 | I57: Receipt | J57: 0 | K57: 63308 | L57: 63308 | M57: 108808 | N57: Recurring Transaction | O57: Yes | P57: SHREE GANESH EN | Q57: 0 | R57: 1 | S57: 0 | T57: 0 | U57: 0 | V57: 0 | W57: 0 | X57: 0 | Y57: 0 | Z57: 0 | AA57: 46117 | AB57: =HYPERLINK("#'Transactions'!A54", "View Source Row")
A58: 54 | B58: 502 input.pdf | C58: 46113 | D58: 46142 | E58: 46118 | F58: 46118 | G58: DIGITA-MUMBAI/ NEFT-AXNPN09635263353-PHONEPE LIMITED-PAYMENT AGGR | I58: Receipt | J58: 0 | K58: 58335.21 | L58: 58335.21 | M58: 167143.21 | N58: Recurring Transaction | O58: Yes | P58: PHONEPE LIMITED | Q58: 0 | R58: 1 | S58: 0 | T58: 0 | U58: 0 | V58: 0 | W58: 0 | X58: 0 | Y58: 0 | Z58: 0 | AA58: 46118 | AB58: =HYPERLINK("#'Transactions'!A55", "View Source Row")
A59: 55 | B59: 502 input.pdf | C59: 46113 | D59: 46142 | E59: 46118 | F59: 46118 | G59: DIGITA-MUMBAI/ NEFT-YESAP60964000643-PhonePe Limited | I59: Receipt | J59: 0 | K59: 169456 | L59: 169456 | M59: 336599.21 | N59: High Transaction; Recurring Transaction | O59: Yes | P59: PHONEPE LIMITED | Q59: 0 | R59: 1 | S59: 0 | T59: 0 | U59: 1 | V59: 0 | W59: 0 | X59: 0 | Y59: 0 | Z59: 0 | AA59: 46118 | AB59: =HYPERLINK("#'Transactions'!A56", "View Source Row")
A60: 56 | B60: 502 input.pdf | C60: 46113 | D60: 46142 | E60: 46118 | F60: 46118 | G60: DIGITA-MUMBAI/ NEFT-AXISCN1302642509-ONE MOBIKWIK SYSTEMS LIMITED | I60: Receipt | J60: 0 | K60: 31681 | L60: 31681 | M60: 368280.21 | N60: Recurring Transaction | O60: Yes | P60: ONE MOBIKWIK SYSTEMS LIMITED | Q60: 0 | R60: 1 | S60: 0 | T60: 0 | U60: 0 | V60: 0 | W60: 0 | X60: 0 | Y60: 0 | Z60: 0 | AA60: 46118 | AB60: =HYPERLINK("#'Transactions'!A57", "View Source Row")
A61: 57 | B61: 502 input.pdf | C61: 46113 | D61: 46142 | E61: 46118 | F61: 46118 | G61: EBANK:WIB/1502 EBANK:WIB/1502642025/Edfs | I61: Payment | J61: 365780.21 | K61: 0 | L61: 365780.21 | M61: 2500 | N61: High Transaction; Recurring Transaction | O61: Yes | P61: EBANKWIB | Q61: 0 | R61: 1 | S61: 0 | T61: 0 | U61: 1 | V61: 0 | W61: 0 | X61: 0 | Y61: 0 | Z61: 0 | AA61: 46118 | AB61: =HYPERLINK("#'Transactions'!A58", "View Source Row")
A62: 58 | B62: 502 input.pdf | C62: 46113 | D62: 46142 | E62: 46118 | F62: 46118 | G62: DIGITA-MUMBAI/ NEFT-AXISCN1302721272-PINE LABS PRIVATE LIMITED-NO | I62: Receipt | J62: 0 | K62: 29516 | L62: 29516 | M62: 32016 | N62: Recurring Transaction | O62: Yes | P62: PINE LABS PRIVATE LIMITED | Q62: 0 | R62: 1 | S62: 0 | T62: 0 | U62: 0 | V62: 0 | W62: 0 | X62: 0 | Y62: 0 | Z62: 0 | AA62: 46118 | AB62: =HYPERLINK("#'Transactions'!A59", "View Source Row")
A63: 59 | B63: 502 input.pdf | C63: 46113 | D63: 46142 | E63: 46118 | F63: 46118 | G63: DIGITA-MUMBAI/ ---------------------------------------------------------------------------------------------------------------------------------- Page Total: 7,86,664.57 8,85,980.57 1,32,016.00Cr ---------------------------------------------------------------------------------------------------------------------------------- Note: Cheques received in inward clearing will be considered for debiting/ returning on the basis opening balance in account Unless the constituent notifies the bank of any | I63: Receipt | J63: 0 | K63: 100000 | L63: 100000 | M63: 132016 | N63: High Transaction; Recurring Transaction | O63: Yes | P63: PAGE TOTAL CR | Q63: 0 | R63: 1 | S63: 0 | T63: 0 | U63: 1 | V63: 0 | W63: 0 | X63: 0 | Y63: 0 | Z63: 0 | AA63: 46118 | AB63: =HYPERLINK("#'Transactions'!A60", "View Source Row")
A64: 60 | B64: 502 input.pdf | C64: 46113 | D64: 46142 | E64: 46118 | F64: 46118 | G64: DIGITA-MUMBAI/ NEFT-AXISCN1302925515-PINE LABS PRIVATE LIMITED-NO | I64: Receipt | J64: 0 | K64: 14073 | L64: 14073 | M64: 146089 | N64: Recurring Transaction | O64: Yes | P64: PINE LABS PRIVATE LIMITED | Q64: 0 | R64: 1 | S64: 0 | T64: 0 | U64: 0 | V64: 0 | W64: 0 | X64: 0 | Y64: 0 | Z64: 0 | AA64: 46118 | AB64: =HYPERLINK("#'Transactions'!A61", "View Source Row")
A65: 61 | B65: 502 input.pdf | C65: 46113 | D65: 46142 | E65: 46118 | F65: 46118 | G65: UPI/8321480914 48091426 UPI/832148091426/12:12:00/UPI/7507026281@axl/Paym | I65: Receipt | J65: 0 | K65: 1000 | L65: 1000 | M65: 147089 | N65: UPI | O65: No | P65: UPI/# # UPI/#/#:#:#/UPI/#@AXL/PAYM | Q65: 0 | R65: 0 | S65: 0 | T65: 0 | U65: 0 | V65: 1 | W65: 0 | X65: 0 | Y65: 0 | Z65: 0 | AA65: 46118 | AB65: =HYPERLINK("#'Transactions'!A62", "View Source Row")
A66: 62 | B66: 502 input.pdf | C66: 46113 | D66: 46142 | E66: 46118 | F66: 46118 | G66: DIGITA-MUMBAI/ NEFT-HDFCH00913518284-CORPAK | I66: Receipt | J66: 0 | K66: 38524 | L66: 38524 | M66: 185613 | N66: Recurring Transaction | O66: Yes | P66: DIGITA-MUMBAI/ NEFT-HDFCH#-CORPAK | Q66: 0 | R66: 1 | S66: 0 | T66: 0 | U66: 0 | V66: 0 | W66: 0 | X66: 0 | Y66: 0 | Z66: 0 | AA66: 46118 | AB66: =HYPERLINK("#'Transactions'!A63", "View Source Row")
A67: 63 | B67: 502 input.pdf | C67: 46113 | D67: 46142 | E67: 46118 | F67: 46118 | G67: DIGITA-MUMBAI/ NEFT-NKGSH26096901712-GEBI PRODUCTS PRIVATE LIMITE | I67: Receipt | J67: 0 | K67: 15001 | L67: 15001 | M67: 200614 | N67: Recurring Transaction | O67: Yes | P67: GEBI PRODUCTS PRIVATE LIMITE | Q67: 0 | R67: 1 | S67: 0 | T67: 0 | U67: 0 | V67: 0 | W67: 0 | X67: 0 | Y67: 0 | Z67: 0 | AA67: 46118 | AB67: =HYPERLINK("#'Transactions'!A64", "View Source Row")
A68: 64 | B68: 502 input.pdf | C68: 46113 | D68: 46142 | E68: 46118 | F68: 46118 | G68: EBANK:WIB/1502 EBANK:WIB/1502790855/Edfs | I68: Payment | J68: 198114 | K68: 0 | L68: 198114 | M68: 2500 | N68: High Transaction; Recurring Transaction | O68: Yes | P68: EBANKWIB | Q68: 0 | R68: 1 | S68: 0 | T68: 0 | U68: 1 | V68: 0 | W68: 0 | X68: 0 | Y68: 0 | Z68: 0 | AA68: 46118 | AB68: =HYPERLINK("#'Transactions'!A65", "View Source Row")
A69: 65 | B69: 502 input.pdf | C69: 46113 | D69: 46142 | E69: 46118 | F69: 46118 | G69: DIGITA-MUMBAI/ NEFT-HDFCH00915259780-MOHANJI BHARAT WELFARE FOUND | I69: Receipt | J69: 0 | K69: 18448 | L69: 18448 | M69: 20948 | N69: Recurring Transaction | O69: Yes | P69: MOHANJI BHARAT WELFARE FOUND | Q69: 0 | R69: 1 | S69: 0 | T69: 0 | U69: 0 | V69: 0 | W69: 0 | X69: 0 | Y69: 0 | Z69: 0 | AA69: 46118 | AB69: =HYPERLINK("#'Transactions'!A66", "View Source Row")
A70: 66 | B70: 502 input.pdf | C70: 46113 | D70: 46142 | E70: 46119 | F70: 46119 | G70: DIGITA-MUMBAI/ NEFT-YESAP60974165954-PhonePe Limited | I70: Receipt | J70: 0 | K70: 260044.42 | L70: 260044.42 | M70: 280992.42 | N70: High Transaction; Recurring Transaction | O70: Yes | P70: PHONEPE LIMITED | Q70: 0 | R70: 1 | S70: 0 | T70: 0 | U70: 1 | V70: 0 | W70: 0 | X70: 0 | Y70: 0 | Z70: 0 | AA70: 46119 | AB70: =HYPERLINK("#'Transactions'!A67", "View Source Row")
A71: 67 | B71: 502 input.pdf | C71: 46113 | D71: 46142 | E71: 46119 | F71: 46119 | G71: DIGITA-MUMBAI/ NEFT-AXNPN09743969962-PHONEPE LIMITED-PAYMENT AGGR | I71: Receipt | J71: 0 | K71: 55000.65 | L71: 55000.65 | M71: 335993.07 | N71: Recurring Transaction | O71: Yes | P71: PHONEPE LIMITED | Q71: 0 | R71: 1 | S71: 0 | T71: 0 | U71: 0 | V71: 0 | W71: 0 | X71: 0 | Y71: 0 | Z71: 0 | AA71: 46119 | AB71: =HYPERLINK("#'Transactions'!A68", "View Source Row")
A72: 68 | B72: 502 input.pdf | C72: 46113 | D72: 46142 | E72: 46119 | F72: 46119 | G72: EBANK:WIB/1502 EBANK:WIB/1502821939/Edfs | I72: Payment | J72: 330493.07 | K72: 0 | L72: 330493.07 | M72: 5500 | N72: High Transaction; Recurring Transaction | O72: Yes | P72: EBANKWIB | Q72: 0 | R72: 1 | S72: 0 | T72: 0 | U72: 1 | V72: 0 | W72: 0 | X72: 0 | Y72: 0 | Z72: 0 | AA72: 46119 | AB72: =HYPERLINK("#'Transactions'!A69", "View Source Row")
A73: 69 | B73: 502 input.pdf | C73: 46113 | D73: 46142 | E73: 46119 | F73: 46119 | G73: UPI/8639137766 13776666 UPI/863913776666/06:48:44/UPI/surajdhanotra1@ibl/ | I73: Receipt | J73: 0 | K73: 9000 | L73: 9000 | M73: 14500 | N73: UPI; Recurring Transaction | O73: Yes | P73: SURAJDHANOTRAIBL | Q73: 0 | R73: 1 | S73: 0 | T73: 0 | U73: 0 | V73: 1 | W73: 0 | X73: 0 | Y73: 0 | Z73: 0 | AA73: 46119 | AB73: =HYPERLINK("#'Transactions'!A70", "View Source Row")
A74: 70 | B74: 502 input.pdf | C74: 46113 | D74: 46142 | E74: 46119 | F74: 46119 | G74: DIGITA-MUMBAI/ NEFT-AXISCN1303901852-ONE MOBIKWIK SYSTEMS LIMITED | I74: Receipt | J74: 0 | K74: 23072 | L74: 23072 | M74: 37572 | N74: Recurring Transaction | O74: Yes | P74: ONE MOBIKWIK SYSTEMS LIMITED | Q74: 0 | R74: 1 | S74: 0 | T74: 0 | U74: 0 | V74: 0 | W74: 0 | X74: 0 | Y74: 0 | Z74: 0 | AA74: 46119 | AB74: =HYPERLINK("#'Transactions'!A71", "View Source Row")
A75: 71 | B75: 502 input.pdf | C75: 46113 | D75: 46142 | E75: 46119 | F75: 46119 | G75: DIGITA-MUMBAI/ NEFT-AXISCN1303985526-PINE LABS PRIVATE LIMITED-NO | I75: Receipt | J75: 0 | K75: 25110 | L75: 25110 | M75: 62682 | N75: Recurring Transaction | O75: Yes | P75: PINE LABS PRIVATE LIMITED | Q75: 0 | R75: 1 | S75: 0 | T75: 0 | U75: 0 | V75: 0 | W75: 0 | X75: 0 | Y75: 0 | Z75: 0 | AA75: 46119 | AB75: =HYPERLINK("#'Transactions'!A72", "View Source Row")
A76: 72 | B76: 502 input.pdf | C76: 46113 | D76: 46142 | E76: 46119 | F76: 46119 | G76: Charges for Charges for PORD Customer Payment :003566909942 | I76: Payment | J76: 2.65 | K76: 0 | L76: 2.65 | M76: 62679.35 | N76: Recurring Transaction | O76: Yes | P76: CHARGES FOR CHARGES FOR PORD CUSTOMER PA | Q76: 0 | R76: 1 | S76: 0 | T76: 0 | U76: 0 | V76: 0 | W76: 0 | X76: 0 | Y76: 0 | Z76: 0 | AA76: 46119 | AB76: =HYPERLINK("#'Transactions'!A73", "View Source Row")
A77: 73 | B77: 502 input.pdf | C77: 46113 | D77: 46142 | E77: 46119 | F77: 46119 | G77: NEFT-BARBT2609 NEFT-BARBT26097282981-PETROL DEALERS ASSOCIATION | I77: Payment | J77: 4000 | K77: 0 | L77: 4000 | M77: 58679.35 | N77: Other | O77: No | P77: BARBT NEFT | Q77: 0 | R77: 0 | S77: 0 | T77: 0 | U77: 0 | V77: 0 | W77: 0 | X77: 0 | Y77: 0 | Z77: 0 | AA77: 46119 | AB77: =HYPERLINK("#'Transactions'!A74", "View Source Row")
A78: 74 | B78: 502 input.pdf | C78: 46113 | D78: 46142 | E78: 46119 | F78: 46119 | G78: DIGITA-MUMBAI/ NEFT-HDFCH00916196159-MARK LUBES PRIVATE LIMITED | I78: Receipt | J78: 0 | K78: 3617 | L78: 3617 | M78: 62296.35 | N78: Recurring Transaction | O78: Yes | P78: MARK LUBES PRIVATE LIMITED | Q78: 0 | R78: 1 | S78: 0 | T78: 0 | U78: 0 | V78: 0 | W78: 0 | X78: 0 | Y78: 0 | Z78: 0 | AA78: 46119 | AB78: =HYPERLINK("#'Transactions'!A75", "View Source Row")
A79: 75 | B79: 502 input.pdf | C79: 46113 | D79: 46142 | E79: 46119 | F79: 46119 | G79: BY CASH ---------------------------------------------------------------------------------------------------------------------------------- Page Total: 5,32,609.72 5,77,390.07 1,76,796.35Cr ---------------------------------------------------------------------------------------------------------------------------------- Note: Cheques received in inward clearing will be considered for debiting/ returning on the basis opening balance in account Unless the constituent notifies the bank of any discrep | I79: Receipt | J79: 0 | K79: 114500 | L79: 114500 | M79: 176796.35 | N79: Cash; High Transaction; Recurring Transaction | O79: Yes | P79: PAGE TOTAL CR | Q79: 1 | R79: 1 | S79: 0 | T79: 0 | U79: 1 | V79: 0 | W79: 0 | X79: 0 | Y79: 0 | Z79: 0 | AA79: 46119 | AB79: =HYPERLINK("#'Transactions'!A76", "View Source Row")
A80: 76 | B80: 502 input.pdf | C80: 46113 | D80: 46142 | E80: 46119 | F80: 46119 | G80: WADPAL-WADA,MH 143 BOB DD EXECUTIVE ENG PWD JAWHAR-WADPAL | I80: Payment | J80: 99037 | K80: 0 | L80: 99037 | M80: 77759.35 | N80: Other | O80: No | P80: WADAMH BOB DD EXECUTIVE ENG PWD JAWHAR | Q80: 0 | R80: 0 | S80: 0 | T80: 0 | U80: 0 | V80: 0 | W80: 0 | X80: 0 | Y80: 0 | Z80: 0 | AA80: 46119 | AB80: =HYPERLINK("#'Transactions'!A77", "View Source Row")
A81: 77 | B81: 502 input.pdf | C81: 46113 | D81: 46142 | E81: 46119 | F81: 46119 | G81: UPI/6463233094 23309409 UPI/646323309409/14:08:53/UPI/gotarne.pratik@axl/ | I81: Payment | J81: 500 | K81: 0 | L81: 500 | M81: 77259.35 | N81: UPI | O81: No | P81: GOTARNEPRATIKAXL | Q81: 0 | R81: 0 | S81: 0 | T81: 0 | U81: 0 | V81: 1 | W81: 0 | X81: 0 | Y81: 0 | Z81: 0 | AA81: 46119 | AB81: =HYPERLINK("#'Transactions'!A78", "View Source Row")
A82: 78 | B82: 502 input.pdf | C82: 46113 | D82: 46142 | E82: 46119 | F82: 46119 | G82: DIGITA-MUMBAI/ NEFT-KKBKH26097664663-ATLAS COMMODITIES PRIVATE LI | I82: Receipt | J82: 0 | K82: 3405 | L82: 3405 | M82: 80664.35 | N82: Recurring Transaction | O82: Yes | P82: ATLAS COMMODITIES PRIVATE LI | Q82: 0 | R82: 1 | S82: 0 | T82: 0 | U82: 0 | V82: 0 | W82: 0 | X82: 0 | Y82: 0 | Z82: 0 | AA82: 46119 | AB82: =HYPERLINK("#'Transactions'!A79", "View Source Row")
A83: 79 | B83: 502 input.pdf | C83: 46113 | D83: 46142 | E83: 46119 | F83: 46119 | G83: DIGITA-MUMBAI/ https://cbdrpt101.bankofbaroda.co.in:22000/finbranch/arjspmorph/INFENG/tran_rpt.jsp?... 04-05-2026 NEFT-NKGSH26097920270-GEBI PRODUCTS PRIVATE LIMITE | I83: Receipt | J83: 0 | K83: 2618 | L83: 2618 | M83: 83282.35 | N83: Recurring Transaction | O83: Yes | P83: CBDRPTBANKOFBARODACOIN | Q83: 0 | R83: 1 | S83: 0 | T83: 0 | U83: 0 | V83: 0 | W83: 0 | X83: 0 | Y83: 0 | Z83: 0 | AA83: 46119 | AB83: =HYPERLINK("#'Transactions'!A80", "View Source Row")
A84: 80 | B84: 502 input.pdf | C84: 46113 | D84: 46142 | E84: 46119 | F84: 46119 | G84: DIGITA-MUMBAI/ NEFT-HDFCH00917822677-SL CORBOX PRIVATE LIMITED | I84: Receipt | J84: 0 | K84: 56800 | L84: 56800 | M84: 140082.35 | N84: Recurring Transaction | O84: Yes | P84: SL CORBOX PRIVATE LIMITED | Q84: 0 | R84: 1 | S84: 0 | T84: 0 | U84: 0 | V84: 0 | W84: 0 | X84: 0 | Y84: 0 | Z84: 0 | AA84: 46119 | AB84: =HYPERLINK("#'Transactions'!A81", "View Source Row")
A85: 81 | B85: 502 input.pdf | C85: 46113 | D85: 46142 | E85: 46119 | F85: 46119 | G85: EBANK:WIB/1502 EBANK:WIB/1502986421/Edfs | I85: Payment | J85: 137582.35 | K85: 0 | L85: 137582.35 | M85: 2500 | N85: High Transaction; Recurring Transaction | O85: Yes | P85: EBANKWIB | Q85: 0 | R85: 1 | S85: 0 | T85: 0 | U85: 1 | V85: 0 | W85: 0 | X85: 0 | Y85: 0 | Z85: 0 | AA85: 46119 | AB85: =HYPERLINK("#'Transactions'!A82", "View Source Row")
A86: 82 | B86: 502 input.pdf | C86: 46113 | D86: 46142 | E86: 46119 | F86: 46119 | G86: DIGITA-MUMBAI/ NEFT-IN42609750724469-VINAYAK OIL INDUSTRIES | I86: Receipt | J86: 0 | K86: 37413 | L86: 37413 | M86: 39913 | N86: Recurring Transaction | O86: Yes | P86: VINAYAK OIL INDUSTRIES | Q86: 0 | R86: 1 | S86: 0 | T86: 0 | U86: 0 | V86: 0 | W86: 0 | X86: 0 | Y86: 0 | Z86: 0 | AA86: 46119 | AB86: =HYPERLINK("#'Transactions'!A83", "View Source Row")
A87: 83 | B87: 502 input.pdf | C87: 46113 | D87: 46142 | E87: 46120 | F87: 46120 | G87: DIGITA-MUMBAI/ NEFT-YESAP60983679319-PhonePe Limited | I87: Receipt | J87: 0 | K87: 243684 | L87: 243684 | M87: 283597 | N87: High Transaction; Recurring Transaction | O87: Yes | P87: PHONEPE LIMITED | Q87: 0 | R87: 1 | S87: 0 | T87: 0 | U87: 1 | V87: 0 | W87: 0 | X87: 0 | Y87: 0 | Z87: 0 | AA87: 46120 | AB87: =HYPERLINK("#'Transactions'!A84", "View Source Row")
A88: 84 | B88: 502 input.pdf | C88: 46113 | D88: 46142 | E88: 46120 | F88: 46120 | G88: UPI/6464912624 91262434 UPI/646491262434/06:48:01/UPI/9822321566@centralb | I88: Payment | J88: 37085 | K88: 0 | L88: 37085 | M88: 246512 | N88: UPI | O88: No | P88: CENTRALB | Q88: 0 | R88: 0 | S88: 0 | T88: 0 | U88: 0 | V88: 1 | W88: 0 | X88: 0 | Y88: 0 | Z88: 0 | AA88: 46120 | AB88: =HYPERLINK("#'Transactions'!A85", "View Source Row")
A89: 85 | B89: 502 input.pdf | C89: 46113 | D89: 46142 | E89: 46120 | F89: 46120 | G89: DIGITA-MUMBAI/ NEFT-AXNPN09852795681-PHONEPE LIMITED-PAYMENT AGGR | I89: Receipt | J89: 0 | K89: 47737 | L89: 47737 | M89: 294249 | N89: Recurring Transaction | O89: Yes | P89: PHONEPE LIMITED | Q89: 0 | R89: 1 | S89: 0 | T89: 0 | U89: 0 | V89: 0 | W89: 0 | X89: 0 | Y89: 0 | Z89: 0 | AA89: 46120 | AB89: =HYPERLINK("#'Transactions'!A86", "View Source Row")
A90: 86 | B90: 502 input.pdf | C90: 46113 | D90: 46142 | E90: 46120 | F90: 46120 | G90: Chg Cash Chg Cash handling for:30-03-2026 | I90: Payment | J90: 24 | K90: 0 | L90: 24 | M90: 294225 | N90: Cash | O90: No | P90: CHG CASH CHG CASH HANDLING FOR | Q90: 1 | R90: 0 | S90: 0 | T90: 0 | U90: 0 | V90: 0 | W90: 0 | X90: 0 | Y90: 0 | Z90: 0 | AA90: 46120 | AB90: =HYPERLINK("#'Transactions'!A87", "View Source Row")
A91: 87 | B91: 502 input.pdf | C91: 46113 | D91: 46142 | E91: 46120 | F91: 46120 | G91: DIGITA-MUMBAI/ NEFT-AXISCN1305078531-ONE MOBIKWIK SYSTEMS LIMITED | I91: Receipt | J91: 0 | K91: 13338 | L91: 13338 | M91: 307563 | N91: Recurring Transaction | O91: Yes | P91: ONE MOBIKWIK SYSTEMS LIMITED | Q91: 0 | R91: 1 | S91: 0 | T91: 0 | U91: 0 | V91: 0 | W91: 0 | X91: 0 | Y91: 0 | Z91: 0 | AA91: 46120 | AB91: =HYPERLINK("#'Transactions'!A88", "View Source Row")
A92: 88 | B92: 502 input.pdf | C92: 46113 | D92: 46142 | E92: 46120 | F92: 46120 | G92: DIGITA-MUMBAI/ NEFT-AXISCN1305183876-PINE LABS PRIVATE LIMITED-NO | I92: Receipt | J92: 0 | K92: 76050 | L92: 76050 | M92: 383613 | N92: Recurring Transaction | O92: Yes | P92: PINE LABS PRIVATE LIMITED | Q92: 0 | R92: 1 | S92: 0 | T92: 0 | U92: 0 | V92: 0 | W92: 0 | X92: 0 | Y92: 0 | Z92: 0 | AA92: 46120 | AB92: =HYPERLINK("#'Transactions'!A89", "View Source Row")
A93: 89 | B93: 502 input.pdf | C93: 46113 | D93: 46142 | E93: 46120 | F93: 46120 | G93: EBANK:WIB/1503 EBANK:WIB/1503050809/Edfs | I93: Payment | J93: 381113 | K93: 0 | L93: 381113 | M93: 2500 | N93: High Transaction; Recurring Transaction | O93: Yes | P93: EBANKWIB | Q93: 0 | R93: 1 | S93: 0 | T93: 0 | U93: 1 | V93: 0 | W93: 0 | X93: 0 | Y93: 0 | Z93: 0 | AA93: 46120 | AB93: =HYPERLINK("#'Transactions'!A90", "View Source Row")
A94: 90 | B94: 502 input.pdf | C94: 46113 | D94: 46142 | E94: 46120 | F94: 46120 | G94: DIGITA-MUMBAI/ IMPS/P2A/609812907682/OMSANITRANSPORT/Diesel Bill | I94: Receipt | J94: 0 | K94: 40356 | L94: 40356 | M94: 42856 | N94: Recurring Transaction | O94: Yes | P94: OMSANITRANSPORT | Q94: 0 | R94: 1 | S94: 0 | T94: 0 | U94: 0 | V94: 0 | W94: 0 | X94: 0 | Y94: 0 | Z94: 0 | AA94: 46120 | AB94: =HYPERLINK("#'Transactions'!A91", "View Source Row")
A95: 91 | B95: 502 input.pdf | C95: 46113 | D95: 46142 | E95: 46120 | F95: 46120 | G95: DIGITA-MUMBAI/ ---------------------------------------------------------------------------------------------------------------------------------- Page Total: 6,55,341.35 5,23,307.00 44,762.00Cr ---------------------------------------------------------------------------------------------------------------------------------- Note: Cheques received in inward clearing will be considered for debiting/ returning on the basis opening balance in account Unless the constituent notifies the bank of any di | I95: Receipt | J95: 0 | K95: 1906 | L95: 1906 | M95: 44762 | N95: Recurring Transaction | O95: Yes | P95: PAGE TOTAL CR | Q95: 0 | R95: 1 | S95: 0 | T95: 0 | U95: 0 | V95: 0 | W95: 0 | X95: 0 | Y95: 0 | Z95: 0 | AA95: 46120 | AB95: =HYPERLINK("#'Transactions'!A92", "View Source Row")
A96: 92 | B96: 502 input.pdf | C96: 46113 | D96: 46142 | E96: 46120 | F96: 46120 | G96: DIGITA-MUMBAI/ NEFT-IDIBH09837346562-JAI AMBE TRANSPORT | I96: Receipt | J96: 0 | K96: 3050 | L96: 3050 | M96: 47812 | N96: Recurring Transaction | O96: Yes | P96: JAI AMBE TRANSPORT | Q96: 0 | R96: 1 | S96: 0 | T96: 0 | U96: 0 | V96: 0 | W96: 0 | X96: 0 | Y96: 0 | Z96: 0 | AA96: 46120 | AB96: =HYPERLINK("#'Transactions'!A93", "View Source Row")
A97: 93 | B97: 502 input.pdf | C97: 46113 | D97: 46142 | E97: 46120 | F97: 46120 | G97: DIGITA-MUMBAI/ IMPS/P2A/609818576145/SHREE GANESH EN/diselVVS910 | I97: Receipt | J97: 0 | K97: 63308 | L97: 63308 | M97: 111120 | N97: Recurring Transaction | O97: Yes | P97: SHREE GANESH EN | Q97: 0 | R97: 1 | S97: 0 | T97: 0 | U97: 0 | V97: 0 | W97: 0 | X97: 0 | Y97: 0 | Z97: 0 | AA97: 46120 | AB97: =HYPERLINK("#'Transactions'!A94", "View Source Row")
A98: 94 | B98: 502 input.pdf | C98: 46113 | D98: 46142 | E98: 46120 | F98: 46120 | G98: EBANK:WIB/1503 EBANK:WIB/1503170712/Edfs | I98: Payment | J98: 108620 | K98: 0 | L98: 108620 | M98: 2500 | N98: High Transaction; Recurring Transaction | O98: Yes | P98: EBANKWIB | Q98: 0 | R98: 1 | S98: 0 | T98: 0 | U98: 1 | V98: 0 | W98: 0 | X98: 0 | Y98: 0 | Z98: 0 | AA98: 46120 | AB98: =HYPERLINK("#'Transactions'!A95", "View Source Row")
A99: 95 | B99: 502 input.pdf | C99: 46113 | D99: 46142 | E99: 46121 | F99: 46121 | G99: DIGITA-MUMBAI/ NEFT-YESAP60993677587-PhonePe Limited | I99: Receipt | J99: 0 | K99: 170522 | L99: 170522 | M99: 173022 | N99: High Transaction; Recurring Transaction | O99: Yes | P99: PHONEPE LIMITED | Q99: 0 | R99: 1 | S99: 0 | T99: 0 | U99: 1 | V99: 0 | W99: 0 | X99: 0 | Y99: 0 | Z99: 0 | AA99: 46121 | AB99: =HYPERLINK("#'Transactions'!A96", "View Source Row")
A100: 96 | B100: 502 input.pdf | C100: 46113 | D100: 46142 | E100: 46121 | F100: 46121 | G100: DIGITA-MUMBAI/ NEFT-AXNPN09961131765-PHONEPE LIMITED-PAYMENT AGGR | I100: Receipt | J100: 0 | K100: 49090 | L100: 49090 | M100: 222112 | N100: Recurring Transaction | O100: Yes | P100: PHONEPE LIMITED | Q100: 0 | R100: 1 | S100: 0 | T100: 0 | U100: 0 | V100: 0 | W100: 0 | X100: 0 | Y100: 0 | Z100: 0 | AA100: 46121 | AB100: =HYPERLINK("#'Transactions'!A97", "View Source Row")
A101: 97 | B101: 502 input.pdf | C101: 46113 | D101: 46142 | E101: 46121 | F101: 46121 | G101: DIGITA-MUMBAI/ NEFT-AXISCN1306324510-ONE MOBIKWIK SYSTEMS LIMITED | I101: Receipt | J101: 0 | K101: 15270 | L101: 15270 | M101: 237382 | N101: Recurring Transaction | O101: Yes | P101: ONE MOBIKWIK SYSTEMS LIMITED | Q101: 0 | R101: 1 | S101: 0 | T101: 0 | U101: 0 | V101: 0 | W101: 0 | X101: 0 | Y101: 0 | Z101: 0 | AA101: 46121 | AB101: =HYPERLINK("#'Transactions'!A98", "View Source Row")
...

Sheet Detail Cash
A1: =HYPERLINK("#'Dashboard'!A1", "← Return to Dashboard") | B1: Cash Transactions
A2: Rows | B2: 2 | C2: Match | D2: Cash
A4: Seq | B4: Source File | C4: Statement From | D4: Statement To | E4: Date | F4: Value Date | G4: Narration | H4: Reference | I4: Direction | J4: Withdrawal | K4: Deposit | L4: Amount | M4: Closing Balance | N4: Categories | O4: Recurring? | P4: Recurring Key | Q4: Flag - Cash | R4: Flag - Recurring Transaction | S4: Flag - EMI | T4: Flag - Salary | U4: Flag - High Transaction | V4: Flag - UPI | W4: Flag - LIC | X4: Flag - FD interest | Y4: Flag - FD Deposit and withdrawals | Z4: Flag - PPF/PF interest and contribution | AA4: Month Date | AB4: View Source Row
A5: 75 | B5: 502 input.pdf | C5: 46113 | D5: 46142 | E5: 46119 | F5: 46119 | G5: BY CASH ---------------------------------------------------------------------------------------------------------------------------------- Page Total: 5,32,609.72 5,77,390.07 1,76,796.35Cr ---------------------------------------------------------------------------------------------------------------------------------- Note: Cheques received in inward clearing will be considered for debiting/ returning on the basis opening balance in account Unless the constituent notifies the bank of any discrep | I5: Receipt | J5: 0 | K5: 114500 | L5: 114500 | M5: 176796.35 | N5: Cash; High Transaction; Recurring Transaction | O5: Yes | P5: PAGE TOTAL CR | Q5: 1 | R5: 1 | S5: 0 | T5: 0 | U5: 1 | V5: 0 | W5: 0 | X5: 0 | Y5: 0 | Z5: 0 | AA5: 46119 | AB5: =HYPERLINK("#'Transactions'!A76", "View Source Row")
A6: 86 | B6: 502 input.pdf | C6: 46113 | D6: 46142 | E6: 46120 | F6: 46120 | G6: Chg Cash Chg Cash handling for:30-03-2026 | I6: Payment | J6: 24 | K6: 0 | L6: 24 | M6: 294225 | N6: Cash | O6: No | P6: CHG CASH CHG CASH HANDLING FOR | Q6: 1 | R6: 0 | S6: 0 | T6: 0 | U6: 0 | V6: 0 | W6: 0 | X6: 0 | Y6: 0 | Z6: 0 | AA6: 46120 | AB6: =HYPERLINK("#'Transactions'!A87", "View Source Row")

Sheet Detail Recurring Transaction
A1: =HYPERLINK("#'Dashboard'!A1", "← Return to Dashboard") | B1: Recurring Transaction Transactions
A2: Rows | B2: 346 | C2: Match | D2: Recurring Transaction
A4: Seq | B4: Source File | C4: Statement From | D4: Statement To | E4: Date | F4: Value Date | G4: Narration | H4: Reference | I4: Direction | J4: Withdrawal | K4: Deposit | L4: Amount | M4: Closing Balance | N4: Categories | O4: Recurring? | P4: Recurring Key | Q4: Flag - Cash | R4: Flag - Recurring Transaction | S4: Flag - EMI | T4: Flag - Salary | U4: Flag - High Transaction | V4: Flag - UPI | W4: Flag - LIC | X4: Flag - FD interest | Y4: Flag - FD Deposit and withdrawals | Z4: Flag - PPF/PF interest and contribution | AA4: Month Date | AB4: View Source Row
A5: 2 | B5: 502 input.pdf | C5: 46113 | D5: 46142 | E5: 46114 | F5: 46114 | G5: DIGITA-MUMBAI/ NEFT-YESAP60912594024-PhonePe Limited | I5: Receipt | J5: 0 | K5: 165179 | L5: 165179 | M5: 581570 | N5: High Transaction; Recurring Transaction | O5: Yes | P5: PHONEPE LIMITED | Q5: 0 | R5: 1 | S5: 0 | T5: 0 | U5: 1 | V5: 0 | W5: 0 | X5: 0 | Y5: 0 | Z5: 0 | AA5: 46114 | AB5: =HYPERLINK("#'Transactions'!A3", "View Source Row")
A6: 6 | B6: 502 input.pdf | C6: 46113 | D6: 46142 | E6: 46114 | F6: 46114 | G6: EBANK:WIB/1502 EBANK:WIB/1502021829/Edfs | I6: Payment | J6: 681881.6 | K6: 0 | L6: 681881.6 | M6: 2500 | N6: High Transaction; Recurring Transaction | O6: Yes | P6: EBANKWIB | Q6: 0 | R6: 1 | S6: 0 | T6: 0 | U6: 1 | V6: 0 | W6: 0 | X6: 0 | Y6: 0 | Z6: 0 | AA6: 46114 | AB6: =HYPERLINK("#'Transactions'!A7", "View Source Row")
A7: 7 | B7: 502 input.pdf | C7: 46113 | D7: 46142 | E7: 46114 | F7: 46114 | G7: DIGITA-MUMBAI/ NEFT-FBPT260916108327-PREMIER CONVEYORS PRIVATE LI | I7: Receipt | J7: 0 | K7: 18409 | L7: 18409 | M7: 20909 | N7: EMI; Recurring Transaction | O7: Yes | P7: PREMIER CONVEYORS PRIVATE LI | Q7: 0 | R7: 1 | S7: 1 | T7: 0 | U7: 0 | V7: 0 | W7: 0 | X7: 0 | Y7: 0 | Z7: 0 | AA7: 46114 | AB7: =HYPERLINK("#'Transactions'!A8", "View Source Row")
A8: 8 | B8: 502 input.pdf | C8: 46113 | D8: 46142 | E8: 46114 | F8: 46114 | G8: DIGITA-MUMBAI/ NEFT-CNRBH00121803213-QUALITY PLAST INDUSTRIES LIM | I8: Receipt | J8: 0 | K8: 121431 | L8: 121431 | M8: 142340 | N8: High Transaction; Recurring Transaction | O8: Yes | P8: QUALITY PLAST INDUSTRIES LIM | Q8: 0 | R8: 1 | S8: 0 | T8: 0 | U8: 1 | V8: 0 | W8: 0 | X8: 0 | Y8: 0 | Z8: 0 | AA8: 46114 | AB8: =HYPERLINK("#'Transactions'!A9", "View Source Row")
A9: 10 | B9: 502 input.pdf | C9: 46113 | D9: 46142 | E9: 46114 | F9: 46114 | G9: DIGITA-MUMBAI/ IMPS/P2A/609116466512/AFZALSIRAJUDDIN/IMPSUOB9191 | I9: Receipt | J9: 0 | K9: 100000 | L9: 100000 | M9: 240840 | N9: High Transaction; Recurring Transaction | O9: Yes | P9: AFZALSIRAJUDDIN | Q9: 0 | R9: 1 | S9: 0 | T9: 0 | U9: 1 | V9: 0 | W9: 0 | X9: 0 | Y9: 0 | Z9: 0 | AA9: 46114 | AB9: =HYPERLINK("#'Transactions'!A11", "View Source Row")
A10: 11 | B10: 502 input.pdf | C10: 46113 | D10: 46142 | E10: 46114 | F10: 46114 | G10: DIGITA-MUMBAI/ NEFT-KKBKH26091970510-VENKTESHWAR INDUSTRIAL CORPO | I10: Receipt | J10: 0 | K10: 10000 | L10: 10000 | M10: 250840 | N10: Recurring Transaction | O10: Yes | P10: VENKTESHWAR INDUSTRIAL CORPO | Q10: 0 | R10: 1 | S10: 0 | T10: 0 | U10: 0 | V10: 0 | W10: 0 | X10: 0 | Y10: 0 | Z10: 0 | AA10: 46114 | AB10: =HYPERLINK("#'Transactions'!A12", "View Source Row")
A11: 12 | B11: 502 input.pdf | C11: 46113 | D11: 46142 | E11: 46114 | F11: 46114 | G11: EBANK:WIB/1502 ---------------------------------------------------------------------------------------------------------------------------------- Page Total: 9,34,077.60 5,73,386.60 2,500.00Cr ---------------------------------------------------------------------------------------------------------------------------------- Note: Cheques received in inward clearing will be considered for debiting/ returning on the basis opening balance in account Unless the constituent notifies the bank of any dis | I11: Payment | J11: 248340 | K11: 0 | L11: 248340 | M11: 2500 | N11: High Transaction; Recurring Transaction | O11: Yes | P11: EBANKWIB | Q11: 0 | R11: 1 | S11: 0 | T11: 0 | U11: 1 | V11: 0 | W11: 0 | X11: 0 | Y11: 0 | Z11: 0 | AA11: 46114 | AB11: =HYPERLINK("#'Transactions'!A13", "View Source Row")
A12: 13 | B12: 502 input.pdf | C12: 46113 | D12: 46142 | E12: 46114 | F12: 46114 | G12: DIGITA-MUMBAI/ NEFT-YESAP60924833309-PhonePe Limited | I12: Receipt | J12: 0 | K12: 188588.4 | L12: 188588.4 | M12: 191088.4 | N12: High Transaction; Recurring Transaction | O12: Yes | P12: PHONEPE LIMITED | Q12: 0 | R12: 1 | S12: 0 | T12: 0 | U12: 1 | V12: 0 | W12: 0 | X12: 0 | Y12: 0 | Z12: 0 | AA12: 46114 | AB12: =HYPERLINK("#'Transactions'!A14", "View Source Row")
A13: 14 | B13: 502 input.pdf | C13: 46113 | D13: 46142 | E13: 46114 | F13: 46114 | G13: DIGITA-MUMBAI/ NEFT-AXNPN09202196281-PHONEPE LIMITED-PAYMENT AGGR | I13: Receipt | J13: 0 | K13: 50884.1 | L13: 50884.1 | M13: 241972.5 | N13: Recurring Transaction | O13: Yes | P13: PHONEPE LIMITED | Q13: 0 | R13: 1 | S13: 0 | T13: 0 | U13: 0 | V13: 0 | W13: 0 | X13: 0 | Y13: 0 | Z13: 0 | AA13: 46114 | AB13: =HYPERLINK("#'Transactions'!A15", "View Source Row")
A14: 15 | B14: 502 input.pdf | C14: 46113 | D14: 46142 | E14: 46114 | F14: 46114 | G14: DIGITA-MUMBAI/ NEFT-AXISCN1298773772-ONE MOBIKWIK SYSTEMS LIMITED https://cbdrpt101.bankofbaroda.co.in:22000/finbranch/arjspmorph/INFENG/tran_rpt.jsp?... 04-05-2026 | I14: Receipt | J14: 0 | K14: 26312 | L14: 26312 | M14: 268284.5 | N14: Recurring Transaction | O14: Yes | P14: ONE MOBIKWIK SYSTEMS LIMITED HTTPS | Q14: 0 | R14: 1 | S14: 0 | T14: 0 | U14: 0 | V14: 0 | W14: 0 | X14: 0 | Y14: 0 | Z14: 0 | AA14: 46114 | AB14: =HYPERLINK("#'Transactions'!A16", "View Source Row")
A15: 16 | B15: 502 input.pdf | C15: 46113 | D15: 46142 | E15: 46114 | F15: 46114 | G15: DIGITA-MUMBAI/ IMPS/P2A/609208556385/OMSANITRANSPORT/IMPSUOB9195 | I15: Receipt | J15: 0 | K15: 16450 | L15: 16450 | M15: 284734.5 | N15: Recurring Transaction | O15: Yes | P15: OMSANITRANSPORT | Q15: 0 | R15: 1 | S15: 0 | T15: 0 | U15: 0 | V15: 0 | W15: 0 | X15: 0 | Y15: 0 | Z15: 0 | AA15: 46114 | AB15: =HYPERLINK("#'Transactions'!A17", "View Source Row")
A16: 17 | B16: 502 input.pdf | C16: 46113 | D16: 46142 | E16: 46114 | F16: 46114 | G16: DIGITA-MUMBAI/ NEFT-AXISCN1298906804-PINE LABS PRIVATE LIMITED-NO | I16: Receipt | J16: 0 | K16: 61903 | L16: 61903 | M16: 346637.5 | N16: Recurring Transaction | O16: Yes | P16: PINE LABS PRIVATE LIMITED | Q16: 0 | R16: 1 | S16: 0 | T16: 0 | U16: 0 | V16: 0 | W16: 0 | X16: 0 | Y16: 0 | Z16: 0 | AA16: 46114 | AB16: =HYPERLINK("#'Transactions'!A18", "View Source Row")
A17: 18 | B17: 502 input.pdf | C17: 46113 | D17: 46142 | E17: 46114 | F17: 46114 | G17: DIGITA-MUMBAI/ NEFT-AXISCN1299028324-PINE LABS PRIVATE LIMITED-NO | I17: Receipt | J17: 0 | K17: 166884 | L17: 166884 | M17: 513521.5 | N17: High Transaction; Recurring Transaction | O17: Yes | P17: PINE LABS PRIVATE LIMITED | Q17: 0 | R17: 1 | S17: 0 | T17: 0 | U17: 1 | V17: 0 | W17: 0 | X17: 0 | Y17: 0 | Z17: 0 | AA17: 46114 | AB17: =HYPERLINK("#'Transactions'!A19", "View Source Row")
A18: 20 | B18: 502 input.pdf | C18: 46113 | D18: 46142 | E18: 46114 | F18: 46114 | G18: DIGITA-MUMBAI/ IMPS/P2A/609211135154/SHREE GANESH EN/dieselVVS91 | I18: Receipt | J18: 0 | K18: 63308 | L18: 63308 | M18: 572829.5 | N18: Recurring Transaction | O18: Yes | P18: SHREE GANESH EN | Q18: 0 | R18: 1 | S18: 0 | T18: 0 | U18: 0 | V18: 0 | W18: 0 | X18: 0 | Y18: 0 | Z18: 0 | AA18: 46114 | AB18: =HYPERLINK("#'Transactions'!A21", "View Source Row")
A19: 21 | B19: 502 input.pdf | C19: 46113 | D19: 46142 | E19: 46114 | F19: 46114 | G19: DIGITA-MUMBAI/ NEFT-KKBKH26092777992-VENKTESHWAR INDUSTRIAL CORPO | I19: Receipt | J19: 0 | K19: 18088 | L19: 18088 | M19: 590917.5 | N19: Recurring Transaction | O19: Yes | P19: VENKTESHWAR INDUSTRIAL CORPO | Q19: 0 | R19: 1 | S19: 0 | T19: 0 | U19: 0 | V19: 0 | W19: 0 | X19: 0 | Y19: 0 | Z19: 0 | AA19: 46114 | AB19: =HYPERLINK("#'Transactions'!A22", "View Source Row")
A20: 23 | B20: 502 input.pdf | C20: 46113 | D20: 46142 | E20: 46114 | F20: 46114 | G20: DIGITA-MUMBAI/ NEFT-NKGSH26092846591-GEBI PRODUCTS PRIVATE LIMITE | I20: Receipt | J20: 0 | K20: 12813 | L20: 12813 | M20: 600930.5 | N20: Recurring Transaction | O20: Yes | P20: GEBI PRODUCTS PRIVATE LIMITE | Q20: 0 | R20: 1 | S20: 0 | T20: 0 | U20: 0 | V20: 0 | W20: 0 | X20: 0 | Y20: 0 | Z20: 0 | AA20: 46114 | AB20: =HYPERLINK("#'Transactions'!A24", "View Source Row")
A21: 24 | B21: 502 input.pdf | C21: 46113 | D21: 46142 | E21: 46114 | F21: 46114 | G21: DIGITA-MUMBAI/ NEFT-IDIBH09236262399-JAI AMBE TRANSPORT | I21: Receipt | J21: 0 | K21: 4378 | L21: 4378 | M21: 605308.5 | N21: Recurring Transaction | O21: Yes | P21: JAI AMBE TRANSPORT | Q21: 0 | R21: 1 | S21: 0 | T21: 0 | U21: 0 | V21: 0 | W21: 0 | X21: 0 | Y21: 0 | Z21: 0 | AA21: 46114 | AB21: =HYPERLINK("#'Transactions'!A25", "View Source Row")
A22: 25 | B22: 502 input.pdf | C22: 46113 | D22: 46142 | E22: 46114 | F22: 46114 | G22: DIGITA-MUMBAI/ NEFT-HDFCH00905140576-Adekar enterprises pvt ltd | I22: Receipt | J22: 0 | K22: 138674 | L22: 138674 | M22: 743982.5 | N22: High Transaction; Recurring Transaction | O22: Yes | P22: ADEKAR ENTERPRISES PVT LTD | Q22: 0 | R22: 1 | S22: 0 | T22: 0 | U22: 1 | V22: 0 | W22: 0 | X22: 0 | Y22: 0 | Z22: 0 | AA22: 46114 | AB22: =HYPERLINK("#'Transactions'!A26", "View Source Row")
A23: 26 | B23: 502 input.pdf | C23: 46113 | D23: 46142 | E23: 46114 | F23: 46114 | G23: DIGITA-MUMBAI/ NEFT-TDCBH26092001785-V C ENTERPRISES | I23: Receipt | J23: 0 | K23: 50000 | L23: 50000 | M23: 793982.5 | N23: Recurring Transaction | O23: Yes | P23: V C ENTERPRISES | Q23: 0 | R23: 1 | S23: 0 | T23: 0 | U23: 0 | V23: 0 | W23: 0 | X23: 0 | Y23: 0 | Z23: 0 | AA23: 46114 | AB23: =HYPERLINK("#'Transactions'!A27", "View Source Row")
A24: 27 | B24: 502 input.pdf | C24: 46113 | D24: 46142 | E24: 46114 | F24: 46114 | G24: EBANK:WIB/1502 EBANK:WIB/1502234210/Edfs | I24: Payment | J24: 791482.5 | K24: 0 | L24: 791482.5 | M24: 2500 | N24: High Transaction; Recurring Transaction | O24: Yes | P24: EBANKWIB | Q24: 0 | R24: 1 | S24: 0 | T24: 0 | U24: 1 | V24: 0 | W24: 0 | X24: 0 | Y24: 0 | Z24: 0 | AA24: 46114 | AB24: =HYPERLINK("#'Transactions'!A28", "View Source Row")
A25: 28 | B25: 502 input.pdf | C25: 46113 | D25: 46142 | E25: 46114 | F25: 46114 | G25: DIGITA-MUMBAI/ ---------------------------------------------------------------------------------------------------------------------------------- Page Total: 7,98,282.50 8,34,458.50 38,676.00Cr ---------------------------------------------------------------------------------------------------------------------------------- Note: Cheques received in inward clearing will be considered for debiting/ returning on the basis opening balance in account Unless the constituent notifies the bank of any di | I25: Receipt | J25: 0 | K25: 36176 | L25: 36176 | M25: 38676 | N25: Recurring Transaction | O25: Yes | P25: PAGE TOTAL CR | Q25: 0 | R25: 1 | S25: 0 | T25: 0 | U25: 0 | V25: 0 | W25: 0 | X25: 0 | Y25: 0 | Z25: 0 | AA25: 46114 | AB25: =HYPERLINK("#'Transactions'!A29", "View Source Row")
A26: 29 | B26: 502 input.pdf | C26: 46113 | D26: 46142 | E26: 46114 | F26: 46114 | G26: DIGITA-MUMBAI/ NEFT-KKBKH26092921670-ATLAS COMMODITIES PRIVATE LI | I26: Receipt | J26: 0 | K26: 4353 | L26: 4353 | M26: 43029 | N26: Recurring Transaction | O26: Yes | P26: ATLAS COMMODITIES PRIVATE LI | Q26: 0 | R26: 1 | S26: 0 | T26: 0 | U26: 0 | V26: 0 | W26: 0 | X26: 0 | Y26: 0 | Z26: 0 | AA26: 46114 | AB26: =HYPERLINK("#'Transactions'!A30", "View Source Row")
A27: 30 | B27: 502 input.pdf | C27: 46113 | D27: 46142 | E27: 46115 | F27: 46115 | G27: DIGITA-MUMBAI/ NEFT-YESAP60934071902-PhonePe Limited | I27: Receipt | J27: 0 | K27: 173393.9 | L27: 173393.9 | M27: 216422.9 | N27: High Transaction; Recurring Transaction | O27: Yes | P27: PHONEPE LIMITED | Q27: 0 | R27: 1 | S27: 0 | T27: 0 | U27: 1 | V27: 0 | W27: 0 | X27: 0 | Y27: 0 | Z27: 0 | AA27: 46115 | AB27: =HYPERLINK("#'Transactions'!A31", "View Source Row")
A28: 31 | B28: 502 input.pdf | C28: 46113 | D28: 46142 | E28: 46115 | F28: 46115 | G28: DIGITA-MUMBAI/ NEFT-AXNPN09311160907-PHONEPE LIMITED-PAYMENT AGGR | I28: Receipt | J28: 0 | K28: 53957.68 | L28: 53957.68 | M28: 270380.58 | N28: Recurring Transaction | O28: Yes | P28: PHONEPE LIMITED | Q28: 0 | R28: 1 | S28: 0 | T28: 0 | U28: 0 | V28: 0 | W28: 0 | X28: 0 | Y28: 0 | Z28: 0 | AA28: 46115 | AB28: =HYPERLINK("#'Transactions'!A32", "View Source Row")
A29: 32 | B29: 502 input.pdf | C29: 46113 | D29: 46142 | E29: 46115 | F29: 46115 | G29: DIGITA-MUMBAI/ NEFT-AXISCN1300289999-ONE MOBIKWIK SYSTEMS LIMITED | I29: Receipt | J29: 0 | K29: 21700 | L29: 21700 | M29: 292080.58 | N29: Recurring Transaction | O29: Yes | P29: ONE MOBIKWIK SYSTEMS LIMITED | Q29: 0 | R29: 1 | S29: 0 | T29: 0 | U29: 0 | V29: 0 | W29: 0 | X29: 0 | Y29: 0 | Z29: 0 | AA29: 46115 | AB29: =HYPERLINK("#'Transactions'!A33", "View Source Row")
A30: 33 | B30: 502 input.pdf | C30: 46113 | D30: 46142 | E30: 46115 | F30: 46115 | G30: DIGITA-MUMBAI/ IMPS/P2A/609308206742/S TRANS 14851/Mh04ju3738I | I30: Receipt | J30: 0 | K30: 5750 | L30: 5750 | M30: 297830.58 | N30: Recurring Transaction | O30: Yes | P30: DIGITA-MUMBAI/ IMPS/P#A/#/S TRANS #/MH#JU#I | Q30: 0 | R30: 1 | S30: 0 | T30: 0 | U30: 0 | V30: 0 | W30: 0 | X30: 0 | Y30: 0 | Z30: 0 | AA30: 46115 | AB30: =HYPERLINK("#'Transactions'!A34", "View Source Row")
A31: 34 | B31: 502 input.pdf | C31: 46113 | D31: 46142 | E31: 46115 | F31: 46115 | G31: DIGITA-MUMBAI/ NEFT-AXISCN1300388689-PINE LABS PRIVATE LIMITED-NO | I31: Receipt | J31: 0 | K31: 112894 | L31: 112894 | M31: 410724.58 | N31: High Transaction; Recurring Transaction | O31: Yes | P31: PINE LABS PRIVATE LIMITED | Q31: 0 | R31: 1 | S31: 0 | T31: 0 | U31: 1 | V31: 0 | W31: 0 | X31: 0 | Y31: 0 | Z31: 0 | AA31: 46115 | AB31: =HYPERLINK("#'Transactions'!A35", "View Source Row")
A32: 35 | B32: 502 input.pdf | C32: 46113 | D32: 46142 | E32: 46115 | F32: 46115 | G32: DIGITA-MUMBAI/ IMPS/P2A/609312855509/AFZALSIRAJUDDIN/IMPSUOB9191 | I32: Receipt | J32: 0 | K32: 200000 | L32: 200000 | M32: 610724.58 | N32: High Transaction; Recurring Transaction | O32: Yes | P32: AFZALSIRAJUDDIN | Q32: 0 | R32: 1 | S32: 0 | T32: 0 | U32: 1 | V32: 0 | W32: 0 | X32: 0 | Y32: 0 | Z32: 0 | AA32: 46115 | AB32: =HYPERLINK("#'Transactions'!A36", "View Source Row")
A33: 37 | B33: 502 input.pdf | C33: 46113 | D33: 46142 | E33: 46115 | F33: 46115 | G33: EBANK:WIB/1502 EBANK:WIB/1502413595/Edfs | I33: Payment | J33: 790104.58 | K33: 0 | L33: 790104.58 | M33: 1500 | N33: High Transaction; Recurring Transaction | O33: Yes | P33: EBANKWIB | Q33: 0 | R33: 1 | S33: 0 | T33: 0 | U33: 1 | V33: 0 | W33: 0 | X33: 0 | Y33: 0 | Z33: 0 | AA33: 46115 | AB33: =HYPERLINK("#'Transactions'!A38", "View Source Row")
A34: 38 | B34: 502 input.pdf | C34: 46113 | D34: 46142 | E34: 46116 | F34: 46116 | G34: DIGITA-MUMBAI/ NEFT-YESAP60944128518-PhonePe Limited | I34: Receipt | J34: 0 | K34: 171014 | L34: 171014 | M34: 172514 | N34: High Transaction; Recurring Transaction | O34: Yes | P34: PHONEPE LIMITED | Q34: 0 | R34: 1 | S34: 0 | T34: 0 | U34: 1 | V34: 0 | W34: 0 | X34: 0 | Y34: 0 | Z34: 0 | AA34: 46116 | AB34: =HYPERLINK("#'Transactions'!A39", "View Source Row")
A35: 39 | B35: 502 input.pdf | C35: 46113 | D35: 46142 | E35: 46116 | F35: 46116 | G35: DIGITA-MUMBAI/ https://cbdrpt101.bankofbaroda.co.in:22000/finbranch/arjspmorph/INFENG/tran_rpt.jsp?... 04-05-2026 NEFT-AXNPN09418938602-PHONEPE LIMITED-PAYMENT AGGR | I35: Receipt | J35: 0 | K35: 49956 | L35: 49956 | M35: 222470 | N35: Recurring Transaction | O35: Yes | P35: CBDRPTBANKOFBARODACOIN | Q35: 0 | R35: 1 | S35: 0 | T35: 0 | U35: 0 | V35: 0 | W35: 0 | X35: 0 | Y35: 0 | Z35: 0 | AA35: 46116 | AB35: =HYPERLINK("#'Transactions'!A40", "View Source Row")
A36: 40 | B36: 502 input.pdf | C36: 46113 | D36: 46142 | E36: 46116 | F36: 46116 | G36: DIGITA-MUMBAI/ NEFT-AXISCN1301100257-ONE MOBIKWIK SYSTEMS LIMITED | I36: Receipt | J36: 0 | K36: 22121 | L36: 22121 | M36: 244591 | N36: Recurring Transaction | O36: Yes | P36: ONE MOBIKWIK SYSTEMS LIMITED | Q36: 0 | R36: 1 | S36: 0 | T36: 0 | U36: 0 | V36: 0 | W36: 0 | X36: 0 | Y36: 0 | Z36: 0 | AA36: 46116 | AB36: =HYPERLINK("#'Transactions'!A41", "View Source Row")
A37: 41 | B37: 502 input.pdf | C37: 46113 | D37: 46142 | E37: 46116 | F37: 46116 | G37: EBANK:WIB/1502 EBANK:WIB/1502423934/Edfs | I37: Payment | J37: 240091 | K37: 0 | L37: 240091 | M37: 4500 | N37: High Transaction; Recurring Transaction | O37: Yes | P37: EBANKWIB | Q37: 0 | R37: 1 | S37: 0 | T37: 0 | U37: 1 | V37: 0 | W37: 0 | X37: 0 | Y37: 0 | Z37: 0 | AA37: 46116 | AB37: =HYPERLINK("#'Transactions'!A42", "View Source Row")
A38: 42 | B38: 502 input.pdf | C38: 46113 | D38: 46142 | E38: 46116 | F38: 46116 | G38: DIGITA-MUMBAI/ NEFT-AXISCN1301297166-PINE LABS PRIVATE LIMITED-NO | I38: Receipt | J38: 0 | K38: 22400 | L38: 22400 | M38: 26900 | N38: Recurring Transaction | O38: Yes | P38: PINE LABS PRIVATE LIMITED | Q38: 0 | R38: 1 | S38: 0 | T38: 0 | U38: 0 | V38: 0 | W38: 0 | X38: 0 | Y38: 0 | Z38: 0 | AA38: 46116 | AB38: =HYPERLINK("#'Transactions'!A43", "View Source Row")
A39: 43 | B39: 502 input.pdf | C39: 46113 | D39: 46142 | E39: 46116 | F39: 46116 | G39: DIGITA-MUMBAI/ NEFT-HDFCH00909652553-KUNDAN QUARRY ---------------------------------------------------------------------------------------------------------------------------------- Page Total: 10,30,195.58 10,24,219.58 32,700.00Cr ---------------------------------------------------------------------------------------------------------------------------------- Note: Cheques received in inward clearing will be considered for debiting/ returning on the basis opening balance in account Unless the c | I39: Receipt | J39: 0 | K39: 5800 | L39: 5800 | M39: 32700 | N39: Recurring Transaction | O39: Yes | P39: KUNDAN QUARRY | Q39: 0 | R39: 1 | S39: 0 | T39: 0 | U39: 0 | V39: 0 | W39: 0 | X39: 0 | Y39: 0 | Z39: 0 | AA39: 46116 | AB39: =HYPERLINK("#'Transactions'!A44", "View Source Row")
A40: 45 | B40: 502 input.pdf | C40: 46113 | D40: 46142 | E40: 46116 | F40: 46116 | G40: DIGITA-MUMBAI/ NEFT-KKBKH26094919635-ATLAS COMMODITIES PRIVATE LI | I40: Receipt | J40: 0 | K40: 7885 | L40: 7885 | M40: 40434.37 | N40: Recurring Transaction | O40: Yes | P40: ATLAS COMMODITIES PRIVATE LI | Q40: 0 | R40: 1 | S40: 0 | T40: 0 | U40: 0 | V40: 0 | W40: 0 | X40: 0 | Y40: 0 | Z40: 0 | AA40: 46116 | AB40: =HYPERLINK("#'Transactions'!A46", "View Source Row")
A41: 47 | B41: 502 input.pdf | C41: 46113 | D41: 46142 | E41: 46116 | F41: 46116 | G41: EBANK:WIB/1502 EBANK:WIB/1502545632/Edfs | I41: Payment | J41: 120330.37 | K41: 0 | L41: 120330.37 | M41: 1500 | N41: High Transaction; Recurring Transaction | O41: Yes | P41: EBANKWIB | Q41: 0 | R41: 1 | S41: 0 | T41: 0 | U41: 1 | V41: 0 | W41: 0 | X41: 0 | Y41: 0 | Z41: 0 | AA41: 46116 | AB41: =HYPERLINK("#'Transactions'!A48", "View Source Row")
A42: 48 | B42: 502 input.pdf | C42: 46113 | D42: 46142 | E42: 46116 | F42: 46116 | G42: DIGITA-MUMBAI/ NEFT-HDFCH00911243518-KAVITA ENTERPRISES | I42: Receipt | J42: 0 | K42: 81396 | L42: 81396 | M42: 82896 | N42: Recurring Transaction | O42: Yes | P42: KAVITA ENTERPRISES | Q42: 0 | R42: 1 | S42: 0 | T42: 0 | U42: 0 | V42: 0 | W42: 0 | X42: 0 | Y42: 0 | Z42: 0 | AA42: 46116 | AB42: =HYPERLINK("#'Transactions'!A49", "View Source Row")
A43: 49 | B43: 502 input.pdf | C43: 46113 | D43: 46142 | E43: 46117 | F43: 46117 | G43: DIGITA-MUMBAI/ NEFT-YESAP60953903247-PhonePe Limited | I43: Receipt | J43: 0 | K43: 167015 | L43: 167015 | M43: 249911 | N43: High Transaction; Recurring Transaction | O43: Yes | P43: PHONEPE LIMITED | Q43: 0 | R43: 1 | S43: 0 | T43: 0 | U43: 1 | V43: 0 | W43: 0 | X43: 0 | Y43: 0 | Z43: 0 | AA43: 46117 | AB43: =HYPERLINK("#'Transactions'!A50", "View Source Row")
A44: 50 | B44: 502 input.pdf | C44: 46113 | D44: 46142 | E44: 46117 | F44: 46117 | G44: DIGITA-MUMBAI/ NEFT-AXNPN09528140899-PHONEPE LIMITED-PAYMENT AGGR | I44: Receipt | J44: 0 | K44: 67868.36 | L44: 67868.36 | M44: 317779.36 | N44: Recurring Transaction | O44: Yes | P44: PHONEPE LIMITED | Q44: 0 | R44: 1 | S44: 0 | T44: 0 | U44: 0 | V44: 0 | W44: 0 | X44: 0 | Y44: 0 | Z44: 0 | AA44: 46117 | AB44: =HYPERLINK("#'Transactions'!A51", "View Source Row")
A45: 51 | B45: 502 input.pdf | C45: 46113 | D45: 46142 | E45: 46117 | F45: 46117 | G45: DIGITA-MUMBAI/ NEFT-AXISCN1301923332-ONE MOBIKWIK SYSTEMS LIMITED | I45: Receipt | J45: 0 | K45: 28124 | L45: 28124 | M45: 345903.36 | N45: Recurring Transaction | O45: Yes | P45: ONE MOBIKWIK SYSTEMS LIMITED | Q45: 0 | R45: 1 | S45: 0 | T45: 0 | U45: 0 | V45: 0 | W45: 0 | X45: 0 | Y45: 0 | Z45: 0 | AA45: 46117 | AB45: =HYPERLINK("#'Transactions'!A52", "View Source Row")
A46: 52 | B46: 502 input.pdf | C46: 46113 | D46: 46142 | E46: 46117 | F46: 46117 | G46: EBANK:WIB/1502 EBANK:WIB/1502577386/Edfs | I46: Payment | J46: 300403.36 | K46: 0 | L46: 300403.36 | M46: 45500 | N46: High Transaction; Recurring Transaction | O46: Yes | P46: EBANKWIB | Q46: 0 | R46: 1 | S46: 0 | T46: 0 | U46: 1 | V46: 0 | W46: 0 | X46: 0 | Y46: 0 | Z46: 0 | AA46: 46117 | AB46: =HYPERLINK("#'Transactions'!A53", "View Source Row")
A47: 53 | B47: 502 input.pdf | C47: 46113 | D47: 46142 | E47: 46117 | F47: 46117 | G47: DIGITA-MUMBAI/ IMPS/P2A/609509137308/SHREE GANESH EN/diselVVS910 | I47: Receipt | J47: 0 | K47: 63308 | L47: 63308 | M47: 108808 | N47: Recurring Transaction | O47: Yes | P47: SHREE GANESH EN | Q47: 0 | R47: 1 | S47: 0 | T47: 0 | U47: 0 | V47: 0 | W47: 0 | X47: 0 | Y47: 0 | Z47: 0 | AA47: 46117 | AB47: =HYPERLINK("#'Transactions'!A54", "View Source Row")
A48: 54 | B48: 502 input.pdf | C48: 46113 | D48: 46142 | E48: 46118 | F48: 46118 | G48: DIGITA-MUMBAI/ NEFT-AXNPN09635263353-PHONEPE LIMITED-PAYMENT AGGR | I48: Receipt | J48: 0 | K48: 58335.21 | L48: 58335.21 | M48: 167143.21 | N48: Recurring Transaction | O48: Yes | P48: PHONEPE LIMITED | Q48: 0 | R48: 1 | S48: 0 | T48: 0 | U48: 0 | V48: 0 | W48: 0 | X48: 0 | Y48: 0 | Z48: 0 | AA48: 46118 | AB48: =HYPERLINK("#'Transactions'!A55", "View Source Row")
A49: 55 | B49: 502 input.pdf | C49: 46113 | D49: 46142 | E49: 46118 | F49: 46118 | G49: DIGITA-MUMBAI/ NEFT-YESAP60964000643-PhonePe Limited | I49: Receipt | J49: 0 | K49: 169456 | L49: 169456 | M49: 336599.21 | N49: High Transaction; Recurring Transaction | O49: Yes | P49: PHONEPE LIMITED | Q49: 0 | R49: 1 | S49: 0 | T49: 0 | U49: 1 | V49: 0 | W49: 0 | X49: 0 | Y49: 0 | Z49: 0 | AA49: 46118 | AB49: =HYPERLINK("#'Transactions'!A56", "View Source Row")
A50: 56 | B50: 502 input.pdf | C50: 46113 | D50: 46142 | E50: 46118 | F50: 46118 | G50: DIGITA-MUMBAI/ NEFT-AXISCN1302642509-ONE MOBIKWIK SYSTEMS LIMITED | I50: Receipt | J50: 0 | K50: 31681 | L50: 31681 | M50: 368280.21 | N50: Recurring Transaction | O50: Yes | P50: ONE MOBIKWIK SYSTEMS LIMITED | Q50: 0 | R50: 1 | S50: 0 | T50: 0 | U50: 0 | V50: 0 | W50: 0 | X50: 0 | Y50: 0 | Z50: 0 | AA50: 46118 | AB50: =HYPERLINK("#'Transactions'!A57", "View Source Row")
A51: 57 | B51: 502 input.pdf | C51: 46113 | D51: 46142 | E51: 46118 | F51: 46118 | G51: EBANK:WIB/1502 EBANK:WIB/1502642025/Edfs | I51: Payment | J51: 365780.21 | K51: 0 | L51: 365780.21 | M51: 2500 | N51: High Transaction; Recurring Transaction | O51: Yes | P51: EBANKWIB | Q51: 0 | R51: 1 | S51: 0 | T51: 0 | U51: 1 | V51: 0 | W51: 0 | X51: 0 | Y51: 0 | Z51: 0 | AA51: 46118 | AB51: =HYPERLINK("#'Transactions'!A58", "View Source Row")
A52: 58 | B52: 502 input.pdf | C52: 46113 | D52: 46142 | E52: 46118 | F52: 46118 | G52: DIGITA-MUMBAI/ NEFT-AXISCN1302721272-PINE LABS PRIVATE LIMITED-NO | I52: Receipt | J52: 0 | K52: 29516 | L52: 29516 | M52: 32016 | N52: Recurring Transaction | O52: Yes | P52: PINE LABS PRIVATE LIMITED | Q52: 0 | R52: 1 | S52: 0 | T52: 0 | U52: 0 | V52: 0 | W52: 0 | X52: 0 | Y52: 0 | Z52: 0 | AA52: 46118 | AB52: =HYPERLINK("#'Transactions'!A59", "View Source Row")
A53: 59 | B53: 502 input.pdf | C53: 46113 | D53: 46142 | E53: 46118 | F53: 46118 | G53: DIGITA-MUMBAI/ ---------------------------------------------------------------------------------------------------------------------------------- Page Total: 7,86,664.57 8,85,980.57 1,32,016.00Cr ---------------------------------------------------------------------------------------------------------------------------------- Note: Cheques received in inward clearing will be considered for debiting/ returning on the basis opening balance in account Unless the constituent notifies the bank of any | I53: Receipt | J53: 0 | K53: 100000 | L53: 100000 | M53: 132016 | N53: High Transaction; Recurring Transaction | O53: Yes | P53: PAGE TOTAL CR | Q53: 0 | R53: 1 | S53: 0 | T53: 0 | U53: 1 | V53: 0 | W53: 0 | X53: 0 | Y53: 0 | Z53: 0 | AA53: 46118 | AB53: =HYPERLINK("#'Transactions'!A60", "View Source Row")
A54: 60 | B54: 502 input.pdf | C54: 46113 | D54: 46142 | E54: 46118 | F54: 46118 | G54: DIGITA-MUMBAI/ NEFT-AXISCN1302925515-PINE LABS PRIVATE LIMITED-NO | I54: Receipt | J54: 0 | K54: 14073 | L54: 14073 | M54: 146089 | N54: Recurring Transaction | O54: Yes | P54: PINE LABS PRIVATE LIMITED | Q54: 0 | R54: 1 | S54: 0 | T54: 0 | U54: 0 | V54: 0 | W54: 0 | X54: 0 | Y54: 0 | Z54: 0 | AA54: 46118 | AB54: =HYPERLINK("#'Transactions'!A61", "View Source Row")
A55: 62 | B55: 502 input.pdf | C55: 46113 | D55: 46142 | E55: 46118 | F55: 46118 | G55: DIGITA-MUMBAI/ NEFT-HDFCH00913518284-CORPAK | I55: Receipt | J55: 0 | K55: 38524 | L55: 38524 | M55: 185613 | N55: Recurring Transaction | O55: Yes | P55: DIGITA-MUMBAI/ NEFT-HDFCH#-CORPAK | Q55: 0 | R55: 1 | S55: 0 | T55: 0 | U55: 0 | V55: 0 | W55: 0 | X55: 0 | Y55: 0 | Z55: 0 | AA55: 46118 | AB55: =HYPERLINK("#'Transactions'!A63", "View Source Row")
A56: 63 | B56: 502 input.pdf | C56: 46113 | D56: 46142 | E56: 46118 | F56: 46118 | G56: DIGITA-MUMBAI/ NEFT-NKGSH26096901712-GEBI PRODUCTS PRIVATE LIMITE | I56: Receipt | J56: 0 | K56: 15001 | L56: 15001 | M56: 200614 | N56: Recurring Transaction | O56: Yes | P56: GEBI PRODUCTS PRIVATE LIMITE | Q56: 0 | R56: 1 | S56: 0 | T56: 0 | U56: 0 | V56: 0 | W56: 0 | X56: 0 | Y56: 0 | Z56: 0 | AA56: 46118 | AB56: =HYPERLINK("#'Transactions'!A64", "View Source Row")
A57: 64 | B57: 502 input.pdf | C57: 46113 | D57: 46142 | E57: 46118 | F57: 46118 | G57: EBANK:WIB/1502 EBANK:WIB/1502790855/Edfs | I57: Payment | J57: 198114 | K57: 0 | L57: 198114 | M57: 2500 | N57: High Transaction; Recurring Transaction | O57: Yes | P57: EBANKWIB | Q57: 0 | R57: 1 | S57: 0 | T57: 0 | U57: 1 | V57: 0 | W57: 0 | X57: 0 | Y57: 0 | Z57: 0 | AA57: 46118 | AB57: =HYPERLINK("#'Transactions'!A65", "View Source Row")
A58: 65 | B58: 502 input.pdf | C58: 46113 | D58: 46142 | E58: 46118 | F58: 46118 | G58: DIGITA-MUMBAI/ NEFT-HDFCH00915259780-MOHANJI BHARAT WELFARE FOUND | I58: Receipt | J58: 0 | K58: 18448 | L58: 18448 | M58: 20948 | N58: Recurring Transaction | O58: Yes | P58: MOHANJI BHARAT WELFARE FOUND | Q58: 0 | R58: 1 | S58: 0 | T58: 0 | U58: 0 | V58: 0 | W58: 0 | X58: 0 | Y58: 0 | Z58: 0 | AA58: 46118 | AB58: =HYPERLINK("#'Transactions'!A66", "View Source Row")
A59: 66 | B59: 502 input.pdf | C59: 46113 | D59: 46142 | E59: 46119 | F59: 46119 | G59: DIGITA-MUMBAI/ NEFT-YESAP60974165954-PhonePe Limited | I59: Receipt | J59: 0 | K59: 260044.42 | L59: 260044.42 | M59: 280992.42 | N59: High Transaction; Recurring Transaction | O59: Yes | P59: PHONEPE LIMITED | Q59: 0 | R59: 1 | S59: 0 | T59: 0 | U59: 1 | V59: 0 | W59: 0 | X59: 0 | Y59: 0 | Z59: 0 | AA59: 46119 | AB59: =HYPERLINK("#'Transactions'!A67", "View Source Row")
A60: 67 | B60: 502 input.pdf | C60: 46113 | D60: 46142 | E60: 46119 | F60: 46119 | G60: DIGITA-MUMBAI/ NEFT-AXNPN09743969962-PHONEPE LIMITED-PAYMENT AGGR | I60: Receipt | J60: 0 | K60: 55000.65 | L60: 55000.65 | M60: 335993.07 | N60: Recurring Transaction | O60: Yes | P60: PHONEPE LIMITED | Q60: 0 | R60: 1 | S60: 0 | T60: 0 | U60: 0 | V60: 0 | W60: 0 | X60: 0 | Y60: 0 | Z60: 0 | AA60: 46119 | AB60: =HYPERLINK("#'Transactions'!A68", "View Source Row")
A61: 68 | B61: 502 input.pdf | C61: 46113 | D61: 46142 | E61: 46119 | F61: 46119 | G61: EBANK:WIB/1502 EBANK:WIB/1502821939/Edfs | I61: Payment | J61: 330493.07 | K61: 0 | L61: 330493.07 | M61: 5500 | N61: High Transaction; Recurring Transaction | O61: Yes | P61: EBANKWIB | Q61: 0 | R61: 1 | S61: 0 | T61: 0 | U61: 1 | V61: 0 | W61: 0 | X61: 0 | Y61: 0 | Z61: 0 | AA61: 46119 | AB61: =HYPERLINK("#'Transactions'!A69", "View Source Row")
A62: 69 | B62: 502 input.pdf | C62: 46113 | D62: 46142 | E62: 46119 | F62: 46119 | G62: UPI/8639137766 13776666 UPI/863913776666/06:48:44/UPI/surajdhanotra1@ibl/ | I62: Receipt | J62: 0 | K62: 9000 | L62: 9000 | M62: 14500 | N62: UPI; Recurring Transaction | O62: Yes | P62: SURAJDHANOTRAIBL | Q62: 0 | R62: 1 | S62: 0 | T62: 0 | U62: 0 | V62: 1 | W62: 0 | X62: 0 | Y62: 0 | Z62: 0 | AA62: 46119 | AB62: =HYPERLINK("#'Transactions'!A70", "View Source Row")
A63: 70 | B63: 502 input.pdf | C63: 46113 | D63: 46142 | E63: 46119 | F63: 46119 | G63: DIGITA-MUMBAI/ NEFT-AXISCN1303901852-ONE MOBIKWIK SYSTEMS LIMITED | I63: Receipt | J63: 0 | K63: 23072 | L63: 23072 | M63: 37572 | N63: Recurring Transaction | O63: Yes | P63: ONE MOBIKWIK SYSTEMS LIMITED | Q63: 0 | R63: 1 | S63: 0 | T63: 0 | U63: 0 | V63: 0 | W63: 0 | X63: 0 | Y63: 0 | Z63: 0 | AA63: 46119 | AB63: =HYPERLINK("#'Transactions'!A71", "View Source Row")
A64: 71 | B64: 502 input.pdf | C64: 46113 | D64: 46142 | E64: 46119 | F64: 46119 | G64: DIGITA-MUMBAI/ NEFT-AXISCN1303985526-PINE LABS PRIVATE LIMITED-NO | I64: Receipt | J64: 0 | K64: 25110 | L64: 25110 | M64: 62682 | N64: Recurring Transaction | O64: Yes | P64: PINE LABS PRIVATE LIMITED | Q64: 0 | R64: 1 | S64: 0 | T64: 0 | U64: 0 | V64: 0 | W64: 0 | X64: 0 | Y64: 0 | Z64: 0 | AA64: 46119 | AB64: =HYPERLINK("#'Transactions'!A72", "View Source Row")
A65: 72 | B65: 502 input.pdf | C65: 46113 | D65: 46142 | E65: 46119 | F65: 46119 | G65: Charges for Charges for PORD Customer Payment :003566909942 | I65: Payment | J65: 2.65 | K65: 0 | L65: 2.65 | M65: 62679.35 | N65: Recurring Transaction | O65: Yes | P65: CHARGES FOR CHARGES FOR PORD CUSTOMER PA | Q65: 0 | R65: 1 | S65: 0 | T65: 0 | U65: 0 | V65: 0 | W65: 0 | X65: 0 | Y65: 0 | Z65: 0 | AA65: 46119 | AB65: =HYPERLINK("#'Transactions'!A73", "View Source Row")
A66: 74 | B66: 502 input.pdf | C66: 46113 | D66: 46142 | E66: 46119 | F66: 46119 | G66: DIGITA-MUMBAI/ NEFT-HDFCH00916196159-MARK LUBES PRIVATE LIMITED | I66: Receipt | J66: 0 | K66: 3617 | L66: 3617 | M66: 62296.35 | N66: Recurring Transaction | O66: Yes | P66: MARK LUBES PRIVATE LIMITED | Q66: 0 | R66: 1 | S66: 0 | T66: 0 | U66: 0 | V66: 0 | W66: 0 | X66: 0 | Y66: 0 | Z66: 0 | AA66: 46119 | AB66: =HYPERLINK("#'Transactions'!A75", "View Source Row")
A67: 75 | B67: 502 input.pdf | C67: 46113 | D67: 46142 | E67: 46119 | F67: 46119 | G67: BY CASH ---------------------------------------------------------------------------------------------------------------------------------- Page Total: 5,32,609.72 5,77,390.07 1,76,796.35Cr ---------------------------------------------------------------------------------------------------------------------------------- Note: Cheques received in inward clearing will be considered for debiting/ returning on the basis opening balance in account Unless the constituent notifies the bank of any discrep | I67: Receipt | J67: 0 | K67: 114500 | L67: 114500 | M67: 176796.35 | N67: Cash; High Transaction; Recurring Transaction | O67: Yes | P67: PAGE TOTAL CR | Q67: 1 | R67: 1 | S67: 0 | T67: 0 | U67: 1 | V67: 0 | W67: 0 | X67: 0 | Y67: 0 | Z67: 0 | AA67: 46119 | AB67: =HYPERLINK("#'Transactions'!A76", "View Source Row")
A68: 78 | B68: 502 input.pdf | C68: 46113 | D68: 46142 | E68: 46119 | F68: 46119 | G68: DIGITA-MUMBAI/ NEFT-KKBKH26097664663-ATLAS COMMODITIES PRIVATE LI | I68: Receipt | J68: 0 | K68: 3405 | L68: 3405 | M68: 80664.35 | N68: Recurring Transaction | O68: Yes | P68: ATLAS COMMODITIES PRIVATE LI | Q68: 0 | R68: 1 | S68: 0 | T68: 0 | U68: 0 | V68: 0 | W68: 0 | X68: 0 | Y68: 0 | Z68: 0 | AA68: 46119 | AB68: =HYPERLINK("#'Transactions'!A79", "View Source Row")
A69: 79 | B69: 502 input.pdf | C69: 46113 | D69: 46142 | E69: 46119 | F69: 46119 | G69: DIGITA-MUMBAI/ https://cbdrpt101.bankofbaroda.co.in:22000/finbranch/arjspmorph/INFENG/tran_rpt.jsp?... 04-05-2026 NEFT-NKGSH26097920270-GEBI PRODUCTS PRIVATE LIMITE | I69: Receipt | J69: 0 | K69: 2618 | L69: 2618 | M69: 83282.35 | N69: Recurring Transaction | O69: Yes | P69: CBDRPTBANKOFBARODACOIN | Q69: 0 | R69: 1 | S69: 0 | T69: 0 | U69: 0 | V69: 0 | W69: 0 | X69: 0 | Y69: 0 | Z69: 0 | AA69: 46119 | AB69: =HYPERLINK("#'Transactions'!A80", "View Source Row")
A70: 80 | B70: 502 input.pdf | C70: 46113 | D70: 46142 | E70: 46119 | F70: 46119 | G70: DIGITA-MUMBAI/ NEFT-HDFCH00917822677-SL CORBOX PRIVATE LIMITED | I70: Receipt | J70: 0 | K70: 56800 | L70: 56800 | M70: 140082.35 | N70: Recurring Transaction | O70: Yes | P70: SL CORBOX PRIVATE LIMITED | Q70: 0 | R70: 1 | S70: 0 | T70: 0 | U70: 0 | V70: 0 | W70: 0 | X70: 0 | Y70: 0 | Z70: 0 | AA70: 46119 | AB70: =HYPERLINK("#'Transactions'!A81", "View Source Row")
A71: 81 | B71: 502 input.pdf | C71: 46113 | D71: 46142 | E71: 46119 | F71: 46119 | G71: EBANK:WIB/1502 EBANK:WIB/1502986421/Edfs | I71: Payment | J71: 137582.35 | K71: 0 | L71: 137582.35 | M71: 2500 | N71: High Transaction; Recurring Transaction | O71: Yes | P71: EBANKWIB | Q71: 0 | R71: 1 | S71: 0 | T71: 0 | U71: 1 | V71: 0 | W71: 0 | X71: 0 | Y71: 0 | Z71: 0 | AA71: 46119 | AB71: =HYPERLINK("#'Transactions'!A82", "View Source Row")
A72: 82 | B72: 502 input.pdf | C72: 46113 | D72: 46142 | E72: 46119 | F72: 46119 | G72: DIGITA-MUMBAI/ NEFT-IN42609750724469-VINAYAK OIL INDUSTRIES | I72: Receipt | J72: 0 | K72: 37413 | L72: 37413 | M72: 39913 | N72: Recurring Transaction | O72: Yes | P72: VINAYAK OIL INDUSTRIES | Q72: 0 | R72: 1 | S72: 0 | T72: 0 | U72: 0 | V72: 0 | W72: 0 | X72: 0 | Y72: 0 | Z72: 0 | AA72: 46119 | AB72: =HYPERLINK("#'Transactions'!A83", "View Source Row")
A73: 83 | B73: 502 input.pdf | C73: 46113 | D73: 46142 | E73: 46120 | F73: 46120 | G73: DIGITA-MUMBAI/ NEFT-YESAP60983679319-PhonePe Limited | I73: Receipt | J73: 0 | K73: 243684 | L73: 243684 | M73: 283597 | N73: High Transaction; Recurring Transaction | O73: Yes | P73: PHONEPE LIMITED | Q73: 0 | R73: 1 | S73: 0 | T73: 0 | U73: 1 | V73: 0 | W73: 0 | X73: 0 | Y73: 0 | Z73: 0 | AA73: 46120 | AB73: =HYPERLINK("#'Transactions'!A84", "View Source Row")
A74: 85 | B74: 502 input.pdf | C74: 46113 | D74: 46142 | E74: 46120 | F74: 46120 | G74: DIGITA-MUMBAI/ NEFT-AXNPN09852795681-PHONEPE LIMITED-PAYMENT AGGR | I74: Receipt | J74: 0 | K74: 47737 | L74: 47737 | M74: 294249 | N74: Recurring Transaction | O74: Yes | P74: PHONEPE LIMITED | Q74: 0 | R74: 1 | S74: 0 | T74: 0 | U74: 0 | V74: 0 | W74: 0 | X74: 0 | Y74: 0 | Z74: 0 | AA74: 46120 | AB74: =HYPERLINK("#'Transactions'!A86", "View Source Row")
A75: 87 | B75: 502 input.pdf | C75: 46113 | D75: 46142 | E75: 46120 | F75: 46120 | G75: DIGITA-MUMBAI/ NEFT-AXISCN1305078531-ONE MOBIKWIK SYSTEMS LIMITED | I75: Receipt | J75: 0 | K75: 13338 | L75: 13338 | M75: 307563 | N75: Recurring Transaction | O75: Yes | P75: ONE MOBIKWIK SYSTEMS LIMITED | Q75: 0 | R75: 1 | S75: 0 | T75: 0 | U75: 0 | V75: 0 | W75: 0 | X75: 0 | Y75: 0 | Z75: 0 | AA75: 46120 | AB75: =HYPERLINK("#'Transactions'!A88", "View Source Row")
A76: 88 | B76: 502 input.pdf | C76: 46113 | D76: 46142 | E76: 46120 | F76: 46120 | G76: DIGITA-MUMBAI/ NEFT-AXISCN1305183876-PINE LABS PRIVATE LIMITED-NO | I76: Receipt | J76: 0 | K76: 76050 | L76: 76050 | M76: 383613 | N76: Recurring Transaction | O76: Yes | P76: PINE LABS PRIVATE LIMITED | Q76: 0 | R76: 1 | S76: 0 | T76: 0 | U76: 0 | V76: 0 | W76: 0 | X76: 0 | Y76: 0 | Z76: 0 | AA76: 46120 | AB76: =HYPERLINK("#'Transactions'!A89", "View Source Row")
A77: 89 | B77: 502 input.pdf | C77: 46113 | D77: 46142 | E77: 46120 | F77: 46120 | G77: EBANK:WIB/1503 EBANK:WIB/1503050809/Edfs | I77: Payment | J77: 381113 | K77: 0 | L77: 381113 | M77: 2500 | N77: High Transaction; Recurring Transaction | O77: Yes | P77: EBANKWIB | Q77: 0 | R77: 1 | S77: 0 | T77: 0 | U77: 1 | V77: 0 | W77: 0 | X77: 0 | Y77: 0 | Z77: 0 | AA77: 46120 | AB77: =HYPERLINK("#'Transactions'!A90", "View Source Row")
A78: 90 | B78: 502 input.pdf | C78: 46113 | D78: 46142 | E78: 46120 | F78: 46120 | G78: DIGITA-MUMBAI/ IMPS/P2A/609812907682/OMSANITRANSPORT/Diesel Bill | I78: Receipt | J78: 0 | K78: 40356 | L78: 40356 | M78: 42856 | N78: Recurring Transaction | O78: Yes | P78: OMSANITRANSPORT | Q78: 0 | R78: 1 | S78: 0 | T78: 0 | U78: 0 | V78: 0 | W78: 0 | X78: 0 | Y78: 0 | Z78: 0 | AA78: 46120 | AB78: =HYPERLINK("#'Transactions'!A91", "View Source Row")
A79: 91 | B79: 502 input.pdf | C79: 46113 | D79: 46142 | E79: 46120 | F79: 46120 | G79: DIGITA-MUMBAI/ ---------------------------------------------------------------------------------------------------------------------------------- Page Total: 6,55,341.35 5,23,307.00 44,762.00Cr ---------------------------------------------------------------------------------------------------------------------------------- Note: Cheques received in inward clearing will be considered for debiting/ returning on the basis opening balance in account Unless the constituent notifies the bank of any di | I79: Receipt | J79: 0 | K79: 1906 | L79: 1906 | M79: 44762 | N79: Recurring Transaction | O79: Yes | P79: PAGE TOTAL CR | Q79: 0 | R79: 1 | S79: 0 | T79: 0 | U79: 0 | V79: 0 | W79: 0 | X79: 0 | Y79: 0 | Z79: 0 | AA79: 46120 | AB79: =HYPERLINK("#'Transactions'!A92", "View Source Row")
A80: 92 | B80: 502 input.pdf | C80: 46113 | D80: 46142 | E80: 46120 | F80: 46120 | G80: DIGITA-MUMBAI/ NEFT-IDIBH09837346562-JAI AMBE TRANSPORT | I80: Receipt | J80: 0 | K80: 3050 | L80: 3050 | M80: 47812 | N80: Recurring Transaction | O80: Yes | P80: JAI AMBE TRANSPORT | Q80: 0 | R80: 1 | S80: 0 | T80: 0 | U80: 0 | V80: 0 | W80: 0 | X80: 0 | Y80: 0 | Z80: 0 | AA80: 46120 | AB80: =HYPERLINK("#'Transactions'!A93", "View Source Row")
A81: 93 | B81: 502 input.pdf | C81: 46113 | D81: 46142 | E81: 46120 | F81: 46120 | G81: DIGITA-MUMBAI/ IMPS/P2A/609818576145/SHREE GANESH EN/diselVVS910 | I81: Receipt | J81: 0 | K81: 63308 | L81: 63308 | M81: 111120 | N81: Recurring Transaction | O81: Yes | P81: SHREE GANESH EN | Q81: 0 | R81: 1 | S81: 0 | T81: 0 | U81: 0 | V81: 0 | W81: 0 | X81: 0 | Y81: 0 | Z81: 0 | AA81: 46120 | AB81: =HYPERLINK("#'Transactions'!A94", "View Source Row")
A82: 94 | B82: 502 input.pdf | C82: 46113 | D82: 46142 | E82: 46120 | F82: 46120 | G82: EBANK:WIB/1503 EBANK:WIB/1503170712/Edfs | I82: Payment | J82: 108620 | K82: 0 | L82: 108620 | M82: 2500 | N82: High Transaction; Recurring Transaction | O82: Yes | P82: EBANKWIB | Q82: 0 | R82: 1 | S82: 0 | T82: 0 | U82: 1 | V82: 0 | W82: 0 | X82: 0 | Y82: 0 | Z82: 0 | AA82: 46120 | AB82: =HYPERLINK("#'Transactions'!A95", "View Source Row")
A83: 95 | B83: 502 input.pdf | C83: 46113 | D83: 46142 | E83: 46121 | F83: 46121 | G83: DIGITA-MUMBAI/ NEFT-YESAP60993677587-PhonePe Limited | I83: Receipt | J83: 0 | K83: 170522 | L83: 170522 | M83: 173022 | N83: High Transaction; Recurring Transaction | O83: Yes | P83: PHONEPE LIMITED | Q83: 0 | R83: 1 | S83: 0 | T83: 0 | U83: 1 | V83: 0 | W83: 0 | X83: 0 | Y83: 0 | Z83: 0 | AA83: 46121 | AB83: =HYPERLINK("#'Transactions'!A96", "View Source Row")
A84: 96 | B84: 502 input.pdf | C84: 46113 | D84: 46142 | E84: 46121 | F84: 46121 | G84: DIGITA-MUMBAI/ NEFT-AXNPN09961131765-PHONEPE LIMITED-PAYMENT AGGR | I84: Receipt | J84: 0 | K84: 49090 | L84: 49090 | M84: 222112 | N84: Recurring Transaction | O84: Yes | P84: PHONEPE LIMITED | Q84: 0 | R84: 1 | S84: 0 | T84: 0 | U84: 0 | V84: 0 | W84: 0 | X84: 0 | Y84: 0 | Z84: 0 | AA84: 46121 | AB84: =HYPERLINK("#'Transactions'!A97", "View Source Row")
A85: 97 | B85: 502 input.pdf | C85: 46113 | D85: 46142 | E85: 46121 | F85: 46121 | G85: DIGITA-MUMBAI/ NEFT-AXISCN1306324510-ONE MOBIKWIK SYSTEMS LIMITED | I85: Receipt | J85: 0 | K85: 15270 | L85: 15270 | M85: 237382 | N85: Recurring Transaction | O85: Yes | P85: ONE MOBIKWIK SYSTEMS LIMITED | Q85: 0 | R85: 1 | S85: 0 | T85: 0 | U85: 0 | V85: 0 | W85: 0 | X85: 0 | Y85: 0 | Z85: 0 | AA85: 46121 | AB85: =HYPERLINK("#'Transactions'!A98", "View Source Row")
A86: 98 | B86: 502 input.pdf | C86: 46113 | D86: 46142 | E86: 46121 | F86: 46121 | G86: DIGITA-MUMBAI/ NEFT-AXISCN1306426056-PINE LABS PRIVATE LIMITED-NO | I86: Receipt | J86: 0 | K86: 87897 | L86: 87897 | M86: 325279 | N86: Recurring Transaction | O86: Yes | P86: PINE LABS PRIVATE LIMITED | Q86: 0 | R86: 1 | S86: 0 | T86: 0 | U86: 0 | V86: 0 | W86: 0 | X86: 0 | Y86: 0 | Z86: 0 | AA86: 46121 | AB86: =HYPERLINK("#'Transactions'!A99", "View Source Row")
A87: 99 | B87: 502 input.pdf | C87: 46113 | D87: 46142 | E87: 46121 | F87: 46121 | G87: DIGITA-MUMBAI/ NEFT-KKBKH26099766302-VENKTESHWAR INDUSTRIAL CORPO | I87: Receipt | J87: 0 | K87: 10000 | L87: 10000 | M87: 335279 | N87: Recurring Transaction | O87: Yes | P87: VENKTESHWAR INDUSTRIAL CORPO | Q87: 0 | R87: 1 | S87: 0 | T87: 0 | U87: 0 | V87: 0 | W87: 0 | X87: 0 | Y87: 0 | Z87: 0 | AA87: 46121 | AB87: =HYPERLINK("#'Transactions'!A100", "View Source Row")
A88: 100 | B88: 502 input.pdf | C88: 46113 | D88: 46142 | E88: 46121 | F88: 46121 | G88: DIGITA-MUMBAI/ NEFT-NKGSH26099959094-GEBI PRODUCTS PRIVATE LIMITE | I88: Receipt | J88: 0 | K88: 2598 | L88: 2598 | M88: 337877 | N88: Recurring Transaction | O88: Yes | P88: GEBI PRODUCTS PRIVATE LIMITE | Q88: 0 | R88: 1 | S88: 0 | T88: 0 | U88: 0 | V88: 0 | W88: 0 | X88: 0 | Y88: 0 | Z88: 0 | AA88: 46121 | AB88: =HYPERLINK("#'Transactions'!A101", "View Source Row")
A89: 101 | B89: 502 input.pdf | C89: 46113 | D89: 46142 | E89: 46121 | F89: 46121 | G89: DIGITA-MUMBAI/ IMPS/P2A/609918190676/VAKAS TEMPO SER/IMPSCNB9199 | I89: Receipt | J89: 0 | K89: 44741 | L89: 44741 | M89: 382618 | N89: Recurring Transaction | O89: Yes | P89: VAKAS TEMPO SER | Q89: 0 | R89: 1 | S89: 0 | T89: 0 | U89: 0 | V89: 0 | W89: 0 | X89: 0 | Y89: 0 | Z89: 0 | AA89: 46121 | AB89: =HYPERLINK("#'Transactions'!A102", "View Source Row")
A90: 102 | B90: 502 input.pdf | C90: 46113 | D90: 46142 | E90: 46121 | F90: 46121 | G90: EBANK:WIB/1503 EBANK:WIB/1503311707/Edfs | I90: Payment | J90: 380118 | K90: 0 | L90: 380118 | M90: 2500 | N90: High Transaction; Recurring Transaction | O90: Yes | P90: EBANKWIB | Q90: 0 | R90: 1 | S90: 0 | T90: 0 | U90: 1 | V90: 0 | W90: 0 | X90: 0 | Y90: 0 | Z90: 0 | AA90: 46121 | AB90: =HYPERLINK("#'Transactions'!A103", "View Source Row")
A91: 103 | B91: 502 input.pdf | C91: 46113 | D91: 46142 | E91: 46121 | F91: 46121 | G91: DIGITA-MUMBAI/ https://cbdrpt101.bankofbaroda.co.in:22000/finbranch/arjspmorph/INFENG/tran_rpt.jsp?... 04-05-2026 NEFT-HDFCH00925247332-KAVITA ENTERPRISES | I91: Receipt | J91: 0 | K91: 63308 | L91: 63308 | M91: 65808 | N91: Recurring Transaction | O91: Yes | P91: CBDRPTBANKOFBARODACOIN | Q91: 0 | R91: 1 | S91: 0 | T91: 0 | U91: 0 | V91: 0 | W91: 0 | X91: 0 | Y91: 0 | Z91: 0 | AA91: 46121 | AB91: =HYPERLINK("#'Transactions'!A104", "View Source Row")
A92: 104 | B92: 502 input.pdf | C92: 46113 | D92: 46142 | E92: 46122 | F92: 46122 | G92: DIGITA-MUMBAI/ NEFT-YESAP61002547485-PhonePe Limited | I92: Receipt | J92: 0 | K92: 310276 | L92: 310276 | M92: 376084 | N92: High Transaction; Recurring Transaction | O92: Yes | P92: PHONEPE LIMITED | Q92: 0 | R92: 1 | S92: 0 | T92: 0 | U92: 1 | V92: 0 | W92: 0 | X92: 0 | Y92: 0 | Z92: 0 | AA92: 46122 | AB92: =HYPERLINK("#'Transactions'!A105", "View Source Row")
A93: 105 | B93: 502 input.pdf | C93: 46113 | D93: 46142 | E93: 46122 | F93: 46122 | G93: DIGITA-MUMBAI/ NEFT-AXNPN10069579474-PHONEPE LIMITED-PAYMENT AGGR | I93: Receipt | J93: 0 | K93: 59415 | L93: 59415 | M93: 435499 | N93: Recurring Transaction | O93: Yes | P93: PHONEPE LIMITED | Q93: 0 | R93: 1 | S93: 0 | T93: 0 | U93: 0 | V93: 0 | W93: 0 | X93: 0 | Y93: 0 | Z93: 0 | AA93: 46122 | AB93: =HYPERLINK("#'Transactions'!A106", "View Source Row")
A94: 106 | B94: 502 input.pdf | C94: 46113 | D94: 46142 | E94: 46122 | F94: 46122 | G94: EBANK:WIB/1503 EBANK:WIB/1503339201/Edfs ---------------------------------------------------------------------------------------------------------------------------------- Page Total: 9,21,737.00 8,79,475.00 2,500.00Cr ---------------------------------------------------------------------------------------------------------------------------------- Note: Cheques received in inward clearing will be considered for debiting/ returning on the basis opening balance in account Unless the constituent no | I94: Payment | J94: 432999 | K94: 0 | L94: 432999 | M94: 2500 | N94: High Transaction; Recurring Transaction | O94: Yes | P94: EBANKWIB | Q94: 0 | R94: 1 | S94: 0 | T94: 0 | U94: 1 | V94: 0 | W94: 0 | X94: 0 | Y94: 0 | Z94: 0 | AA94: 46122 | AB94: =HYPERLINK("#'Transactions'!A107", "View Source Row")
A95: 107 | B95: 502 input.pdf | C95: 46113 | D95: 46142 | E95: 46122 | F95: 46122 | G95: DIGITA-MUMBAI/ NEFT-AXISCN1307461851-ONE MOBIKWIK SYSTEMS LIMITED | I95: Receipt | J95: 0 | K95: 23400 | L95: 23400 | M95: 25900 | N95: Recurring Transaction | O95: Yes | P95: ONE MOBIKWIK SYSTEMS LIMITED | Q95: 0 | R95: 1 | S95: 0 | T95: 0 | U95: 0 | V95: 0 | W95: 0 | X95: 0 | Y95: 0 | Z95: 0 | AA95: 46122 | AB95: =HYPERLINK("#'Transactions'!A108", "View Source Row")
A96: 108 | B96: 502 input.pdf | C96: 46113 | D96: 46142 | E96: 46122 | F96: 46122 | G96: UPI/7501693995 69399505 UPI/750169399505/08:58:54/UPI/surajdhanotra1@ibl/ | I96: Receipt | J96: 0 | K96: 3165 | L96: 3165 | M96: 29065 | N96: UPI; Recurring Transaction | O96: Yes | P96: SURAJDHANOTRAIBL | Q96: 0 | R96: 1 | S96: 0 | T96: 0 | U96: 0 | V96: 1 | W96: 0 | X96: 0 | Y96: 0 | Z96: 0 | AA96: 46122 | AB96: =HYPERLINK("#'Transactions'!A109", "View Source Row")
A97: 109 | B97: 502 input.pdf | C97: 46113 | D97: 46142 | E97: 46122 | F97: 46122 | G97: DIGITA-MUMBAI/ NEFT-AXISCN1307585087-PINE LABS PRIVATE LIMITED-NO | I97: Receipt | J97: 0 | K97: 23121 | L97: 23121 | M97: 52186 | N97: Recurring Transaction | O97: Yes | P97: PINE LABS PRIVATE LIMITED | Q97: 0 | R97: 1 | S97: 0 | T97: 0 | U97: 0 | V97: 0 | W97: 0 | X97: 0 | Y97: 0 | Z97: 0 | AA97: 46122 | AB97: =HYPERLINK("#'Transactions'!A110", "View Source Row")
A98: 110 | B98: 502 input.pdf | C98: 46113 | D98: 46142 | E98: 46122 | F98: 46122 | G98: EBANK:WIB/1503 EBANK:WIB/1503385381/Edfs | I98: Payment | J98: 49686 | K98: 0 | L98: 49686 | M98: 2500 | N98: Recurring Transaction | O98: Yes | P98: EBANKWIB | Q98: 0 | R98: 1 | S98: 0 | T98: 0 | U98: 0 | V98: 0 | W98: 0 | X98: 0 | Y98: 0 | Z98: 0 | AA98: 46122 | AB98: =HYPERLINK("#'Transactions'!A111", "View Source Row")
A99: 111 | B99: 502 input.pdf | C99: 46113 | D99: 46142 | E99: 46122 | F99: 46122 | G99: DIGITA-MUMBAI/ NEFT-NKGSH26100973635-GEBI PRODUCTS PRIVATE LIMITE | I99: Receipt | J99: 0 | K99: 5273 | L99: 5273 | M99: 7773 | N99: Recurring Transaction | O99: Yes | P99: GEBI PRODUCTS PRIVATE LIMITE | Q99: 0 | R99: 1 | S99: 0 | T99: 0 | U99: 0 | V99: 0 | W99: 0 | X99: 0 | Y99: 0 | Z99: 0 | AA99: 46122 | AB99: =HYPERLINK("#'Transactions'!A112", "View Source Row")
A100: 112 | B100: 502 input.pdf | C100: 46113 | D100: 46142 | E100: 46122 | F100: 46122 | G100: DIGITA-MUMBAI/ NEFT-KKBKH26100693248-ATLAS COMMODITIES PRIVATE LI | I100: Receipt | J100: 0 | K100: 7922 | L100: 7922 | M100: 15695 | N100: Recurring Transaction | O100: Yes | P100: ATLAS COMMODITIES PRIVATE LI | Q100: 0 | R100: 1 | S100: 0 | T100: 0 | U100: 0 | V100: 0 | W100: 0 | X100: 0 | Y100: 0 | Z100: 0 | AA100: 46122 | AB100: =HYPERLINK("#'Transactions'!A113", "View Source Row")
A101: 114 | B101: 502 input.pdf | C101: 46113 | D101: 46142 | E101: 46123 | F101: 46123 | G101: DIGITA-MUMBAI/ NEFT-YESAP61011187841-PhonePe Limited | I101: Receipt | J101: 0 | K101: 217794 | L101: 217794 | M101: 233709 | N101: High Transaction; Recurring Transaction | O101: Yes | P101: PHONEPE LIMITED | Q101: 0 | R101: 1 | S101: 0 | T101: 0 | U101: 1 | V101: 0 | W101: 0 | X101: 0 | Y101: 0 | Z101: 0 | AA101: 46123 | AB101: =HYPERLINK("#'Transactions'!A115", "View Source Row")
...

Sheet Detail EMI
A1: =HYPERLINK("#'Dashboard'!A1", "← Return to Dashboard") | B1: EMI Transactions
A2: Rows | B2: 2 | C2: Match | D2: EMI
A4: Seq | B4: Source File | C4: Statement From | D4: Statement To | E4: Date | F4: Value Date | G4: Narration | H4: Reference | I4: Direction | J4: Withdrawal | K4: Deposit | L4: Amount | M4: Closing Balance | N4: Categories | O4: Recurring? | P4: Recurring Key | Q4: Flag - Cash | R4: Flag - Recurring Transaction | S4: Flag - EMI | T4: Flag - Salary | U4: Flag - High Transaction | V4: Flag - UPI | W4: Flag - LIC | X4: Flag - FD interest | Y4: Flag - FD Deposit and withdrawals | Z4: Flag - PPF/PF interest and contribution | AA4: Month Date | AB4: View Source Row
A5: 7 | B5: 502 input.pdf | C5: 46113 | D5: 46142 | E5: 46114 | F5: 46114 | G5: DIGITA-MUMBAI/ NEFT-FBPT260916108327-PREMIER CONVEYORS PRIVATE LI | I5: Receipt | J5: 0 | K5: 18409 | L5: 18409 | M5: 20909 | N5: EMI; Recurring Transaction | O5: Yes | P5: PREMIER CONVEYORS PRIVATE LI | Q5: 0 | R5: 1 | S5: 1 | T5: 0 | U5: 0 | V5: 0 | W5: 0 | X5: 0 | Y5: 0 | Z5: 0 | AA5: 46114 | AB5: =HYPERLINK("#'Transactions'!A8", "View Source Row")
A6: 226 | B6: 502 input.pdf | C6: 46113 | D6: 46142 | E6: 46130 | F6: 46130 | G6: DIGITA-MUMBAI/ NEFT-FBPT261087153653-PREMIER CONVEYORS PRIVATE LI | I6: Receipt | J6: 0 | K6: 37132 | L6: 37132 | M6: 483167.28 | N6: EMI; Recurring Transaction | O6: Yes | P6: PREMIER CONVEYORS PRIVATE LI | Q6: 0 | R6: 1 | S6: 1 | T6: 0 | U6: 0 | V6: 0 | W6: 0 | X6: 0 | Y6: 0 | Z6: 0 | AA6: 46130 | AB6: =HYPERLINK("#'Transactions'!A227", "View Source Row")

Sheet Detail Salary
A1: =HYPERLINK("#'Dashboard'!A1", "← Return to Dashboard") | B1: Salary Transactions
A2: Rows | B2: 0 | C2: Match | D2: Salary
A4: Seq | B4: Source File | C4: Statement From | D4: Statement To | E4: Date | F4: Value Date | G4: Narration | H4: Reference | I4: Direction | J4: Withdrawal | K4: Deposit | L4: Amount | M4: Closing Balance | N4: Categories | O4: Recurring? | P4: Recurring Key | Q4: Flag - Cash | R4: Flag - Recurring Transaction | S4: Flag - EMI | T4: Flag - Salary | U4: Flag - High Transaction | V4: Flag - UPI | W4: Flag - LIC | X4: Flag - FD interest | Y4: Flag - FD Deposit and withdrawals | Z4: Flag - PPF/PF interest and contribution | AA4: Month Date | AB4: View Source Row
A5: No matching transactions.

Sheet Detail High Transaction
A1: =HYPERLINK("#'Dashboard'!A1", "← Return to Dashboard") | B1: High Transaction Transactions
A2: Rows | B2: 112 | C2: Match | D2: High Transaction
A4: Seq | B4: Source File | C4: Statement From | D4: Statement To | E4: Date | F4: Value Date | G4: Narration | H4: Reference | I4: Direction | J4: Withdrawal | K4: Deposit | L4: Amount | M4: Closing Balance | N4: Categories | O4: Recurring? | P4: Recurring Key | Q4: Flag - Cash | R4: Flag - Recurring Transaction | S4: Flag - EMI | T4: Flag - Salary | U4: Flag - High Transaction | V4: Flag - UPI | W4: Flag - LIC | X4: Flag - FD interest | Y4: Flag - FD Deposit and withdrawals | Z4: Flag - PPF/PF interest and contribution | AA4: Month Date | AB4: View Source Row
A5: 2 | B5: 502 input.pdf | C5: 46113 | D5: 46142 | E5: 46114 | F5: 46114 | G5: DIGITA-MUMBAI/ NEFT-YESAP60912594024-PhonePe Limited | I5: Receipt | J5: 0 | K5: 165179 | L5: 165179 | M5: 581570 | N5: High Transaction; Recurring Transaction | O5: Yes | P5: PHONEPE LIMITED | Q5: 0 | R5: 1 | S5: 0 | T5: 0 | U5: 1 | V5: 0 | W5: 0 | X5: 0 | Y5: 0 | Z5: 0 | AA5: 46114 | AB5: =HYPERLINK("#'Transactions'!A3", "View Source Row")
A6: 6 | B6: 502 input.pdf | C6: 46113 | D6: 46142 | E6: 46114 | F6: 46114 | G6: EBANK:WIB/1502 EBANK:WIB/1502021829/Edfs | I6: Payment | J6: 681881.6 | K6: 0 | L6: 681881.6 | M6: 2500 | N6: High Transaction; Recurring Transaction | O6: Yes | P6: EBANKWIB | Q6: 0 | R6: 1 | S6: 0 | T6: 0 | U6: 1 | V6: 0 | W6: 0 | X6: 0 | Y6: 0 | Z6: 0 | AA6: 46114 | AB6: =HYPERLINK("#'Transactions'!A7", "View Source Row")
A7: 8 | B7: 502 input.pdf | C7: 46113 | D7: 46142 | E7: 46114 | F7: 46114 | G7: DIGITA-MUMBAI/ NEFT-CNRBH00121803213-QUALITY PLAST INDUSTRIES LIM | I7: Receipt | J7: 0 | K7: 121431 | L7: 121431 | M7: 142340 | N7: High Transaction; Recurring Transaction | O7: Yes | P7: QUALITY PLAST INDUSTRIES LIM | Q7: 0 | R7: 1 | S7: 0 | T7: 0 | U7: 1 | V7: 0 | W7: 0 | X7: 0 | Y7: 0 | Z7: 0 | AA7: 46114 | AB7: =HYPERLINK("#'Transactions'!A9", "View Source Row")
A8: 10 | B8: 502 input.pdf | C8: 46113 | D8: 46142 | E8: 46114 | F8: 46114 | G8: DIGITA-MUMBAI/ IMPS/P2A/609116466512/AFZALSIRAJUDDIN/IMPSUOB9191 | I8: Receipt | J8: 0 | K8: 100000 | L8: 100000 | M8: 240840 | N8: High Transaction; Recurring Transaction | O8: Yes | P8: AFZALSIRAJUDDIN | Q8: 0 | R8: 1 | S8: 0 | T8: 0 | U8: 1 | V8: 0 | W8: 0 | X8: 0 | Y8: 0 | Z8: 0 | AA8: 46114 | AB8: =HYPERLINK("#'Transactions'!A11", "View Source Row")
A9: 12 | B9: 502 input.pdf | C9: 46113 | D9: 46142 | E9: 46114 | F9: 46114 | G9: EBANK:WIB/1502 ---------------------------------------------------------------------------------------------------------------------------------- Page Total: 9,34,077.60 5,73,386.60 2,500.00Cr ---------------------------------------------------------------------------------------------------------------------------------- Note: Cheques received in inward clearing will be considered for debiting/ returning on the basis opening balance in account Unless the constituent notifies the bank of any dis | I9: Payment | J9: 248340 | K9: 0 | L9: 248340 | M9: 2500 | N9: High Transaction; Recurring Transaction | O9: Yes | P9: EBANKWIB | Q9: 0 | R9: 1 | S9: 0 | T9: 0 | U9: 1 | V9: 0 | W9: 0 | X9: 0 | Y9: 0 | Z9: 0 | AA9: 46114 | AB9: =HYPERLINK("#'Transactions'!A13", "View Source Row")
A10: 13 | B10: 502 input.pdf | C10: 46113 | D10: 46142 | E10: 46114 | F10: 46114 | G10: DIGITA-MUMBAI/ NEFT-YESAP60924833309-PhonePe Limited | I10: Receipt | J10: 0 | K10: 188588.4 | L10: 188588.4 | M10: 191088.4 | N10: High Transaction; Recurring Transaction | O10: Yes | P10: PHONEPE LIMITED | Q10: 0 | R10: 1 | S10: 0 | T10: 0 | U10: 1 | V10: 0 | W10: 0 | X10: 0 | Y10: 0 | Z10: 0 | AA10: 46114 | AB10: =HYPERLINK("#'Transactions'!A14", "View Source Row")
A11: 18 | B11: 502 input.pdf | C11: 46113 | D11: 46142 | E11: 46114 | F11: 46114 | G11: DIGITA-MUMBAI/ NEFT-AXISCN1299028324-PINE LABS PRIVATE LIMITED-NO | I11: Receipt | J11: 0 | K11: 166884 | L11: 166884 | M11: 513521.5 | N11: High Transaction; Recurring Transaction | O11: Yes | P11: PINE LABS PRIVATE LIMITED | Q11: 0 | R11: 1 | S11: 0 | T11: 0 | U11: 1 | V11: 0 | W11: 0 | X11: 0 | Y11: 0 | Z11: 0 | AA11: 46114 | AB11: =HYPERLINK("#'Transactions'!A19", "View Source Row")
A12: 25 | B12: 502 input.pdf | C12: 46113 | D12: 46142 | E12: 46114 | F12: 46114 | G12: DIGITA-MUMBAI/ NEFT-HDFCH00905140576-Adekar enterprises pvt ltd | I12: Receipt | J12: 0 | K12: 138674 | L12: 138674 | M12: 743982.5 | N12: High Transaction; Recurring Transaction | O12: Yes | P12: ADEKAR ENTERPRISES PVT LTD | Q12: 0 | R12: 1 | S12: 0 | T12: 0 | U12: 1 | V12: 0 | W12: 0 | X12: 0 | Y12: 0 | Z12: 0 | AA12: 46114 | AB12: =HYPERLINK("#'Transactions'!A26", "View Source Row")
A13: 27 | B13: 502 input.pdf | C13: 46113 | D13: 46142 | E13: 46114 | F13: 46114 | G13: EBANK:WIB/1502 EBANK:WIB/1502234210/Edfs | I13: Payment | J13: 791482.5 | K13: 0 | L13: 791482.5 | M13: 2500 | N13: High Transaction; Recurring Transaction | O13: Yes | P13: EBANKWIB | Q13: 0 | R13: 1 | S13: 0 | T13: 0 | U13: 1 | V13: 0 | W13: 0 | X13: 0 | Y13: 0 | Z13: 0 | AA13: 46114 | AB13: =HYPERLINK("#'Transactions'!A28", "View Source Row")
A14: 30 | B14: 502 input.pdf | C14: 46113 | D14: 46142 | E14: 46115 | F14: 46115 | G14: DIGITA-MUMBAI/ NEFT-YESAP60934071902-PhonePe Limited | I14: Receipt | J14: 0 | K14: 173393.9 | L14: 173393.9 | M14: 216422.9 | N14: High Transaction; Recurring Transaction | O14: Yes | P14: PHONEPE LIMITED | Q14: 0 | R14: 1 | S14: 0 | T14: 0 | U14: 1 | V14: 0 | W14: 0 | X14: 0 | Y14: 0 | Z14: 0 | AA14: 46115 | AB14: =HYPERLINK("#'Transactions'!A31", "View Source Row")
A15: 34 | B15: 502 input.pdf | C15: 46113 | D15: 46142 | E15: 46115 | F15: 46115 | G15: DIGITA-MUMBAI/ NEFT-AXISCN1300388689-PINE LABS PRIVATE LIMITED-NO | I15: Receipt | J15: 0 | K15: 112894 | L15: 112894 | M15: 410724.58 | N15: High Transaction; Recurring Transaction | O15: Yes | P15: PINE LABS PRIVATE LIMITED | Q15: 0 | R15: 1 | S15: 0 | T15: 0 | U15: 1 | V15: 0 | W15: 0 | X15: 0 | Y15: 0 | Z15: 0 | AA15: 46115 | AB15: =HYPERLINK("#'Transactions'!A35", "View Source Row")
A16: 35 | B16: 502 input.pdf | C16: 46113 | D16: 46142 | E16: 46115 | F16: 46115 | G16: DIGITA-MUMBAI/ IMPS/P2A/609312855509/AFZALSIRAJUDDIN/IMPSUOB9191 | I16: Receipt | J16: 0 | K16: 200000 | L16: 200000 | M16: 610724.58 | N16: High Transaction; Recurring Transaction | O16: Yes | P16: AFZALSIRAJUDDIN | Q16: 0 | R16: 1 | S16: 0 | T16: 0 | U16: 1 | V16: 0 | W16: 0 | X16: 0 | Y16: 0 | Z16: 0 | AA16: 46115 | AB16: =HYPERLINK("#'Transactions'!A36", "View Source Row")
A17: 36 | B17: 502 input.pdf | C17: 46113 | D17: 46142 | E17: 46115 | F17: 46115 | G17: DIGITA-MUMBAI/ NEFT-002663976089-GANGAMAI INDUSTRIES AND CONSTR | I17: Receipt | J17: 0 | K17: 180880 | L17: 180880 | M17: 791604.58 | N17: High Transaction | O17: No | P17: GANGAMAI INDUSTRIES AND CONSTR | Q17: 0 | R17: 0 | S17: 0 | T17: 0 | U17: 1 | V17: 0 | W17: 0 | X17: 0 | Y17: 0 | Z17: 0 | AA17: 46115 | AB17: =HYPERLINK("#'Transactions'!A37", "View Source Row")
A18: 37 | B18: 502 input.pdf | C18: 46113 | D18: 46142 | E18: 46115 | F18: 46115 | G18: EBANK:WIB/1502 EBANK:WIB/1502413595/Edfs | I18: Payment | J18: 790104.58 | K18: 0 | L18: 790104.58 | M18: 1500 | N18: High Transaction; Recurring Transaction | O18: Yes | P18: EBANKWIB | Q18: 0 | R18: 1 | S18: 0 | T18: 0 | U18: 1 | V18: 0 | W18: 0 | X18: 0 | Y18: 0 | Z18: 0 | AA18: 46115 | AB18: =HYPERLINK("#'Transactions'!A38", "View Source Row")
A19: 38 | B19: 502 input.pdf | C19: 46113 | D19: 46142 | E19: 46116 | F19: 46116 | G19: DIGITA-MUMBAI/ NEFT-YESAP60944128518-PhonePe Limited | I19: Receipt | J19: 0 | K19: 171014 | L19: 171014 | M19: 172514 | N19: High Transaction; Recurring Transaction | O19: Yes | P19: PHONEPE LIMITED | Q19: 0 | R19: 1 | S19: 0 | T19: 0 | U19: 1 | V19: 0 | W19: 0 | X19: 0 | Y19: 0 | Z19: 0 | AA19: 46116 | AB19: =HYPERLINK("#'Transactions'!A39", "View Source Row")
A20: 41 | B20: 502 input.pdf | C20: 46113 | D20: 46142 | E20: 46116 | F20: 46116 | G20: EBANK:WIB/1502 EBANK:WIB/1502423934/Edfs | I20: Payment | J20: 240091 | K20: 0 | L20: 240091 | M20: 4500 | N20: High Transaction; Recurring Transaction | O20: Yes | P20: EBANKWIB | Q20: 0 | R20: 1 | S20: 0 | T20: 0 | U20: 1 | V20: 0 | W20: 0 | X20: 0 | Y20: 0 | Z20: 0 | AA20: 46116 | AB20: =HYPERLINK("#'Transactions'!A42", "View Source Row")
A21: 47 | B21: 502 input.pdf | C21: 46113 | D21: 46142 | E21: 46116 | F21: 46116 | G21: EBANK:WIB/1502 EBANK:WIB/1502545632/Edfs | I21: Payment | J21: 120330.37 | K21: 0 | L21: 120330.37 | M21: 1500 | N21: High Transaction; Recurring Transaction | O21: Yes | P21: EBANKWIB | Q21: 0 | R21: 1 | S21: 0 | T21: 0 | U21: 1 | V21: 0 | W21: 0 | X21: 0 | Y21: 0 | Z21: 0 | AA21: 46116 | AB21: =HYPERLINK("#'Transactions'!A48", "View Source Row")
A22: 49 | B22: 502 input.pdf | C22: 46113 | D22: 46142 | E22: 46117 | F22: 46117 | G22: DIGITA-MUMBAI/ NEFT-YESAP60953903247-PhonePe Limited | I22: Receipt | J22: 0 | K22: 167015 | L22: 167015 | M22: 249911 | N22: High Transaction; Recurring Transaction | O22: Yes | P22: PHONEPE LIMITED | Q22: 0 | R22: 1 | S22: 0 | T22: 0 | U22: 1 | V22: 0 | W22: 0 | X22: 0 | Y22: 0 | Z22: 0 | AA22: 46117 | AB22: =HYPERLINK("#'Transactions'!A50", "View Source Row")
A23: 52 | B23: 502 input.pdf | C23: 46113 | D23: 46142 | E23: 46117 | F23: 46117 | G23: EBANK:WIB/1502 EBANK:WIB/1502577386/Edfs | I23: Payment | J23: 300403.36 | K23: 0 | L23: 300403.36 | M23: 45500 | N23: High Transaction; Recurring Transaction | O23: Yes | P23: EBANKWIB | Q23: 0 | R23: 1 | S23: 0 | T23: 0 | U23: 1 | V23: 0 | W23: 0 | X23: 0 | Y23: 0 | Z23: 0 | AA23: 46117 | AB23: =HYPERLINK("#'Transactions'!A53", "View Source Row")
A24: 55 | B24: 502 input.pdf | C24: 46113 | D24: 46142 | E24: 46118 | F24: 46118 | G24: DIGITA-MUMBAI/ NEFT-YESAP60964000643-PhonePe Limited | I24: Receipt | J24: 0 | K24: 169456 | L24: 169456 | M24: 336599.21 | N24: High Transaction; Recurring Transaction | O24: Yes | P24: PHONEPE LIMITED | Q24: 0 | R24: 1 | S24: 0 | T24: 0 | U24: 1 | V24: 0 | W24: 0 | X24: 0 | Y24: 0 | Z24: 0 | AA24: 46118 | AB24: =HYPERLINK("#'Transactions'!A56", "View Source Row")
A25: 57 | B25: 502 input.pdf | C25: 46113 | D25: 46142 | E25: 46118 | F25: 46118 | G25: EBANK:WIB/1502 EBANK:WIB/1502642025/Edfs | I25: Payment | J25: 365780.21 | K25: 0 | L25: 365780.21 | M25: 2500 | N25: High Transaction; Recurring Transaction | O25: Yes | P25: EBANKWIB | Q25: 0 | R25: 1 | S25: 0 | T25: 0 | U25: 1 | V25: 0 | W25: 0 | X25: 0 | Y25: 0 | Z25: 0 | AA25: 46118 | AB25: =HYPERLINK("#'Transactions'!A58", "View Source Row")
A26: 59 | B26: 502 input.pdf | C26: 46113 | D26: 46142 | E26: 46118 | F26: 46118 | G26: DIGITA-MUMBAI/ ---------------------------------------------------------------------------------------------------------------------------------- Page Total: 7,86,664.57 8,85,980.57 1,32,016.00Cr ---------------------------------------------------------------------------------------------------------------------------------- Note: Cheques received in inward clearing will be considered for debiting/ returning on the basis opening balance in account Unless the constituent notifies the bank of any | I26: Receipt | J26: 0 | K26: 100000 | L26: 100000 | M26: 132016 | N26: High Transaction; Recurring Transaction | O26: Yes | P26: PAGE TOTAL CR | Q26: 0 | R26: 1 | S26: 0 | T26: 0 | U26: 1 | V26: 0 | W26: 0 | X26: 0 | Y26: 0 | Z26: 0 | AA26: 46118 | AB26: =HYPERLINK("#'Transactions'!A60", "View Source Row")
A27: 64 | B27: 502 input.pdf | C27: 46113 | D27: 46142 | E27: 46118 | F27: 46118 | G27: EBANK:WIB/1502 EBANK:WIB/1502790855/Edfs | I27: Payment | J27: 198114 | K27: 0 | L27: 198114 | M27: 2500 | N27: High Transaction; Recurring Transaction | O27: Yes | P27: EBANKWIB | Q27: 0 | R27: 1 | S27: 0 | T27: 0 | U27: 1 | V27: 0 | W27: 0 | X27: 0 | Y27: 0 | Z27: 0 | AA27: 46118 | AB27: =HYPERLINK("#'Transactions'!A65", "View Source Row")
A28: 66 | B28: 502 input.pdf | C28: 46113 | D28: 46142 | E28: 46119 | F28: 46119 | G28: DIGITA-MUMBAI/ NEFT-YESAP60974165954-PhonePe Limited | I28: Receipt | J28: 0 | K28: 260044.42 | L28: 260044.42 | M28: 280992.42 | N28: High Transaction; Recurring Transaction | O28: Yes | P28: PHONEPE LIMITED | Q28: 0 | R28: 1 | S28: 0 | T28: 0 | U28: 1 | V28: 0 | W28: 0 | X28: 0 | Y28: 0 | Z28: 0 | AA28: 46119 | AB28: =HYPERLINK("#'Transactions'!A67", "View Source Row")
A29: 68 | B29: 502 input.pdf | C29: 46113 | D29: 46142 | E29: 46119 | F29: 46119 | G29: EBANK:WIB/1502 EBANK:WIB/1502821939/Edfs | I29: Payment | J29: 330493.07 | K29: 0 | L29: 330493.07 | M29: 5500 | N29: High Transaction; Recurring Transaction | O29: Yes | P29: EBANKWIB | Q29: 0 | R29: 1 | S29: 0 | T29: 0 | U29: 1 | V29: 0 | W29: 0 | X29: 0 | Y29: 0 | Z29: 0 | AA29: 46119 | AB29: =HYPERLINK("#'Transactions'!A69", "View Source Row")
A30: 75 | B30: 502 input.pdf | C30: 46113 | D30: 46142 | E30: 46119 | F30: 46119 | G30: BY CASH ---------------------------------------------------------------------------------------------------------------------------------- Page Total: 5,32,609.72 5,77,390.07 1,76,796.35Cr ---------------------------------------------------------------------------------------------------------------------------------- Note: Cheques received in inward clearing will be considered for debiting/ returning on the basis opening balance in account Unless the constituent notifies the bank of any discrep | I30: Receipt | J30: 0 | K30: 114500 | L30: 114500 | M30: 176796.35 | N30: Cash; High Transaction; Recurring Transaction | O30: Yes | P30: PAGE TOTAL CR | Q30: 1 | R30: 1 | S30: 0 | T30: 0 | U30: 1 | V30: 0 | W30: 0 | X30: 0 | Y30: 0 | Z30: 0 | AA30: 46119 | AB30: =HYPERLINK("#'Transactions'!A76", "View Source Row")
A31: 81 | B31: 502 input.pdf | C31: 46113 | D31: 46142 | E31: 46119 | F31: 46119 | G31: EBANK:WIB/1502 EBANK:WIB/1502986421/Edfs | I31: Payment | J31: 137582.35 | K31: 0 | L31: 137582.35 | M31: 2500 | N31: High Transaction; Recurring Transaction | O31: Yes | P31: EBANKWIB | Q31: 0 | R31: 1 | S31: 0 | T31: 0 | U31: 1 | V31: 0 | W31: 0 | X31: 0 | Y31: 0 | Z31: 0 | AA31: 46119 | AB31: =HYPERLINK("#'Transactions'!A82", "View Source Row")
A32: 83 | B32: 502 input.pdf | C32: 46113 | D32: 46142 | E32: 46120 | F32: 46120 | G32: DIGITA-MUMBAI/ NEFT-YESAP60983679319-PhonePe Limited | I32: Receipt | J32: 0 | K32: 243684 | L32: 243684 | M32: 283597 | N32: High Transaction; Recurring Transaction | O32: Yes | P32: PHONEPE LIMITED | Q32: 0 | R32: 1 | S32: 0 | T32: 0 | U32: 1 | V32: 0 | W32: 0 | X32: 0 | Y32: 0 | Z32: 0 | AA32: 46120 | AB32: =HYPERLINK("#'Transactions'!A84", "View Source Row")
A33: 89 | B33: 502 input.pdf | C33: 46113 | D33: 46142 | E33: 46120 | F33: 46120 | G33: EBANK:WIB/1503 EBANK:WIB/1503050809/Edfs | I33: Payment | J33: 381113 | K33: 0 | L33: 381113 | M33: 2500 | N33: High Transaction; Recurring Transaction | O33: Yes | P33: EBANKWIB | Q33: 0 | R33: 1 | S33: 0 | T33: 0 | U33: 1 | V33: 0 | W33: 0 | X33: 0 | Y33: 0 | Z33: 0 | AA33: 46120 | AB33: =HYPERLINK("#'Transactions'!A90", "View Source Row")
A34: 94 | B34: 502 input.pdf | C34: 46113 | D34: 46142 | E34: 46120 | F34: 46120 | G34: EBANK:WIB/1503 EBANK:WIB/1503170712/Edfs | I34: Payment | J34: 108620 | K34: 0 | L34: 108620 | M34: 2500 | N34: High Transaction; Recurring Transaction | O34: Yes | P34: EBANKWIB | Q34: 0 | R34: 1 | S34: 0 | T34: 0 | U34: 1 | V34: 0 | W34: 0 | X34: 0 | Y34: 0 | Z34: 0 | AA34: 46120 | AB34: =HYPERLINK("#'Transactions'!A95", "View Source Row")
A35: 95 | B35: 502 input.pdf | C35: 46113 | D35: 46142 | E35: 46121 | F35: 46121 | G35: DIGITA-MUMBAI/ NEFT-YESAP60993677587-PhonePe Limited | I35: Receipt | J35: 0 | K35: 170522 | L35: 170522 | M35: 173022 | N35: High Transaction; Recurring Transaction | O35: Yes | P35: PHONEPE LIMITED | Q35: 0 | R35: 1 | S35: 0 | T35: 0 | U35: 1 | V35: 0 | W35: 0 | X35: 0 | Y35: 0 | Z35: 0 | AA35: 46121 | AB35: =HYPERLINK("#'Transactions'!A96", "View Source Row")
A36: 102 | B36: 502 input.pdf | C36: 46113 | D36: 46142 | E36: 46121 | F36: 46121 | G36: EBANK:WIB/1503 EBANK:WIB/1503311707/Edfs | I36: Payment | J36: 380118 | K36: 0 | L36: 380118 | M36: 2500 | N36: High Transaction; Recurring Transaction | O36: Yes | P36: EBANKWIB | Q36: 0 | R36: 1 | S36: 0 | T36: 0 | U36: 1 | V36: 0 | W36: 0 | X36: 0 | Y36: 0 | Z36: 0 | AA36: 46121 | AB36: =HYPERLINK("#'Transactions'!A103", "View Source Row")
A37: 104 | B37: 502 input.pdf | C37: 46113 | D37: 46142 | E37: 46122 | F37: 46122 | G37: DIGITA-MUMBAI/ NEFT-YESAP61002547485-PhonePe Limited | I37: Receipt | J37: 0 | K37: 310276 | L37: 310276 | M37: 376084 | N37: High Transaction; Recurring Transaction | O37: Yes | P37: PHONEPE LIMITED | Q37: 0 | R37: 1 | S37: 0 | T37: 0 | U37: 1 | V37: 0 | W37: 0 | X37: 0 | Y37: 0 | Z37: 0 | AA37: 46122 | AB37: =HYPERLINK("#'Transactions'!A105", "View Source Row")
A38: 106 | B38: 502 input.pdf | C38: 46113 | D38: 46142 | E38: 46122 | F38: 46122 | G38: EBANK:WIB/1503 EBANK:WIB/1503339201/Edfs ---------------------------------------------------------------------------------------------------------------------------------- Page Total: 9,21,737.00 8,79,475.00 2,500.00Cr ---------------------------------------------------------------------------------------------------------------------------------- Note: Cheques received in inward clearing will be considered for debiting/ returning on the basis opening balance in account Unless the constituent no | I38: Payment | J38: 432999 | K38: 0 | L38: 432999 | M38: 2500 | N38: High Transaction; Recurring Transaction | O38: Yes | P38: EBANKWIB | Q38: 0 | R38: 1 | S38: 0 | T38: 0 | U38: 1 | V38: 0 | W38: 0 | X38: 0 | Y38: 0 | Z38: 0 | AA38: 46122 | AB38: =HYPERLINK("#'Transactions'!A107", "View Source Row")
A39: 114 | B39: 502 input.pdf | C39: 46113 | D39: 46142 | E39: 46123 | F39: 46123 | G39: DIGITA-MUMBAI/ NEFT-YESAP61011187841-PhonePe Limited | I39: Receipt | J39: 0 | K39: 217794 | L39: 217794 | M39: 233709 | N39: High Transaction; Recurring Transaction | O39: Yes | P39: PHONEPE LIMITED | Q39: 0 | R39: 1 | S39: 0 | T39: 0 | U39: 1 | V39: 0 | W39: 0 | X39: 0 | Y39: 0 | Z39: 0 | AA39: 46123 | AB39: =HYPERLINK("#'Transactions'!A115", "View Source Row")
A40: 140 | B40: 502 input.pdf | C40: 46113 | D40: 46142 | E40: 46123 | F40: 46123 | G40: EBANK:WIB/1503 EBANK:WIB/1503559058/Edfs | I40: Payment | J40: 353767.15 | K40: 0 | L40: 353767.15 | M40: 20500 | N40: High Transaction; Recurring Transaction | O40: Yes | P40: EBANKWIB | Q40: 0 | R40: 1 | S40: 0 | T40: 0 | U40: 1 | V40: 0 | W40: 0 | X40: 0 | Y40: 0 | Z40: 0 | AA40: 46123 | AB40: =HYPERLINK("#'Transactions'!A141", "View Source Row")
A41: 143 | B41: 502 input.pdf | C41: 46113 | D41: 46142 | E41: 46124 | F41: 46124 | G41: DIGITA-MUMBAI/ NEFT-YESAP61023739033-PhonePe Limited | I41: Receipt | J41: 0 | K41: 316091.5 | L41: 316091.5 | M41: 347443.5 | N41: High Transaction; Recurring Transaction | O41: Yes | P41: PHONEPE LIMITED | Q41: 0 | R41: 1 | S41: 0 | T41: 0 | U41: 1 | V41: 0 | W41: 0 | X41: 0 | Y41: 0 | Z41: 0 | AA41: 46124 | AB41: =HYPERLINK("#'Transactions'!A144", "View Source Row")
A42: 150 | B42: 502 input.pdf | C42: 46113 | D42: 46142 | E42: 46124 | F42: 46124 | G42: EBANK:WIB/1503 EBANK:WIB/1503691094/Edfs | I42: Payment | J42: 521281.39 | K42: 0 | L42: 521281.39 | M42: 2500 | N42: High Transaction; Recurring Transaction | O42: Yes | P42: EBANKWIB | Q42: 0 | R42: 1 | S42: 0 | T42: 0 | U42: 1 | V42: 0 | W42: 0 | X42: 0 | Y42: 0 | Z42: 0 | AA42: 46124 | AB42: =HYPERLINK("#'Transactions'!A151", "View Source Row")
A43: 151 | B43: 502 input.pdf | C43: 46113 | D43: 46142 | E43: 46125 | F43: 46125 | G43: DIGITA-MUMBAI/ NEFT-YESAP61032531277-PhonePe Limited | I43: Receipt | J43: 0 | K43: 250095 | L43: 250095 | M43: 252595 | N43: High Transaction; Recurring Transaction | O43: Yes | P43: PHONEPE LIMITED | Q43: 0 | R43: 1 | S43: 0 | T43: 0 | U43: 1 | V43: 0 | W43: 0 | X43: 0 | Y43: 0 | Z43: 0 | AA43: 46125 | AB43: =HYPERLINK("#'Transactions'!A152", "View Source Row")
A44: 158 | B44: 502 input.pdf | C44: 46113 | D44: 46142 | E44: 46125 | F44: 46125 | G44: DIGITA-MUMBAI/ NEFT-AXODH10395993542-GRISHMA METAL TECHNOLOGY | I44: Receipt | J44: 0 | K44: 124000 | L44: 124000 | M44: 507461.93 | N44: High Transaction; Recurring Transaction | O44: Yes | P44: GRISHMA METAL TECHNOLOGY | Q44: 0 | R44: 1 | S44: 0 | T44: 0 | U44: 1 | V44: 0 | W44: 0 | X44: 0 | Y44: 0 | Z44: 0 | AA44: 46125 | AB44: =HYPERLINK("#'Transactions'!A159", "View Source Row")
A45: 161 | B45: 502 input.pdf | C45: 46113 | D45: 46142 | E45: 46125 | F45: 46125 | G45: DIGITA-MUMBAI/ NEFT-AXISCN1310059428-PINE LABS PRIVATE LIMITED-NO | I45: Receipt | J45: 0 | K45: 102789 | L45: 102789 | M45: 609211.93 | N45: High Transaction; Recurring Transaction | O45: Yes | P45: PINE LABS PRIVATE LIMITED | Q45: 0 | R45: 1 | S45: 0 | T45: 0 | U45: 1 | V45: 0 | W45: 0 | X45: 0 | Y45: 0 | Z45: 0 | AA45: 46125 | AB45: =HYPERLINK("#'Transactions'!A162", "View Source Row")
A46: 165 | B46: 502 input.pdf | C46: 46113 | D46: 46142 | E46: 46125 | F46: 46125 | G46: EBANK:WIB/1503 EBANK:WIB/1503777187/Edfs | I46: Payment | J46: 610444.28 | K46: 0 | L46: 610444.28 | M46: 2500 | N46: High Transaction; Recurring Transaction | O46: Yes | P46: EBANKWIB | Q46: 0 | R46: 1 | S46: 0 | T46: 0 | U46: 1 | V46: 0 | W46: 0 | X46: 0 | Y46: 0 | Z46: 0 | AA46: 46125 | AB46: =HYPERLINK("#'Transactions'!A166", "View Source Row")
A47: 166 | B47: 502 input.pdf | C47: 46113 | D47: 46142 | E47: 46125 | F47: 46125 | G47: DIGITA-MUMBAI/ https://cbdrpt101.bankofbaroda.co.in:22000/finbranch/arjspmorph/INFENG/tran_rpt.jsp?... 04-05-2026 NEFT-HDFCH00930605811-Adekar enterprises pvt ltd | I47: Receipt | J47: 0 | K47: 128900 | L47: 128900 | M47: 131400 | N47: High Transaction; Recurring Transaction | O47: Yes | P47: CBDRPTBANKOFBARODACOIN | Q47: 0 | R47: 1 | S47: 0 | T47: 0 | U47: 1 | V47: 0 | W47: 0 | X47: 0 | Y47: 0 | Z47: 0 | AA47: 46125 | AB47: =HYPERLINK("#'Transactions'!A167", "View Source Row")
A48: 169 | B48: 502 input.pdf | C48: 46113 | D48: 46142 | E48: 46125 | F48: 46125 | G48: EBANK:WIB/1503 ---------------------------------------------------------------------------------------------------------------------------------- Page Total: 7,27,805.71 4,28,529.78 40,500.00Cr ---------------------------------------------------------------------------------------------------------------------------------- Note: Cheques received in inward clearing will be considered for debiting/ returning on the basis opening balance in account Unless the constituent notifies the bank of any di | I48: Payment | J48: 107993.78 | K48: 0 | L48: 107993.78 | M48: 40500 | N48: High Transaction; Recurring Transaction | O48: Yes | P48: EBANKWIB | Q48: 0 | R48: 1 | S48: 0 | T48: 0 | U48: 1 | V48: 0 | W48: 0 | X48: 0 | Y48: 0 | Z48: 0 | AA48: 46125 | AB48: =HYPERLINK("#'Transactions'!A170", "View Source Row")
A49: 172 | B49: 502 input.pdf | C49: 46113 | D49: 46142 | E49: 46126 | F49: 46126 | G49: DIGITA-MUMBAI/ NEFT-HDFCH00932431931-KAVITA ENTERPRISES | I49: Receipt | J49: 0 | K49: 110336 | L49: 110336 | M49: 147179 | N49: High Transaction; Recurring Transaction | O49: Yes | P49: KAVITA ENTERPRISES | Q49: 0 | R49: 1 | S49: 0 | T49: 0 | U49: 1 | V49: 0 | W49: 0 | X49: 0 | Y49: 0 | Z49: 0 | AA49: 46126 | AB49: =HYPERLINK("#'Transactions'!A173", "View Source Row")
A50: 173 | B50: 502 input.pdf | C50: 46113 | D50: 46142 | E50: 46126 | F50: 46126 | G50: DIGITA-MUMBAI/ NEFT-YESAP61042581238-PhonePe Limited | I50: Receipt | J50: 0 | K50: 227801 | L50: 227801 | M50: 374980 | N50: High Transaction; Recurring Transaction | O50: Yes | P50: PHONEPE LIMITED | Q50: 0 | R50: 1 | S50: 0 | T50: 0 | U50: 1 | V50: 0 | W50: 0 | X50: 0 | Y50: 0 | Z50: 0 | AA50: 46126 | AB50: =HYPERLINK("#'Transactions'!A174", "View Source Row")
A51: 176 | B51: 502 input.pdf | C51: 46113 | D51: 46142 | E51: 46126 | F51: 46126 | G51: EBANK:WIB/1503 EBANK:WIB/1503879023/Edfs | I51: Payment | J51: 421121.65 | K51: 0 | L51: 421121.65 | M51: 50500 | N51: High Transaction; Recurring Transaction | O51: Yes | P51: EBANKWIB | Q51: 0 | R51: 1 | S51: 0 | T51: 0 | U51: 1 | V51: 0 | W51: 0 | X51: 0 | Y51: 0 | Z51: 0 | AA51: 46126 | AB51: =HYPERLINK("#'Transactions'!A177", "View Source Row")
A52: 178 | B52: 502 input.pdf | C52: 46113 | D52: 46142 | E52: 46126 | F52: 46126 | G52: DIGITA-MUMBAI/ NEFT-AXISCN1310872121-PINE LABS PRIVATE LIMITED-NO | I52: Receipt | J52: 0 | K52: 181645 | L52: 181645 | M52: 230195 | N52: High Transaction; Recurring Transaction | O52: Yes | P52: PINE LABS PRIVATE LIMITED | Q52: 0 | R52: 1 | S52: 0 | T52: 0 | U52: 1 | V52: 0 | W52: 0 | X52: 0 | Y52: 0 | Z52: 0 | AA52: 46126 | AB52: =HYPERLINK("#'Transactions'!A179", "View Source Row")
A53: 181 | B53: 502 input.pdf | C53: 46113 | D53: 46142 | E53: 46126 | F53: 46126 | G53: EBANK:WIB/1504 EBANK:WIB/1504010401/Edfs | I53: Payment | J53: 240000 | K53: 0 | L53: 240000 | M53: 2325 | N53: High Transaction; Recurring Transaction | O53: Yes | P53: EBANKWIB | Q53: 0 | R53: 1 | S53: 0 | T53: 0 | U53: 1 | V53: 0 | W53: 0 | X53: 0 | Y53: 0 | Z53: 0 | AA53: 46126 | AB53: =HYPERLINK("#'Transactions'!A182", "View Source Row")
A54: 182 | B54: 502 input.pdf | C54: 46113 | D54: 46142 | E54: 46127 | F54: 46127 | G54: DIGITA-MUMBAI/ NEFT-YESAP61053875611-PhonePe Limited | I54: Receipt | J54: 0 | K54: 289276.57 | L54: 289276.57 | M54: 291601.57 | N54: High Transaction; Recurring Transaction | O54: Yes | P54: PHONEPE LIMITED | Q54: 0 | R54: 1 | S54: 0 | T54: 0 | U54: 1 | V54: 0 | W54: 0 | X54: 0 | Y54: 0 | Z54: 0 | AA54: 46127 | AB54: =HYPERLINK("#'Transactions'!A183", "View Source Row")
A55: 183 | B55: 502 input.pdf | C55: 46113 | D55: 46142 | E55: 46127 | F55: 46127 | G55: DIGITA-MUMBAI/ NEFT-AXNPN10512169091-PHONEPE LIMITED-PAYMENT AGGR | I55: Receipt | J55: 0 | K55: 106410 | L55: 106410 | M55: 398011.57 | N55: High Transaction; Recurring Transaction | O55: Yes | P55: PHONEPE LIMITED | Q55: 0 | R55: 1 | S55: 0 | T55: 0 | U55: 1 | V55: 0 | W55: 0 | X55: 0 | Y55: 0 | Z55: 0 | AA55: 46127 | AB55: =HYPERLINK("#'Transactions'!A184", "View Source Row")
A56: 185 | B56: 502 input.pdf | C56: 46113 | D56: 46142 | E56: 46127 | F56: 46127 | G56: EBANK:WIB/1504 ---------------------------------------------------------------------------------------------------------------------------------- Page Total: 10,80,213.22 10,50,213.22 10,500.00Cr ---------------------------------------------------------------------------------------------------------------------------------- Note: Cheques received in inward clearing will be considered for debiting/ returning on the basis opening balance in account Unless the constituent notifies the bank of any | I56: Payment | J56: 401141.57 | K56: 0 | L56: 401141.57 | M56: 10500 | N56: High Transaction; Recurring Transaction | O56: Yes | P56: EBANKWIB | Q56: 0 | R56: 1 | S56: 0 | T56: 0 | U56: 1 | V56: 0 | W56: 0 | X56: 0 | Y56: 0 | Z56: 0 | AA56: 46127 | AB56: =HYPERLINK("#'Transactions'!A186", "View Source Row")
A57: 191 | B57: 502 input.pdf | C57: 46113 | D57: 46142 | E57: 46127 | F57: 46127 | G57: EBANK:WIB/1504 EBANK:WIB/1504096201/Edfs | I57: Payment | J57: 125424 | K57: 0 | L57: 125424 | M57: 2500.8 | N57: High Transaction; Recurring Transaction | O57: Yes | P57: EBANKWIB | Q57: 0 | R57: 1 | S57: 0 | T57: 0 | U57: 1 | V57: 0 | W57: 0 | X57: 0 | Y57: 0 | Z57: 0 | AA57: 46127 | AB57: =HYPERLINK("#'Transactions'!A192", "View Source Row")
A58: 200 | B58: 502 input.pdf | C58: 46113 | D58: 46142 | E58: 46128 | F58: 46128 | G58: DIGITA-MUMBAI/ NEFT-YESAP61062741163-PhonePe Limited ---------------------------------------------------------------------------------------------------------------------------------- Page Total: 2,37,908.80 4,69,664.80 2,42,256.00Cr ---------------------------------------------------------------------------------------------------------------------------------- Note: Cheques received in inward clearing will be considered for debiting/ returning on the basis opening balance in account Unless the | I58: Receipt | J58: 0 | K58: 239756 | L58: 239756 | M58: 242256 | N58: High Transaction; Recurring Transaction | O58: Yes | P58: PHONEPE LIMITED | Q58: 0 | R58: 1 | S58: 0 | T58: 0 | U58: 1 | V58: 0 | W58: 0 | X58: 0 | Y58: 0 | Z58: 0 | AA58: 46128 | AB58: =HYPERLINK("#'Transactions'!A201", "View Source Row")
A59: 203 | B59: 502 input.pdf | C59: 46113 | D59: 46142 | E59: 46128 | F59: 46128 | G59: DIGITA-MUMBAI/ NEFT-AXISCN1312996692-PINE LABS PRIVATE LIMITED-NO | I59: Receipt | J59: 0 | K59: 250421 | L59: 250421 | M59: 568937.78 | N59: High Transaction; Recurring Transaction | O59: Yes | P59: PINE LABS PRIVATE LIMITED | Q59: 0 | R59: 1 | S59: 0 | T59: 0 | U59: 1 | V59: 0 | W59: 0 | X59: 0 | Y59: 0 | Z59: 0 | AA59: 46128 | AB59: =HYPERLINK("#'Transactions'!A204", "View Source Row")
A60: 205 | B60: 502 input.pdf | C60: 46113 | D60: 46142 | E60: 46128 | F60: 46128 | G60: RTGS-UBINR2202 RTGS-UBINR22026041601283543-SAPNA BUILDING MATERIA | I60: Receipt | J60: 0 | K60: 200000 | L60: 200000 | M60: 834958.78 | N60: High Transaction | O60: No | P60: UBINR RTGS | Q60: 0 | R60: 0 | S60: 0 | T60: 0 | U60: 1 | V60: 0 | W60: 0 | X60: 0 | Y60: 0 | Z60: 0 | AA60: 46128 | AB60: =HYPERLINK("#'Transactions'!A206", "View Source Row")
A61: 208 | B61: 502 input.pdf | C61: 46113 | D61: 46142 | E61: 46128 | F61: 46128 | G61: EBANK:WIB/1504 EBANK:WIB/1504268202/Edfs | I61: Payment | J61: 898173.78 | K61: 0 | L61: 898173.78 | M61: 2500 | N61: High Transaction; Recurring Transaction | O61: Yes | P61: EBANKWIB | Q61: 0 | R61: 1 | S61: 0 | T61: 0 | U61: 1 | V61: 0 | W61: 0 | X61: 0 | Y61: 0 | Z61: 0 | AA61: 46128 | AB61: =HYPERLINK("#'Transactions'!A209", "View Source Row")
A62: 210 | B62: 502 input.pdf | C62: 46113 | D62: 46142 | E62: 46129 | F62: 46129 | G62: DIGITA-MUMBAI/ NEFT-YESAP61072570192-PhonePe Limited | I62: Receipt | J62: 0 | K62: 249326.76 | L62: 249326.76 | M62: 258076.76 | N62: High Transaction; Recurring Transaction | O62: Yes | P62: PHONEPE LIMITED | Q62: 0 | R62: 1 | S62: 0 | T62: 0 | U62: 1 | V62: 0 | W62: 0 | X62: 0 | Y62: 0 | Z62: 0 | AA62: 46129 | AB62: =HYPERLINK("#'Transactions'!A211", "View Source Row")
A63: 212 | B63: 502 input.pdf | C63: 46113 | D63: 46142 | E63: 46129 | F63: 46129 | G63: EBANK:WIB/1504 EBANK:WIB/1504347697/Edfs | I63: Payment | J63: 328514.76 | K63: 0 | L63: 328514.76 | M63: 2500 | N63: High Transaction; Recurring Transaction | O63: Yes | P63: EBANKWIB | Q63: 0 | R63: 1 | S63: 0 | T63: 0 | U63: 1 | V63: 0 | W63: 0 | X63: 0 | Y63: 0 | Z63: 0 | AA63: 46129 | AB63: =HYPERLINK("#'Transactions'!A213", "View Source Row")
A64: 217 | B64: 502 input.pdf | C64: 46113 | D64: 46142 | E64: 46129 | F64: 46129 | G64: EBANK:WIB/1504 EBANK:WIB/1504424773/Edfs | I64: Payment | J64: 150000 | K64: 0 | L64: 150000 | M64: 5268 | N64: High Transaction; Recurring Transaction | O64: Yes | P64: EBANKWIB | Q64: 0 | R64: 1 | S64: 0 | T64: 0 | U64: 1 | V64: 0 | W64: 0 | X64: 0 | Y64: 0 | Z64: 0 | AA64: 46129 | AB64: =HYPERLINK("#'Transactions'!A218", "View Source Row")
A65: 220 | B65: 502 input.pdf | C65: 46113 | D65: 46142 | E65: 46130 | F65: 46130 | G65: DIGITA-MUMBAI/ NEFT-YESAP61082703898-PhonePe Limited | I65: Receipt | J65: 0 | K65: 219193 | L65: 219193 | M65: 283765 | N65: High Transaction; Recurring Transaction | O65: Yes | P65: PHONEPE LIMITED | Q65: 0 | R65: 1 | S65: 0 | T65: 0 | U65: 1 | V65: 0 | W65: 0 | X65: 0 | Y65: 0 | Z65: 0 | AA65: 46130 | AB65: =HYPERLINK("#'Transactions'!A221", "View Source Row")
A66: 227 | B66: 502 input.pdf | C66: 46113 | D66: 46142 | E66: 46130 | F66: 46130 | G66: EBANK:WIB/1504 EBANK:WIB/1504650433/Edfs | I66: Payment | J66: 480667.28 | K66: 0 | L66: 480667.28 | M66: 2500 | N66: High Transaction; Recurring Transaction | O66: Yes | P66: EBANKWIB | Q66: 0 | R66: 1 | S66: 0 | T66: 0 | U66: 1 | V66: 0 | W66: 0 | X66: 0 | Y66: 0 | Z66: 0 | AA66: 46130 | AB66: =HYPERLINK("#'Transactions'!A228", "View Source Row")
A67: 229 | B67: 502 input.pdf | C67: 46113 | D67: 46142 | E67: 46131 | F67: 46131 | G67: DIGITA-MUMBAI/ NEFT-YESAP61090338379-PhonePe Limited https://cbdrpt101.bankofbaroda.co.in:22000/finbranch/arjspmorph/INFENG/tran_rpt.jsp?... 04-05-2026 | I67: Receipt | J67: 0 | K67: 218422 | L67: 218422 | M67: 287433 | N67: High Transaction | O67: No | P67: PHONEPE LIMITED HTTPS | Q67: 0 | R67: 0 | S67: 0 | T67: 0 | U67: 1 | V67: 0 | W67: 0 | X67: 0 | Y67: 0 | Z67: 0 | AA67: 46131 | AB67: =HYPERLINK("#'Transactions'!A230", "View Source Row")
A68: 231 | B68: 502 input.pdf | C68: 46113 | D68: 46142 | E68: 46131 | F68: 46131 | G68: EBANK:WIB/1504 EBANK:WIB/1504657570/Edfs | I68: Payment | J68: 259433 | K68: 0 | L68: 259433 | M68: 30500 | N68: High Transaction; Recurring Transaction | O68: Yes | P68: EBANKWIB | Q68: 0 | R68: 1 | S68: 0 | T68: 0 | U68: 1 | V68: 0 | W68: 0 | X68: 0 | Y68: 0 | Z68: 0 | AA68: 46131 | AB68: =HYPERLINK("#'Transactions'!A232", "View Source Row")
A69: 238 | B69: 502 input.pdf | C69: 46113 | D69: 46142 | E69: 46131 | F69: 46131 | G69: EBANK:WIB/1504 EBANK:WIB/1504707135/Edfs | I69: Payment | J69: 211310.53 | K69: 0 | L69: 211310.53 | M69: 2500 | N69: High Transaction; Recurring Transaction | O69: Yes | P69: EBANKWIB | Q69: 0 | R69: 1 | S69: 0 | T69: 0 | U69: 1 | V69: 0 | W69: 0 | X69: 0 | Y69: 0 | Z69: 0 | AA69: 46131 | AB69: =HYPERLINK("#'Transactions'!A239", "View Source Row")
A70: 239 | B70: 502 input.pdf | C70: 46113 | D70: 46142 | E70: 46132 | F70: 46132 | G70: DIGITA-MUMBAI/ NEFT-YESAP61103651332-PhonePe Limited | I70: Receipt | J70: 0 | K70: 174695.6 | L70: 174695.6 | M70: 177195.6 | N70: High Transaction; Recurring Transaction | O70: Yes | P70: PHONEPE LIMITED | Q70: 0 | R70: 1 | S70: 0 | T70: 0 | U70: 1 | V70: 0 | W70: 0 | X70: 0 | Y70: 0 | Z70: 0 | AA70: 46132 | AB70: =HYPERLINK("#'Transactions'!A240", "View Source Row")
A71: 241 | B71: 502 input.pdf | C71: 46113 | D71: 46142 | E71: 46132 | F71: 46132 | G71: EBANK:WIB/1504 EBANK:WIB/1504717278/Edfs | I71: Payment | J71: 260572.52 | K71: 0 | L71: 260572.52 | M71: 3500 | N71: High Transaction; Recurring Transaction | O71: Yes | P71: EBANKWIB | Q71: 0 | R71: 1 | S71: 0 | T71: 0 | U71: 1 | V71: 0 | W71: 0 | X71: 0 | Y71: 0 | Z71: 0 | AA71: 46132 | AB71: =HYPERLINK("#'Transactions'!A242", "View Source Row")
A72: 250 | B72: 502 input.pdf | C72: 46113 | D72: 46142 | E72: 46132 | F72: 46132 | G72: DIGITA-MUMBAI/ NEFT-IN42611050112752-JERAI FITNESS LIMITED | I72: Receipt | J72: 0 | K72: 163337 | L72: 163337 | M72: 289584.78 | N72: High Transaction; Recurring Transaction | O72: Yes | P72: JERAI FITNESS LIMITED | Q72: 0 | R72: 1 | S72: 0 | T72: 0 | U72: 1 | V72: 0 | W72: 0 | X72: 0 | Y72: 0 | Z72: 0 | AA72: 46132 | AB72: =HYPERLINK("#'Transactions'!A251", "View Source Row")
A73: 251 | B73: 502 input.pdf | C73: 46113 | D73: 46142 | E73: 46132 | F73: 46132 | G73: EBANK:WIB/1504 EBANK:WIB/1504868004/Edfs | I73: Payment | J73: 287084.78 | K73: 0 | L73: 287084.78 | M73: 2500 | N73: High Transaction; Recurring Transaction | O73: Yes | P73: EBANKWIB | Q73: 0 | R73: 1 | S73: 0 | T73: 0 | U73: 1 | V73: 0 | W73: 0 | X73: 0 | Y73: 0 | Z73: 0 | AA73: 46132 | AB73: =HYPERLINK("#'Transactions'!A252", "View Source Row")
A74: 253 | B74: 502 input.pdf | C74: 46113 | D74: 46142 | E74: 46133 | F74: 46133 | G74: DIGITA-MUMBAI/ NEFT-YESAP61112557088-PhonePe Limited | I74: Receipt | J74: 0 | K74: 252575.92 | L74: 252575.92 | M74: 265075.92 | N74: High Transaction; Recurring Transaction | O74: Yes | P74: PHONEPE LIMITED | Q74: 0 | R74: 1 | S74: 0 | T74: 0 | U74: 1 | V74: 0 | W74: 0 | X74: 0 | Y74: 0 | Z74: 0 | AA74: 46133 | AB74: =HYPERLINK("#'Transactions'!A254", "View Source Row")
A75: 255 | B75: 502 input.pdf | C75: 46113 | D75: 46142 | E75: 46133 | F75: 46133 | G75: EBANK:WIB/1504 EBANK:WIB/1504892301/Edfs | I75: Payment | J75: 333445.92 | K75: 0 | L75: 333445.92 | M75: 2500 | N75: High Transaction; Recurring Transaction | O75: Yes | P75: EBANKWIB | Q75: 0 | R75: 1 | S75: 0 | T75: 0 | U75: 1 | V75: 0 | W75: 0 | X75: 0 | Y75: 0 | Z75: 0 | AA75: 46133 | AB75: =HYPERLINK("#'Transactions'!A256", "View Source Row")
A76: 263 | B76: 502 input.pdf | C76: 46113 | D76: 46142 | E76: 46133 | F76: 46133 | G76: EBANK:WIB/1505 ---------------------------------------------------------------------------------------------------------------------------------- Page Total: 7,30,619.40 6,18,011.62 2,500.00Cr ---------------------------------------------------------------------------------------------------------------------------------- Note: Cheques received in inward clearing will be considered for debiting/ returning on the basis opening balance in account Unless the constituent notifies the bank of any dis | I76: Payment | J76: 108963.7 | K76: 0 | L76: 108963.7 | M76: 2500 | N76: High Transaction; Recurring Transaction | O76: Yes | P76: EBANKWIB | Q76: 0 | R76: 1 | S76: 0 | T76: 0 | U76: 1 | V76: 0 | W76: 0 | X76: 0 | Y76: 0 | Z76: 0 | AA76: 46133 | AB76: =HYPERLINK("#'Transactions'!A264", "View Source Row")
A77: 265 | B77: 502 input.pdf | C77: 46113 | D77: 46142 | E77: 46134 | F77: 46134 | G77: DIGITA-MUMBAI/ NEFT-YESAP61123591632-PhonePe Limited | I77: Receipt | J77: 0 | K77: 195840 | L77: 195840 | M77: 203340 | N77: High Transaction; Recurring Transaction | O77: Yes | P77: PHONEPE LIMITED | Q77: 0 | R77: 1 | S77: 0 | T77: 0 | U77: 1 | V77: 0 | W77: 0 | X77: 0 | Y77: 0 | Z77: 0 | AA77: 46134 | AB77: =HYPERLINK("#'Transactions'!A266", "View Source Row")
A78: 268 | B78: 502 input.pdf | C78: 46113 | D78: 46142 | E78: 46134 | F78: 46134 | G78: EBANK:WIB/1505 EBANK:WIB/1505048812/Edfs | I78: Payment | J78: 259307.24 | K78: 0 | L78: 259307.24 | M78: 20500 | N78: High Transaction; Recurring Transaction | O78: Yes | P78: EBANKWIB | Q78: 0 | R78: 1 | S78: 0 | T78: 0 | U78: 1 | V78: 0 | W78: 0 | X78: 0 | Y78: 0 | Z78: 0 | AA78: 46134 | AB78: =HYPERLINK("#'Transactions'!A269", "View Source Row")
A79: 272 | B79: 502 input.pdf | C79: 46113 | D79: 46142 | E79: 46134 | F79: 46134 | G79: DIGITA-MUMBAI/ NEFT-CNRBH00126857051-M S COLLEGE OF PHARMACY | I79: Receipt | J79: 0 | K79: 100000 | L79: 100000 | M79: 216698 | N79: High Transaction | O79: No | P79: M S COLLEGE OF PHARMACY | Q79: 0 | R79: 0 | S79: 0 | T79: 0 | U79: 1 | V79: 0 | W79: 0 | X79: 0 | Y79: 0 | Z79: 0 | AA79: 46134 | AB79: =HYPERLINK("#'Transactions'!A273", "View Source Row")
A80: 277 | B80: 502 input.pdf | C80: 46113 | D80: 46142 | E80: 46134 | F80: 46134 | G80: EBANK:WIB/1505 EBANK:WIB/1505171210/Edfs | I80: Payment | J80: 356256.8 | K80: 0 | L80: 356256.8 | M80: 2500 | N80: High Transaction; Recurring Transaction | O80: Yes | P80: EBANKWIB | Q80: 0 | R80: 1 | S80: 0 | T80: 0 | U80: 1 | V80: 0 | W80: 0 | X80: 0 | Y80: 0 | Z80: 0 | AA80: 46134 | AB80: =HYPERLINK("#'Transactions'!A278", "View Source Row")
A81: 280 | B81: 502 input.pdf | C81: 46113 | D81: 46142 | E81: 46135 | F81: 46135 | G81: DIGITA-MUMBAI/ NEFT-YESAP61133866852-PhonePe Limited | I81: Receipt | J81: 0 | K81: 224683 | L81: 224683 | M81: 227183 | N81: High Transaction; Recurring Transaction | O81: Yes | P81: PHONEPE LIMITED | Q81: 0 | R81: 1 | S81: 0 | T81: 0 | U81: 1 | V81: 0 | W81: 0 | X81: 0 | Y81: 0 | Z81: 0 | AA81: 46135 | AB81: =HYPERLINK("#'Transactions'!A281", "View Source Row")
A82: 281 | B82: 502 input.pdf | C82: 46113 | D82: 46142 | E82: 46135 | F82: 46135 | G82: EBANK:WIB/1505 EBANK:WIB/1505193929/Edfs | I82: Payment | J82: 224683 | K82: 0 | L82: 224683 | M82: 2500 | N82: High Transaction; Recurring Transaction | O82: Yes | P82: EBANKWIB | Q82: 0 | R82: 1 | S82: 0 | T82: 0 | U82: 1 | V82: 0 | W82: 0 | X82: 0 | Y82: 0 | Z82: 0 | AA82: 46135 | AB82: =HYPERLINK("#'Transactions'!A282", "View Source Row")
A83: 285 | B83: 502 input.pdf | C83: 46113 | D83: 46142 | E83: 46135 | F83: 46135 | G83: DIGITA-MUMBAI/ NEFT-AXISCN1322079433-PINE LABS PRIVATE LIMITED-NO | I83: Receipt | J83: 0 | K83: 214974 | L83: 214974 | M83: 226804 | N83: High Transaction; Recurring Transaction | O83: Yes | P83: PINE LABS PRIVATE LIMITED | Q83: 0 | R83: 1 | S83: 0 | T83: 0 | U83: 1 | V83: 0 | W83: 0 | X83: 0 | Y83: 0 | Z83: 0 | AA83: 46135 | AB83: =HYPERLINK("#'Transactions'!A286", "View Source Row")
A84: 287 | B84: 502 input.pdf | C84: 46113 | D84: 46142 | E84: 46135 | F84: 46135 | G84: EBANK:WIB/1505 EBANK:WIB/1505205959/Edfs | I84: Payment | J84: 269000 | K84: 0 | L84: 269000 | M84: 3024 | N84: High Transaction; Recurring Transaction | O84: Yes | P84: EBANKWIB | Q84: 0 | R84: 1 | S84: 0 | T84: 0 | U84: 1 | V84: 0 | W84: 0 | X84: 0 | Y84: 0 | Z84: 0 | AA84: 46135 | AB84: =HYPERLINK("#'Transactions'!A288", "View Source Row")
A85: 290 | B85: 502 input.pdf | C85: 46113 | D85: 46142 | E85: 46135 | F85: 46135 | G85: DIGITA-MUMBAI/ NEFT-AXODH11383366299-GRISHMA METAL TECHNOLOGY | I85: Receipt | J85: 0 | K85: 124000 | L85: 124000 | M85: 126021.35 | N85: High Transaction; Recurring Transaction | O85: Yes | P85: GRISHMA METAL TECHNOLOGY | Q85: 0 | R85: 1 | S85: 0 | T85: 0 | U85: 1 | V85: 0 | W85: 0 | X85: 0 | Y85: 0 | Z85: 0 | AA85: 46135 | AB85: =HYPERLINK("#'Transactions'!A291", "View Source Row")
A86: 296 | B86: 502 input.pdf | C86: 46113 | D86: 46142 | E86: 46135 | F86: 46135 | G86: EBANK:WIB/1505 EBANK:WIB/1505315722/Edfs | I86: Payment | J86: 222635.35 | K86: 0 | L86: 222635.35 | M86: 2500 | N86: High Transaction; Recurring Transaction | O86: Yes | P86: EBANKWIB | Q86: 0 | R86: 1 | S86: 0 | T86: 0 | U86: 1 | V86: 0 | W86: 0 | X86: 0 | Y86: 0 | Z86: 0 | AA86: 46135 | AB86: =HYPERLINK("#'Transactions'!A297", "View Source Row")
A87: 297 | B87: 502 input.pdf | C87: 46113 | D87: 46142 | E87: 46136 | F87: 46136 | G87: DIGITA-MUMBAI/ NEFT-YESAP61143829163-PhonePe Limited | I87: Receipt | J87: 0 | K87: 234281 | L87: 234281 | M87: 236781 | N87: High Transaction; Recurring Transaction | O87: Yes | P87: PHONEPE LIMITED | Q87: 0 | R87: 1 | S87: 0 | T87: 0 | U87: 1 | V87: 0 | W87: 0 | X87: 0 | Y87: 0 | Z87: 0 | AA87: 46136 | AB87: =HYPERLINK("#'Transactions'!A298", "View Source Row")
A88: 301 | B88: 502 input.pdf | C88: 46113 | D88: 46142 | E88: 46136 | F88: 46136 | G88: EBANK:WIB/1505 EBANK:WIB/1505337172/Edfs | I88: Payment | J88: 400403 | K88: 0 | L88: 400403 | M88: 11500 | N88: High Transaction; Recurring Transaction | O88: Yes | P88: EBANKWIB | Q88: 0 | R88: 1 | S88: 0 | T88: 0 | U88: 1 | V88: 0 | W88: 0 | X88: 0 | Y88: 0 | Z88: 0 | AA88: 46136 | AB88: =HYPERLINK("#'Transactions'!A302", "View Source Row")
A89: 308 | B89: 502 input.pdf | C89: 46113 | D89: 46142 | E89: 46136 | F89: 46136 | G89: EBANK:WIB/1505 EBANK:WIB/1505452714/Edfs | I89: Payment | J89: 115069 | K89: 0 | L89: 115069 | M89: 2500 | N89: High Transaction; Recurring Transaction | O89: Yes | P89: EBANKWIB | Q89: 0 | R89: 1 | S89: 0 | T89: 0 | U89: 1 | V89: 0 | W89: 0 | X89: 0 | Y89: 0 | Z89: 0 | AA89: 46136 | AB89: =HYPERLINK("#'Transactions'!A309", "View Source Row")
A90: 309 | B90: 502 input.pdf | C90: 46113 | D90: 46142 | E90: 46137 | F90: 46137 | G90: DIGITA-MUMBAI/ NEFT-YESAP61152331743-PhonePe Limited | I90: Receipt | J90: 0 | K90: 273418 | L90: 273418 | M90: 275918 | N90: High Transaction; Recurring Transaction | O90: Yes | P90: PHONEPE LIMITED | Q90: 0 | R90: 1 | S90: 0 | T90: 0 | U90: 1 | V90: 0 | W90: 0 | X90: 0 | Y90: 0 | Z90: 0 | AA90: 46137 | AB90: =HYPERLINK("#'Transactions'!A310", "View Source Row")
A91: 310 | B91: 502 input.pdf | C91: 46113 | D91: 46142 | E91: 46137 | F91: 46137 | G91: EBANK:WIB/1505 ---------------------------------------------------------------------------------------------------------------------------------- Page Total: 10,24,774.35 8,33,793.00 2,500.00Cr ---------------------------------------------------------------------------------------------------------------------------------- Note: Cheques received in inward clearing will be considered for debiting/ returning on the basis opening balance in account Unless the constituent notifies the bank of any di | I91: Payment | J91: 273418 | K91: 0 | L91: 273418 | M91: 2500 | N91: High Transaction; Recurring Transaction | O91: Yes | P91: EBANKWIB | Q91: 0 | R91: 1 | S91: 0 | T91: 0 | U91: 1 | V91: 0 | W91: 0 | X91: 0 | Y91: 0 | Z91: 0 | AA91: 46137 | AB91: =HYPERLINK("#'Transactions'!A311", "View Source Row")
A92: 318 | B92: 502 input.pdf | C92: 46113 | D92: 46142 | E92: 46137 | F92: 46137 | G92: DIGITA-MUMBAI/ IMPS/P2A/611513033420/VILLAGE STONE L/Diesel paym | I92: Receipt | J92: 0 | K92: 100000 | L92: 100000 | M92: 138944.05 | N92: High Transaction; Recurring Transaction | O92: Yes | P92: VILLAGE STONE L | Q92: 0 | R92: 1 | S92: 0 | T92: 0 | U92: 1 | V92: 0 | W92: 0 | X92: 0 | Y92: 0 | Z92: 0 | AA92: 46137 | AB92: =HYPERLINK("#'Transactions'!A319", "View Source Row")
A93: 322 | B93: 502 input.pdf | C93: 46113 | D93: 46142 | E93: 46137 | F93: 46137 | G93: EBANK:WIB/1505 EBANK:WIB/1505585919/Edfs | I93: Payment | J93: 172247.15 | K93: 0 | L93: 172247.15 | M93: 2500 | N93: High Transaction; Recurring Transaction | O93: Yes | P93: EBANKWIB | Q93: 0 | R93: 1 | S93: 0 | T93: 0 | U93: 1 | V93: 0 | W93: 0 | X93: 0 | Y93: 0 | Z93: 0 | AA93: 46137 | AB93: =HYPERLINK("#'Transactions'!A323", "View Source Row")
A94: 323 | B94: 502 input.pdf | C94: 46113 | D94: 46142 | E94: 46138 | F94: 46138 | G94: DIGITA-MUMBAI/ NEFT-YESAP61163896825-PhonePe Limited | I94: Receipt | J94: 0 | K94: 244934 | L94: 244934 | M94: 247434 | N94: High Transaction; Recurring Transaction | O94: Yes | P94: PHONEPE LIMITED | Q94: 0 | R94: 1 | S94: 0 | T94: 0 | U94: 1 | V94: 0 | W94: 0 | X94: 0 | Y94: 0 | Z94: 0 | AA94: 46138 | AB94: =HYPERLINK("#'Transactions'!A324", "View Source Row")
A95: 324 | B95: 502 input.pdf | C95: 46113 | D95: 46142 | E95: 46138 | F95: 46138 | G95: DIGITA-MUMBAI/ NEFT-AXNPN11607066053-PHONEPE LIMITED-PAYMENT AGGR | I95: Receipt | J95: 0 | K95: 100291.79 | L95: 100291.79 | M95: 347725.79 | N95: High Transaction; Recurring Transaction | O95: Yes | P95: PHONEPE LIMITED | Q95: 0 | R95: 1 | S95: 0 | T95: 0 | U95: 1 | V95: 0 | W95: 0 | X95: 0 | Y95: 0 | Z95: 0 | AA95: 46138 | AB95: =HYPERLINK("#'Transactions'!A325", "View Source Row")
A96: 326 | B96: 502 input.pdf | C96: 46113 | D96: 46142 | E96: 46138 | F96: 46138 | G96: EBANK:WIB/1505 ---------------------------------------------------------------------------------------------------------------------------------- Page Total: 5,67,777.82 6,15,777.82 50,500.00Cr ---------------------------------------------------------------------------------------------------------------------------------- Note: Cheques received in inward clearing will be considered for debiting/ returning on the basis opening balance in account Unless the constituent notifies the bank of any di | I96: Payment | J96: 300990.79 | K96: 0 | L96: 300990.79 | M96: 50500 | N96: High Transaction; Recurring Transaction | O96: Yes | P96: EBANKWIB | Q96: 0 | R96: 1 | S96: 0 | T96: 0 | U96: 1 | V96: 0 | W96: 0 | X96: 0 | Y96: 0 | Z96: 0 | AA96: 46138 | AB96: =HYPERLINK("#'Transactions'!A327", "View Source Row")
A97: 329 | B97: 502 input.pdf | C97: 46113 | D97: 46142 | E97: 46138 | F97: 46138 | G97: EBANK:WIB/1505 EBANK:WIB/1505633295/Edfs | I97: Payment | J97: 114728 | K97: 0 | L97: 114728 | M97: 2500 | N97: High Transaction; Recurring Transaction | O97: Yes | P97: EBANKWIB | Q97: 0 | R97: 1 | S97: 0 | T97: 0 | U97: 1 | V97: 0 | W97: 0 | X97: 0 | Y97: 0 | Z97: 0 | AA97: 46138 | AB97: =HYPERLINK("#'Transactions'!A330", "View Source Row")
A98: 330 | B98: 502 input.pdf | C98: 46113 | D98: 46142 | E98: 46139 | F98: 46139 | G98: DIGITA-MUMBAI/ NEFT-YESAP61174218113-PhonePe Limited | I98: Receipt | J98: 0 | K98: 243320.8 | L98: 243320.8 | M98: 245820.8 | N98: High Transaction; Recurring Transaction | O98: Yes | P98: PHONEPE LIMITED | Q98: 0 | R98: 1 | S98: 0 | T98: 0 | U98: 1 | V98: 0 | W98: 0 | X98: 0 | Y98: 0 | Z98: 0 | AA98: 46139 | AB98: =HYPERLINK("#'Transactions'!A331", "View Source Row")
A99: 331 | B99: 502 input.pdf | C99: 46113 | D99: 46142 | E99: 46139 | F99: 46139 | G99: DIGITA-MUMBAI/ NEFT-AXNPN11714754008-PHONEPE LIMITED-PAYMENT AGGR | I99: Receipt | J99: 0 | K99: 109488 | L99: 109488 | M99: 355308.8 | N99: High Transaction; Recurring Transaction | O99: Yes | P99: PHONEPE LIMITED | Q99: 0 | R99: 1 | S99: 0 | T99: 0 | U99: 1 | V99: 0 | W99: 0 | X99: 0 | Y99: 0 | Z99: 0 | AA99: 46139 | AB99: =HYPERLINK("#'Transactions'!A332", "View Source Row")
A100: 335 | B100: 502 input.pdf | C100: 46113 | D100: 46142 | E100: 46139 | F100: 46139 | G100: EBANK:WIB/1505 EBANK:WIB/1505672686/Edfs | I100: Payment | J100: 460000.8 | K100: 0 | L100: 460000.8 | M100: 2317 | N100: High Transaction; Recurring Transaction | O100: Yes | P100: EBANKWIB | Q100: 0 | R100: 1 | S100: 0 | T100: 0 | U100: 1 | V100: 0 | W100: 0 | X100: 0 | Y100: 0 | Z100: 0 | AA100: 46139 | AB100: =HYPERLINK("#'Transactions'!A336", "View Source Row")
A101: 340 | B101: 502 input.pdf | C101: 46113 | D101: 46142 | E101: 46139 | F101: 46139 | G101: DIGITA-MUMBAI/ NEFT-BACBH00004205594-GAONDEVI BUILDING MATERIAL S | I101: Receipt | J101: 0 | K101: 150000 | L101: 150000 | M101: 311816 | N101: High Transaction | O101: No | P101: GAONDEVI BUILDING MATERIAL S | Q101: 0 | R101: 0 | S101: 0 | T101: 0 | U101: 1 | V101: 0 | W101: 0 | X101: 0 | Y101: 0 | Z101: 0 | AA101: 46139 | AB101: =HYPERLINK("#'Transactions'!A341", "View Source Row")
...

Sheet Detail Total Receipts and Payme
A1: =HYPERLINK("#'Dashboard'!A1", "← Return to Dashboard") | B1: Total Receipts and Payments Transactions
A2: Rows | B2: 398 | C2: Match | D2: All transactions
A4: Seq | B4: Source File | C4: Statement From | D4: Statement To | E4: Date | F4: Value Date | G4: Narration | H4: Reference | I4: Direction | J4: Withdrawal | K4: Deposit | L4: Amount | M4: Closing Balance | N4: Categories | O4: Recurring? | P4: Recurring Key | Q4: Flag - Cash | R4: Flag - Recurring Transaction | S4: Flag - EMI | T4: Flag - Salary | U4: Flag - High Transaction | V4: Flag - UPI | W4: Flag - LIC | X4: Flag - FD interest | Y4: Flag - FD Deposit and withdrawals | Z4: Flag - PPF/PF interest and contribution | AA4: Month Date | AB4: View Source Row
A5: 1 | B5: 502 input.pdf | C5: 46113 | D5: 46142 | E5: 46114 | F5: 46114 | G5: DIGITA-MUMBAI/ IMPS/P2A/609147096215/HONEPELIMITEDPA/F09Hpcljige | I5: Receipt | J5: 0 | K5: 53200 | L5: 53200 | M5: 416391 | N5: Other | O5: No | P5: HONEPELIMITEDPA | Q5: 0 | R5: 0 | S5: 0 | T5: 0 | U5: 0 | V5: 0 | W5: 0 | X5: 0 | Y5: 0 | Z5: 0 | AA5: 46114 | AB5: =HYPERLINK("#'Transactions'!A2", "View Source Row")
A6: 2 | B6: 502 input.pdf | C6: 46113 | D6: 46142 | E6: 46114 | F6: 46114 | G6: DIGITA-MUMBAI/ NEFT-YESAP60912594024-PhonePe Limited | I6: Receipt | J6: 0 | K6: 165179 | L6: 165179 | M6: 581570 | N6: High Transaction; Recurring Transaction | O6: Yes | P6: PHONEPE LIMITED | Q6: 0 | R6: 1 | S6: 0 | T6: 0 | U6: 1 | V6: 0 | W6: 0 | X6: 0 | Y6: 0 | Z6: 0 | AA6: 46114 | AB6: =HYPERLINK("#'Transactions'!A3", "View Source Row")
A7: 3 | B7: 502 input.pdf | C7: 46113 | D7: 46142 | E7: 46114 | F7: 46114 | G7: UPI/6091426275 42627513 UPI/609142627513/04:54:21/UPI/dineshjogle086-5@ok | I7: Payment | J7: 2356 | K7: 0 | L7: 2356 | M7: 579214 | N7: UPI | O7: No | P7: DINESHJOGLE | Q7: 0 | R7: 0 | S7: 0 | T7: 0 | U7: 0 | V7: 1 | W7: 0 | X7: 0 | Y7: 0 | Z7: 0 | AA7: 46114 | AB7: =HYPERLINK("#'Transactions'!A4", "View Source Row")
A8: 4 | B8: 502 input.pdf | C8: 46113 | D8: 46142 | E8: 46114 | F8: 46114 | G8: DIGITA-MUMBAI/ IMPS/P2A/609149979773/ONEMOBIKWIKSYST/IMPSAXB9100 | I8: Receipt | J8: 0 | K8: 35167.6 | L8: 35167.6 | M8: 614381.6 | N8: Other | O8: No | P8: ONEMOBIKWIKSYST | Q8: 0 | R8: 0 | S8: 0 | T8: 0 | U8: 0 | V8: 0 | W8: 0 | X8: 0 | Y8: 0 | Z8: 0 | AA8: 46114 | AB8: =HYPERLINK("#'Transactions'!A5", "View Source Row")
A9: 5 | B9: 502 input.pdf | C9: 46113 | D9: 46142 | E9: 46114 | F9: 46114 | G9: UPI/6091243743 24374374 UPI/609124374374/11:47:28/UPI/prasadconstruction2 | I9: Receipt | J9: 0 | K9: 70000 | L9: 70000 | M9: 684381.6 | N9: UPI | O9: No | P9: PRASADCONSTRUCTION | Q9: 0 | R9: 0 | S9: 0 | T9: 0 | U9: 0 | V9: 1 | W9: 0 | X9: 0 | Y9: 0 | Z9: 0 | AA9: 46114 | AB9: =HYPERLINK("#'Transactions'!A6", "View Source Row")
A10: 6 | B10: 502 input.pdf | C10: 46113 | D10: 46142 | E10: 46114 | F10: 46114 | G10: EBANK:WIB/1502 EBANK:WIB/1502021829/Edfs | I10: Payment | J10: 681881.6 | K10: 0 | L10: 681881.6 | M10: 2500 | N10: High Transaction; Recurring Transaction | O10: Yes | P10: EBANKWIB | Q10: 0 | R10: 1 | S10: 0 | T10: 0 | U10: 1 | V10: 0 | W10: 0 | X10: 0 | Y10: 0 | Z10: 0 | AA10: 46114 | AB10: =HYPERLINK("#'Transactions'!A7", "View Source Row")
A11: 7 | B11: 502 input.pdf | C11: 46113 | D11: 46142 | E11: 46114 | F11: 46114 | G11: DIGITA-MUMBAI/ NEFT-FBPT260916108327-PREMIER CONVEYORS PRIVATE LI | I11: Receipt | J11: 0 | K11: 18409 | L11: 18409 | M11: 20909 | N11: EMI; Recurring Transaction | O11: Yes | P11: PREMIER CONVEYORS PRIVATE LI | Q11: 0 | R11: 1 | S11: 1 | T11: 0 | U11: 0 | V11: 0 | W11: 0 | X11: 0 | Y11: 0 | Z11: 0 | AA11: 46114 | AB11: =HYPERLINK("#'Transactions'!A8", "View Source Row")
A12: 8 | B12: 502 input.pdf | C12: 46113 | D12: 46142 | E12: 46114 | F12: 46114 | G12: DIGITA-MUMBAI/ NEFT-CNRBH00121803213-QUALITY PLAST INDUSTRIES LIM | I12: Receipt | J12: 0 | K12: 121431 | L12: 121431 | M12: 142340 | N12: High Transaction; Recurring Transaction | O12: Yes | P12: QUALITY PLAST INDUSTRIES LIM | Q12: 0 | R12: 1 | S12: 0 | T12: 0 | U12: 1 | V12: 0 | W12: 0 | X12: 0 | Y12: 0 | Z12: 0 | AA12: 46114 | AB12: =HYPERLINK("#'Transactions'!A9", "View Source Row")
A13: 9 | B13: 502 input.pdf | C13: 46113 | D13: 46142 | E13: 46114 | F13: 46114 | G13: UPI/6091779614 77961475 UPI/609177961475/16:34:33/UPI/q297956037@ybl/food | I13: Payment | J13: 1500 | K13: 0 | L13: 1500 | M13: 140840 | N13: UPI | O13: No | P13: UPI/# # UPI/#/#:#:#/UPI/Q#@YBL/FOOD | Q13: 0 | R13: 0 | S13: 0 | T13: 0 | U13: 0 | V13: 1 | W13: 0 | X13: 0 | Y13: 0 | Z13: 0 | AA13: 46114 | AB13: =HYPERLINK("#'Transactions'!A10", "View Source Row")
A14: 10 | B14: 502 input.pdf | C14: 46113 | D14: 46142 | E14: 46114 | F14: 46114 | G14: DIGITA-MUMBAI/ IMPS/P2A/609116466512/AFZALSIRAJUDDIN/IMPSUOB9191 | I14: Receipt | J14: 0 | K14: 100000 | L14: 100000 | M14: 240840 | N14: High Transaction; Recurring Transaction | O14: Yes | P14: AFZALSIRAJUDDIN | Q14: 0 | R14: 1 | S14: 0 | T14: 0 | U14: 1 | V14: 0 | W14: 0 | X14: 0 | Y14: 0 | Z14: 0 | AA14: 46114 | AB14: =HYPERLINK("#'Transactions'!A11", "View Source Row")
A15: 11 | B15: 502 input.pdf | C15: 46113 | D15: 46142 | E15: 46114 | F15: 46114 | G15: DIGITA-MUMBAI/ NEFT-KKBKH26091970510-VENKTESHWAR INDUSTRIAL CORPO | I15: Receipt | J15: 0 | K15: 10000 | L15: 10000 | M15: 250840 | N15: Recurring Transaction | O15: Yes | P15: VENKTESHWAR INDUSTRIAL CORPO | Q15: 0 | R15: 1 | S15: 0 | T15: 0 | U15: 0 | V15: 0 | W15: 0 | X15: 0 | Y15: 0 | Z15: 0 | AA15: 46114 | AB15: =HYPERLINK("#'Transactions'!A12", "View Source Row")
A16: 12 | B16: 502 input.pdf | C16: 46113 | D16: 46142 | E16: 46114 | F16: 46114 | G16: EBANK:WIB/1502 ---------------------------------------------------------------------------------------------------------------------------------- Page Total: 9,34,077.60 5,73,386.60 2,500.00Cr ---------------------------------------------------------------------------------------------------------------------------------- Note: Cheques received in inward clearing will be considered for debiting/ returning on the basis opening balance in account Unless the constituent notifies the bank of any dis | I16: Payment | J16: 248340 | K16: 0 | L16: 248340 | M16: 2500 | N16: High Transaction; Recurring Transaction | O16: Yes | P16: EBANKWIB | Q16: 0 | R16: 1 | S16: 0 | T16: 0 | U16: 1 | V16: 0 | W16: 0 | X16: 0 | Y16: 0 | Z16: 0 | AA16: 46114 | AB16: =HYPERLINK("#'Transactions'!A13", "View Source Row")
A17: 13 | B17: 502 input.pdf | C17: 46113 | D17: 46142 | E17: 46114 | F17: 46114 | G17: DIGITA-MUMBAI/ NEFT-YESAP60924833309-PhonePe Limited | I17: Receipt | J17: 0 | K17: 188588.4 | L17: 188588.4 | M17: 191088.4 | N17: High Transaction; Recurring Transaction | O17: Yes | P17: PHONEPE LIMITED | Q17: 0 | R17: 1 | S17: 0 | T17: 0 | U17: 1 | V17: 0 | W17: 0 | X17: 0 | Y17: 0 | Z17: 0 | AA17: 46114 | AB17: =HYPERLINK("#'Transactions'!A14", "View Source Row")
A18: 14 | B18: 502 input.pdf | C18: 46113 | D18: 46142 | E18: 46114 | F18: 46114 | G18: DIGITA-MUMBAI/ NEFT-AXNPN09202196281-PHONEPE LIMITED-PAYMENT AGGR | I18: Receipt | J18: 0 | K18: 50884.1 | L18: 50884.1 | M18: 241972.5 | N18: Recurring Transaction | O18: Yes | P18: PHONEPE LIMITED | Q18: 0 | R18: 1 | S18: 0 | T18: 0 | U18: 0 | V18: 0 | W18: 0 | X18: 0 | Y18: 0 | Z18: 0 | AA18: 46114 | AB18: =HYPERLINK("#'Transactions'!A15", "View Source Row")
A19: 15 | B19: 502 input.pdf | C19: 46113 | D19: 46142 | E19: 46114 | F19: 46114 | G19: DIGITA-MUMBAI/ NEFT-AXISCN1298773772-ONE MOBIKWIK SYSTEMS LIMITED https://cbdrpt101.bankofbaroda.co.in:22000/finbranch/arjspmorph/INFENG/tran_rpt.jsp?... 04-05-2026 | I19: Receipt | J19: 0 | K19: 26312 | L19: 26312 | M19: 268284.5 | N19: Recurring Transaction | O19: Yes | P19: ONE MOBIKWIK SYSTEMS LIMITED HTTPS | Q19: 0 | R19: 1 | S19: 0 | T19: 0 | U19: 0 | V19: 0 | W19: 0 | X19: 0 | Y19: 0 | Z19: 0 | AA19: 46114 | AB19: =HYPERLINK("#'Transactions'!A16", "View Source Row")
A20: 16 | B20: 502 input.pdf | C20: 46113 | D20: 46142 | E20: 46114 | F20: 46114 | G20: DIGITA-MUMBAI/ IMPS/P2A/609208556385/OMSANITRANSPORT/IMPSUOB9195 | I20: Receipt | J20: 0 | K20: 16450 | L20: 16450 | M20: 284734.5 | N20: Recurring Transaction | O20: Yes | P20: OMSANITRANSPORT | Q20: 0 | R20: 1 | S20: 0 | T20: 0 | U20: 0 | V20: 0 | W20: 0 | X20: 0 | Y20: 0 | Z20: 0 | AA20: 46114 | AB20: =HYPERLINK("#'Transactions'!A17", "View Source Row")
A21: 17 | B21: 502 input.pdf | C21: 46113 | D21: 46142 | E21: 46114 | F21: 46114 | G21: DIGITA-MUMBAI/ NEFT-AXISCN1298906804-PINE LABS PRIVATE LIMITED-NO | I21: Receipt | J21: 0 | K21: 61903 | L21: 61903 | M21: 346637.5 | N21: Recurring Transaction | O21: Yes | P21: PINE LABS PRIVATE LIMITED | Q21: 0 | R21: 1 | S21: 0 | T21: 0 | U21: 0 | V21: 0 | W21: 0 | X21: 0 | Y21: 0 | Z21: 0 | AA21: 46114 | AB21: =HYPERLINK("#'Transactions'!A18", "View Source Row")
A22: 18 | B22: 502 input.pdf | C22: 46113 | D22: 46142 | E22: 46114 | F22: 46114 | G22: DIGITA-MUMBAI/ NEFT-AXISCN1299028324-PINE LABS PRIVATE LIMITED-NO | I22: Receipt | J22: 0 | K22: 166884 | L22: 166884 | M22: 513521.5 | N22: High Transaction; Recurring Transaction | O22: Yes | P22: PINE LABS PRIVATE LIMITED | Q22: 0 | R22: 1 | S22: 0 | T22: 0 | U22: 1 | V22: 0 | W22: 0 | X22: 0 | Y22: 0 | Z22: 0 | AA22: 46114 | AB22: =HYPERLINK("#'Transactions'!A19", "View Source Row")
A23: 19 | B23: 502 input.pdf | C23: 46113 | D23: 46142 | E23: 46114 | F23: 46114 | G23: UPI/6092378308 37830859 UPI/609237830859/11:20:36/UPI/9850754712-3@ybl/st | I23: Payment | J23: 4000 | K23: 0 | L23: 4000 | M23: 509521.5 | N23: UPI | O23: No | P23: UPI/# # UPI/#/#:#:#/UPI/#-#@YBL/ST | Q23: 0 | R23: 0 | S23: 0 | T23: 0 | U23: 0 | V23: 1 | W23: 0 | X23: 0 | Y23: 0 | Z23: 0 | AA23: 46114 | AB23: =HYPERLINK("#'Transactions'!A20", "View Source Row")
A24: 20 | B24: 502 input.pdf | C24: 46113 | D24: 46142 | E24: 46114 | F24: 46114 | G24: DIGITA-MUMBAI/ IMPS/P2A/609211135154/SHREE GANESH EN/dieselVVS91 | I24: Receipt | J24: 0 | K24: 63308 | L24: 63308 | M24: 572829.5 | N24: Recurring Transaction | O24: Yes | P24: SHREE GANESH EN | Q24: 0 | R24: 1 | S24: 0 | T24: 0 | U24: 0 | V24: 0 | W24: 0 | X24: 0 | Y24: 0 | Z24: 0 | AA24: 46114 | AB24: =HYPERLINK("#'Transactions'!A21", "View Source Row")
A25: 21 | B25: 502 input.pdf | C25: 46113 | D25: 46142 | E25: 46114 | F25: 46114 | G25: DIGITA-MUMBAI/ NEFT-KKBKH26092777992-VENKTESHWAR INDUSTRIAL CORPO | I25: Receipt | J25: 0 | K25: 18088 | L25: 18088 | M25: 590917.5 | N25: Recurring Transaction | O25: Yes | P25: VENKTESHWAR INDUSTRIAL CORPO | Q25: 0 | R25: 1 | S25: 0 | T25: 0 | U25: 0 | V25: 0 | W25: 0 | X25: 0 | Y25: 0 | Z25: 0 | AA25: 46114 | AB25: =HYPERLINK("#'Transactions'!A22", "View Source Row")
A26: 22 | B26: 502 input.pdf | C26: 46113 | D26: 46142 | E26: 46114 | F26: 46114 | G26: UPI/6092013389 1338963 UPI/609201338963/12:38:06/UPI/gpay-11193876450@ok | I26: Payment | J26: 2800 | K26: 0 | L26: 2800 | M26: 588117.5 | N26: UPI | O26: No | P26: UPI/# # UPI/#/#:#:#/UPI/GPAY-#@OK | Q26: 0 | R26: 0 | S26: 0 | T26: 0 | U26: 0 | V26: 1 | W26: 0 | X26: 0 | Y26: 0 | Z26: 0 | AA26: 46114 | AB26: =HYPERLINK("#'Transactions'!A23", "View Source Row")
A27: 23 | B27: 502 input.pdf | C27: 46113 | D27: 46142 | E27: 46114 | F27: 46114 | G27: DIGITA-MUMBAI/ NEFT-NKGSH26092846591-GEBI PRODUCTS PRIVATE LIMITE | I27: Receipt | J27: 0 | K27: 12813 | L27: 12813 | M27: 600930.5 | N27: Recurring Transaction | O27: Yes | P27: GEBI PRODUCTS PRIVATE LIMITE | Q27: 0 | R27: 1 | S27: 0 | T27: 0 | U27: 0 | V27: 0 | W27: 0 | X27: 0 | Y27: 0 | Z27: 0 | AA27: 46114 | AB27: =HYPERLINK("#'Transactions'!A24", "View Source Row")
A28: 24 | B28: 502 input.pdf | C28: 46113 | D28: 46142 | E28: 46114 | F28: 46114 | G28: DIGITA-MUMBAI/ NEFT-IDIBH09236262399-JAI AMBE TRANSPORT | I28: Receipt | J28: 0 | K28: 4378 | L28: 4378 | M28: 605308.5 | N28: Recurring Transaction | O28: Yes | P28: JAI AMBE TRANSPORT | Q28: 0 | R28: 1 | S28: 0 | T28: 0 | U28: 0 | V28: 0 | W28: 0 | X28: 0 | Y28: 0 | Z28: 0 | AA28: 46114 | AB28: =HYPERLINK("#'Transactions'!A25", "View Source Row")
A29: 25 | B29: 502 input.pdf | C29: 46113 | D29: 46142 | E29: 46114 | F29: 46114 | G29: DIGITA-MUMBAI/ NEFT-HDFCH00905140576-Adekar enterprises pvt ltd | I29: Receipt | J29: 0 | K29: 138674 | L29: 138674 | M29: 743982.5 | N29: High Transaction; Recurring Transaction | O29: Yes | P29: ADEKAR ENTERPRISES PVT LTD | Q29: 0 | R29: 1 | S29: 0 | T29: 0 | U29: 1 | V29: 0 | W29: 0 | X29: 0 | Y29: 0 | Z29: 0 | AA29: 46114 | AB29: =HYPERLINK("#'Transactions'!A26", "View Source Row")
A30: 26 | B30: 502 input.pdf | C30: 46113 | D30: 46142 | E30: 46114 | F30: 46114 | G30: DIGITA-MUMBAI/ NEFT-TDCBH26092001785-V C ENTERPRISES | I30: Receipt | J30: 0 | K30: 50000 | L30: 50000 | M30: 793982.5 | N30: Recurring Transaction | O30: Yes | P30: V C ENTERPRISES | Q30: 0 | R30: 1 | S30: 0 | T30: 0 | U30: 0 | V30: 0 | W30: 0 | X30: 0 | Y30: 0 | Z30: 0 | AA30: 46114 | AB30: =HYPERLINK("#'Transactions'!A27", "View Source Row")
A31: 27 | B31: 502 input.pdf | C31: 46113 | D31: 46142 | E31: 46114 | F31: 46114 | G31: EBANK:WIB/1502 EBANK:WIB/1502234210/Edfs | I31: Payment | J31: 791482.5 | K31: 0 | L31: 791482.5 | M31: 2500 | N31: High Transaction; Recurring Transaction | O31: Yes | P31: EBANKWIB | Q31: 0 | R31: 1 | S31: 0 | T31: 0 | U31: 1 | V31: 0 | W31: 0 | X31: 0 | Y31: 0 | Z31: 0 | AA31: 46114 | AB31: =HYPERLINK("#'Transactions'!A28", "View Source Row")
A32: 28 | B32: 502 input.pdf | C32: 46113 | D32: 46142 | E32: 46114 | F32: 46114 | G32: DIGITA-MUMBAI/ ---------------------------------------------------------------------------------------------------------------------------------- Page Total: 7,98,282.50 8,34,458.50 38,676.00Cr ---------------------------------------------------------------------------------------------------------------------------------- Note: Cheques received in inward clearing will be considered for debiting/ returning on the basis opening balance in account Unless the constituent notifies the bank of any di | I32: Receipt | J32: 0 | K32: 36176 | L32: 36176 | M32: 38676 | N32: Recurring Transaction | O32: Yes | P32: PAGE TOTAL CR | Q32: 0 | R32: 1 | S32: 0 | T32: 0 | U32: 0 | V32: 0 | W32: 0 | X32: 0 | Y32: 0 | Z32: 0 | AA32: 46114 | AB32: =HYPERLINK("#'Transactions'!A29", "View Source Row")
A33: 29 | B33: 502 input.pdf | C33: 46113 | D33: 46142 | E33: 46114 | F33: 46114 | G33: DIGITA-MUMBAI/ NEFT-KKBKH26092921670-ATLAS COMMODITIES PRIVATE LI | I33: Receipt | J33: 0 | K33: 4353 | L33: 4353 | M33: 43029 | N33: Recurring Transaction | O33: Yes | P33: ATLAS COMMODITIES PRIVATE LI | Q33: 0 | R33: 1 | S33: 0 | T33: 0 | U33: 0 | V33: 0 | W33: 0 | X33: 0 | Y33: 0 | Z33: 0 | AA33: 46114 | AB33: =HYPERLINK("#'Transactions'!A30", "View Source Row")
A34: 30 | B34: 502 input.pdf | C34: 46113 | D34: 46142 | E34: 46115 | F34: 46115 | G34: DIGITA-MUMBAI/ NEFT-YESAP60934071902-PhonePe Limited | I34: Receipt | J34: 0 | K34: 173393.9 | L34: 173393.9 | M34: 216422.9 | N34: High Transaction; Recurring Transaction | O34: Yes | P34: PHONEPE LIMITED | Q34: 0 | R34: 1 | S34: 0 | T34: 0 | U34: 1 | V34: 0 | W34: 0 | X34: 0 | Y34: 0 | Z34: 0 | AA34: 46115 | AB34: =HYPERLINK("#'Transactions'!A31", "View Source Row")
A35: 31 | B35: 502 input.pdf | C35: 46113 | D35: 46142 | E35: 46115 | F35: 46115 | G35: DIGITA-MUMBAI/ NEFT-AXNPN09311160907-PHONEPE LIMITED-PAYMENT AGGR | I35: Receipt | J35: 0 | K35: 53957.68 | L35: 53957.68 | M35: 270380.58 | N35: Recurring Transaction | O35: Yes | P35: PHONEPE LIMITED | Q35: 0 | R35: 1 | S35: 0 | T35: 0 | U35: 0 | V35: 0 | W35: 0 | X35: 0 | Y35: 0 | Z35: 0 | AA35: 46115 | AB35: =HYPERLINK("#'Transactions'!A32", "View Source Row")
A36: 32 | B36: 502 input.pdf | C36: 46113 | D36: 46142 | E36: 46115 | F36: 46115 | G36: DIGITA-MUMBAI/ NEFT-AXISCN1300289999-ONE MOBIKWIK SYSTEMS LIMITED | I36: Receipt | J36: 0 | K36: 21700 | L36: 21700 | M36: 292080.58 | N36: Recurring Transaction | O36: Yes | P36: ONE MOBIKWIK SYSTEMS LIMITED | Q36: 0 | R36: 1 | S36: 0 | T36: 0 | U36: 0 | V36: 0 | W36: 0 | X36: 0 | Y36: 0 | Z36: 0 | AA36: 46115 | AB36: =HYPERLINK("#'Transactions'!A33", "View Source Row")
A37: 33 | B37: 502 input.pdf | C37: 46113 | D37: 46142 | E37: 46115 | F37: 46115 | G37: DIGITA-MUMBAI/ IMPS/P2A/609308206742/S TRANS 14851/Mh04ju3738I | I37: Receipt | J37: 0 | K37: 5750 | L37: 5750 | M37: 297830.58 | N37: Recurring Transaction | O37: Yes | P37: DIGITA-MUMBAI/ IMPS/P#A/#/S TRANS #/MH#JU#I | Q37: 0 | R37: 1 | S37: 0 | T37: 0 | U37: 0 | V37: 0 | W37: 0 | X37: 0 | Y37: 0 | Z37: 0 | AA37: 46115 | AB37: =HYPERLINK("#'Transactions'!A34", "View Source Row")
A38: 34 | B38: 502 input.pdf | C38: 46113 | D38: 46142 | E38: 46115 | F38: 46115 | G38: DIGITA-MUMBAI/ NEFT-AXISCN1300388689-PINE LABS PRIVATE LIMITED-NO | I38: Receipt | J38: 0 | K38: 112894 | L38: 112894 | M38: 410724.58 | N38: High Transaction; Recurring Transaction | O38: Yes | P38: PINE LABS PRIVATE LIMITED | Q38: 0 | R38: 1 | S38: 0 | T38: 0 | U38: 1 | V38: 0 | W38: 0 | X38: 0 | Y38: 0 | Z38: 0 | AA38: 46115 | AB38: =HYPERLINK("#'Transactions'!A35", "View Source Row")
A39: 35 | B39: 502 input.pdf | C39: 46113 | D39: 46142 | E39: 46115 | F39: 46115 | G39: DIGITA-MUMBAI/ IMPS/P2A/609312855509/AFZALSIRAJUDDIN/IMPSUOB9191 | I39: Receipt | J39: 0 | K39: 200000 | L39: 200000 | M39: 610724.58 | N39: High Transaction; Recurring Transaction | O39: Yes | P39: AFZALSIRAJUDDIN | Q39: 0 | R39: 1 | S39: 0 | T39: 0 | U39: 1 | V39: 0 | W39: 0 | X39: 0 | Y39: 0 | Z39: 0 | AA39: 46115 | AB39: =HYPERLINK("#'Transactions'!A36", "View Source Row")
A40: 36 | B40: 502 input.pdf | C40: 46113 | D40: 46142 | E40: 46115 | F40: 46115 | G40: DIGITA-MUMBAI/ NEFT-002663976089-GANGAMAI INDUSTRIES AND CONSTR | I40: Receipt | J40: 0 | K40: 180880 | L40: 180880 | M40: 791604.58 | N40: High Transaction | O40: No | P40: GANGAMAI INDUSTRIES AND CONSTR | Q40: 0 | R40: 0 | S40: 0 | T40: 0 | U40: 1 | V40: 0 | W40: 0 | X40: 0 | Y40: 0 | Z40: 0 | AA40: 46115 | AB40: =HYPERLINK("#'Transactions'!A37", "View Source Row")
A41: 37 | B41: 502 input.pdf | C41: 46113 | D41: 46142 | E41: 46115 | F41: 46115 | G41: EBANK:WIB/1502 EBANK:WIB/1502413595/Edfs | I41: Payment | J41: 790104.58 | K41: 0 | L41: 790104.58 | M41: 1500 | N41: High Transaction; Recurring Transaction | O41: Yes | P41: EBANKWIB | Q41: 0 | R41: 1 | S41: 0 | T41: 0 | U41: 1 | V41: 0 | W41: 0 | X41: 0 | Y41: 0 | Z41: 0 | AA41: 46115 | AB41: =HYPERLINK("#'Transactions'!A38", "View Source Row")
A42: 38 | B42: 502 input.pdf | C42: 46113 | D42: 46142 | E42: 46116 | F42: 46116 | G42: DIGITA-MUMBAI/ NEFT-YESAP60944128518-PhonePe Limited | I42: Receipt | J42: 0 | K42: 171014 | L42: 171014 | M42: 172514 | N42: High Transaction; Recurring Transaction | O42: Yes | P42: PHONEPE LIMITED | Q42: 0 | R42: 1 | S42: 0 | T42: 0 | U42: 1 | V42: 0 | W42: 0 | X42: 0 | Y42: 0 | Z42: 0 | AA42: 46116 | AB42: =HYPERLINK("#'Transactions'!A39", "View Source Row")
A43: 39 | B43: 502 input.pdf | C43: 46113 | D43: 46142 | E43: 46116 | F43: 46116 | G43: DIGITA-MUMBAI/ https://cbdrpt101.bankofbaroda.co.in:22000/finbranch/arjspmorph/INFENG/tran_rpt.jsp?... 04-05-2026 NEFT-AXNPN09418938602-PHONEPE LIMITED-PAYMENT AGGR | I43: Receipt | J43: 0 | K43: 49956 | L43: 49956 | M43: 222470 | N43: Recurring Transaction | O43: Yes | P43: CBDRPTBANKOFBARODACOIN | Q43: 0 | R43: 1 | S43: 0 | T43: 0 | U43: 0 | V43: 0 | W43: 0 | X43: 0 | Y43: 0 | Z43: 0 | AA43: 46116 | AB43: =HYPERLINK("#'Transactions'!A40", "View Source Row")
A44: 40 | B44: 502 input.pdf | C44: 46113 | D44: 46142 | E44: 46116 | F44: 46116 | G44: DIGITA-MUMBAI/ NEFT-AXISCN1301100257-ONE MOBIKWIK SYSTEMS LIMITED | I44: Receipt | J44: 0 | K44: 22121 | L44: 22121 | M44: 244591 | N44: Recurring Transaction | O44: Yes | P44: ONE MOBIKWIK SYSTEMS LIMITED | Q44: 0 | R44: 1 | S44: 0 | T44: 0 | U44: 0 | V44: 0 | W44: 0 | X44: 0 | Y44: 0 | Z44: 0 | AA44: 46116 | AB44: =HYPERLINK("#'Transactions'!A41", "View Source Row")
A45: 41 | B45: 502 input.pdf | C45: 46113 | D45: 46142 | E45: 46116 | F45: 46116 | G45: EBANK:WIB/1502 EBANK:WIB/1502423934/Edfs | I45: Payment | J45: 240091 | K45: 0 | L45: 240091 | M45: 4500 | N45: High Transaction; Recurring Transaction | O45: Yes | P45: EBANKWIB | Q45: 0 | R45: 1 | S45: 0 | T45: 0 | U45: 1 | V45: 0 | W45: 0 | X45: 0 | Y45: 0 | Z45: 0 | AA45: 46116 | AB45: =HYPERLINK("#'Transactions'!A42", "View Source Row")
A46: 42 | B46: 502 input.pdf | C46: 46113 | D46: 46142 | E46: 46116 | F46: 46116 | G46: DIGITA-MUMBAI/ NEFT-AXISCN1301297166-PINE LABS PRIVATE LIMITED-NO | I46: Receipt | J46: 0 | K46: 22400 | L46: 22400 | M46: 26900 | N46: Recurring Transaction | O46: Yes | P46: PINE LABS PRIVATE LIMITED | Q46: 0 | R46: 1 | S46: 0 | T46: 0 | U46: 0 | V46: 0 | W46: 0 | X46: 0 | Y46: 0 | Z46: 0 | AA46: 46116 | AB46: =HYPERLINK("#'Transactions'!A43", "View Source Row")
A47: 43 | B47: 502 input.pdf | C47: 46113 | D47: 46142 | E47: 46116 | F47: 46116 | G47: DIGITA-MUMBAI/ NEFT-HDFCH00909652553-KUNDAN QUARRY ---------------------------------------------------------------------------------------------------------------------------------- Page Total: 10,30,195.58 10,24,219.58 32,700.00Cr ---------------------------------------------------------------------------------------------------------------------------------- Note: Cheques received in inward clearing will be considered for debiting/ returning on the basis opening balance in account Unless the c | I47: Receipt | J47: 0 | K47: 5800 | L47: 5800 | M47: 32700 | N47: Recurring Transaction | O47: Yes | P47: KUNDAN QUARRY | Q47: 0 | R47: 1 | S47: 0 | T47: 0 | U47: 0 | V47: 0 | W47: 0 | X47: 0 | Y47: 0 | Z47: 0 | AA47: 46116 | AB47: =HYPERLINK("#'Transactions'!A44", "View Source Row")
A48: 44 | B48: 502 input.pdf | C48: 46113 | D48: 46142 | E48: 46116 | F48: 46116 | G48: UPI/6094661908 66190812 UPI/609466190812/12:12:08/UPI/starbazaarhyper@ybl | I48: Payment | J48: 150.63 | K48: 0 | L48: 150.63 | M48: 32549.37 | N48: UPI | O48: No | P48: STARBAZAARHYPERYBL | Q48: 0 | R48: 0 | S48: 0 | T48: 0 | U48: 0 | V48: 1 | W48: 0 | X48: 0 | Y48: 0 | Z48: 0 | AA48: 46116 | AB48: =HYPERLINK("#'Transactions'!A45", "View Source Row")
A49: 45 | B49: 502 input.pdf | C49: 46113 | D49: 46142 | E49: 46116 | F49: 46116 | G49: DIGITA-MUMBAI/ NEFT-KKBKH26094919635-ATLAS COMMODITIES PRIVATE LI | I49: Receipt | J49: 0 | K49: 7885 | L49: 7885 | M49: 40434.37 | N49: Recurring Transaction | O49: Yes | P49: ATLAS COMMODITIES PRIVATE LI | Q49: 0 | R49: 1 | S49: 0 | T49: 0 | U49: 0 | V49: 0 | W49: 0 | X49: 0 | Y49: 0 | Z49: 0 | AA49: 46116 | AB49: =HYPERLINK("#'Transactions'!A46", "View Source Row")
A50: 46 | B50: 502 input.pdf | C50: 46113 | D50: 46142 | E50: 46116 | F50: 46116 | G50: DIGITA-MUMBAI/ IMPS/P2A/609418057716/PRASAD ROADS AN/JigeeshaICI | I50: Receipt | J50: 0 | K50: 81396 | L50: 81396 | M50: 121830.37 | N50: Other | O50: No | P50: PRASAD ROADS AN | Q50: 0 | R50: 0 | S50: 0 | T50: 0 | U50: 0 | V50: 0 | W50: 0 | X50: 0 | Y50: 0 | Z50: 0 | AA50: 46116 | AB50: =HYPERLINK("#'Transactions'!A47", "View Source Row")
A51: 47 | B51: 502 input.pdf | C51: 46113 | D51: 46142 | E51: 46116 | F51: 46116 | G51: EBANK:WIB/1502 EBANK:WIB/1502545632/Edfs | I51: Payment | J51: 120330.37 | K51: 0 | L51: 120330.37 | M51: 1500 | N51: High Transaction; Recurring Transaction | O51: Yes | P51: EBANKWIB | Q51: 0 | R51: 1 | S51: 0 | T51: 0 | U51: 1 | V51: 0 | W51: 0 | X51: 0 | Y51: 0 | Z51: 0 | AA51: 46116 | AB51: =HYPERLINK("#'Transactions'!A48", "View Source Row")
A52: 48 | B52: 502 input.pdf | C52: 46113 | D52: 46142 | E52: 46116 | F52: 46116 | G52: DIGITA-MUMBAI/ NEFT-HDFCH00911243518-KAVITA ENTERPRISES | I52: Receipt | J52: 0 | K52: 81396 | L52: 81396 | M52: 82896 | N52: Recurring Transaction | O52: Yes | P52: KAVITA ENTERPRISES | Q52: 0 | R52: 1 | S52: 0 | T52: 0 | U52: 0 | V52: 0 | W52: 0 | X52: 0 | Y52: 0 | Z52: 0 | AA52: 46116 | AB52: =HYPERLINK("#'Transactions'!A49", "View Source Row")
A53: 49 | B53: 502 input.pdf | C53: 46113 | D53: 46142 | E53: 46117 | F53: 46117 | G53: DIGITA-MUMBAI/ NEFT-YESAP60953903247-PhonePe Limited | I53: Receipt | J53: 0 | K53: 167015 | L53: 167015 | M53: 249911 | N53: High Transaction; Recurring Transaction | O53: Yes | P53: PHONEPE LIMITED | Q53: 0 | R53: 1 | S53: 0 | T53: 0 | U53: 1 | V53: 0 | W53: 0 | X53: 0 | Y53: 0 | Z53: 0 | AA53: 46117 | AB53: =HYPERLINK("#'Transactions'!A50", "View Source Row")
A54: 50 | B54: 502 input.pdf | C54: 46113 | D54: 46142 | E54: 46117 | F54: 46117 | G54: DIGITA-MUMBAI/ NEFT-AXNPN09528140899-PHONEPE LIMITED-PAYMENT AGGR | I54: Receipt | J54: 0 | K54: 67868.36 | L54: 67868.36 | M54: 317779.36 | N54: Recurring Transaction | O54: Yes | P54: PHONEPE LIMITED | Q54: 0 | R54: 1 | S54: 0 | T54: 0 | U54: 0 | V54: 0 | W54: 0 | X54: 0 | Y54: 0 | Z54: 0 | AA54: 46117 | AB54: =HYPERLINK("#'Transactions'!A51", "View Source Row")
A55: 51 | B55: 502 input.pdf | C55: 46113 | D55: 46142 | E55: 46117 | F55: 46117 | G55: DIGITA-MUMBAI/ NEFT-AXISCN1301923332-ONE MOBIKWIK SYSTEMS LIMITED | I55: Receipt | J55: 0 | K55: 28124 | L55: 28124 | M55: 345903.36 | N55: Recurring Transaction | O55: Yes | P55: ONE MOBIKWIK SYSTEMS LIMITED | Q55: 0 | R55: 1 | S55: 0 | T55: 0 | U55: 0 | V55: 0 | W55: 0 | X55: 0 | Y55: 0 | Z55: 0 | AA55: 46117 | AB55: =HYPERLINK("#'Transactions'!A52", "View Source Row")
A56: 52 | B56: 502 input.pdf | C56: 46113 | D56: 46142 | E56: 46117 | F56: 46117 | G56: EBANK:WIB/1502 EBANK:WIB/1502577386/Edfs | I56: Payment | J56: 300403.36 | K56: 0 | L56: 300403.36 | M56: 45500 | N56: High Transaction; Recurring Transaction | O56: Yes | P56: EBANKWIB | Q56: 0 | R56: 1 | S56: 0 | T56: 0 | U56: 1 | V56: 0 | W56: 0 | X56: 0 | Y56: 0 | Z56: 0 | AA56: 46117 | AB56: =HYPERLINK("#'Transactions'!A53", "View Source Row")
A57: 53 | B57: 502 input.pdf | C57: 46113 | D57: 46142 | E57: 46117 | F57: 46117 | G57: DIGITA-MUMBAI/ IMPS/P2A/609509137308/SHREE GANESH EN/diselVVS910 | I57: Receipt | J57: 0 | K57: 63308 | L57: 63308 | M57: 108808 | N57: Recurring Transaction | O57: Yes | P57: SHREE GANESH EN | Q57: 0 | R57: 1 | S57: 0 | T57: 0 | U57: 0 | V57: 0 | W57: 0 | X57: 0 | Y57: 0 | Z57: 0 | AA57: 46117 | AB57: =HYPERLINK("#'Transactions'!A54", "View Source Row")
A58: 54 | B58: 502 input.pdf | C58: 46113 | D58: 46142 | E58: 46118 | F58: 46118 | G58: DIGITA-MUMBAI/ NEFT-AXNPN09635263353-PHONEPE LIMITED-PAYMENT AGGR | I58: Receipt | J58: 0 | K58: 58335.21 | L58: 58335.21 | M58: 167143.21 | N58: Recurring Transaction | O58: Yes | P58: PHONEPE LIMITED | Q58: 0 | R58: 1 | S58: 0 | T58: 0 | U58: 0 | V58: 0 | W58: 0 | X58: 0 | Y58: 0 | Z58: 0 | AA58: 46118 | AB58: =HYPERLINK("#'Transactions'!A55", "View Source Row")
A59: 55 | B59: 502 input.pdf | C59: 46113 | D59: 46142 | E59: 46118 | F59: 46118 | G59: DIGITA-MUMBAI/ NEFT-YESAP60964000643-PhonePe Limited | I59: Receipt | J59: 0 | K59: 169456 | L59: 169456 | M59: 336599.21 | N59: High Transaction; Recurring Transaction | O59: Yes | P59: PHONEPE LIMITED | Q59: 0 | R59: 1 | S59: 0 | T59: 0 | U59: 1 | V59: 0 | W59: 0 | X59: 0 | Y59: 0 | Z59: 0 | AA59: 46118 | AB59: =HYPERLINK("#'Transactions'!A56", "View Source Row")
A60: 56 | B60: 502 input.pdf | C60: 46113 | D60: 46142 | E60: 46118 | F60: 46118 | G60: DIGITA-MUMBAI/ NEFT-AXISCN1302642509-ONE MOBIKWIK SYSTEMS LIMITED | I60: Receipt | J60: 0 | K60: 31681 | L60: 31681 | M60: 368280.21 | N60: Recurring Transaction | O60: Yes | P60: ONE MOBIKWIK SYSTEMS LIMITED | Q60: 0 | R60: 1 | S60: 0 | T60: 0 | U60: 0 | V60: 0 | W60: 0 | X60: 0 | Y60: 0 | Z60: 0 | AA60: 46118 | AB60: =HYPERLINK("#'Transactions'!A57", "View Source Row")
A61: 57 | B61: 502 input.pdf | C61: 46113 | D61: 46142 | E61: 46118 | F61: 46118 | G61: EBANK:WIB/1502 EBANK:WIB/1502642025/Edfs | I61: Payment | J61: 365780.21 | K61: 0 | L61: 365780.21 | M61: 2500 | N61: High Transaction; Recurring Transaction | O61: Yes | P61: EBANKWIB | Q61: 0 | R61: 1 | S61: 0 | T61: 0 | U61: 1 | V61: 0 | W61: 0 | X61: 0 | Y61: 0 | Z61: 0 | AA61: 46118 | AB61: =HYPERLINK("#'Transactions'!A58", "View Source Row")
A62: 58 | B62: 502 input.pdf | C62: 46113 | D62: 46142 | E62: 46118 | F62: 46118 | G62: DIGITA-MUMBAI/ NEFT-AXISCN1302721272-PINE LABS PRIVATE LIMITED-NO | I62: Receipt | J62: 0 | K62: 29516 | L62: 29516 | M62: 32016 | N62: Recurring Transaction | O62: Yes | P62: PINE LABS PRIVATE LIMITED | Q62: 0 | R62: 1 | S62: 0 | T62: 0 | U62: 0 | V62: 0 | W62: 0 | X62: 0 | Y62: 0 | Z62: 0 | AA62: 46118 | AB62: =HYPERLINK("#'Transactions'!A59", "View Source Row")
A63: 59 | B63: 502 input.pdf | C63: 46113 | D63: 46142 | E63: 46118 | F63: 46118 | G63: DIGITA-MUMBAI/ ---------------------------------------------------------------------------------------------------------------------------------- Page Total: 7,86,664.57 8,85,980.57 1,32,016.00Cr ---------------------------------------------------------------------------------------------------------------------------------- Note: Cheques received in inward clearing will be considered for debiting/ returning on the basis opening balance in account Unless the constituent notifies the bank of any | I63: Receipt | J63: 0 | K63: 100000 | L63: 100000 | M63: 132016 | N63: High Transaction; Recurring Transaction | O63: Yes | P63: PAGE TOTAL CR | Q63: 0 | R63: 1 | S63: 0 | T63: 0 | U63: 1 | V63: 0 | W63: 0 | X63: 0 | Y63: 0 | Z63: 0 | AA63: 46118 | AB63: =HYPERLINK("#'Transactions'!A60", "View Source Row")
A64: 60 | B64: 502 input.pdf | C64: 46113 | D64: 46142 | E64: 46118 | F64: 46118 | G64: DIGITA-MUMBAI/ NEFT-AXISCN1302925515-PINE LABS PRIVATE LIMITED-NO | I64: Receipt | J64: 0 | K64: 14073 | L64: 14073 | M64: 146089 | N64: Recurring Transaction | O64: Yes | P64: PINE LABS PRIVATE LIMITED | Q64: 0 | R64: 1 | S64: 0 | T64: 0 | U64: 0 | V64: 0 | W64: 0 | X64: 0 | Y64: 0 | Z64: 0 | AA64: 46118 | AB64: =HYPERLINK("#'Transactions'!A61", "View Source Row")
A65: 61 | B65: 502 input.pdf | C65: 46113 | D65: 46142 | E65: 46118 | F65: 46118 | G65: UPI/8321480914 48091426 UPI/832148091426/12:12:00/UPI/7507026281@axl/Paym | I65: Receipt | J65: 0 | K65: 1000 | L65: 1000 | M65: 147089 | N65: UPI | O65: No | P65: UPI/# # UPI/#/#:#:#/UPI/#@AXL/PAYM | Q65: 0 | R65: 0 | S65: 0 | T65: 0 | U65: 0 | V65: 1 | W65: 0 | X65: 0 | Y65: 0 | Z65: 0 | AA65: 46118 | AB65: =HYPERLINK("#'Transactions'!A62", "View Source Row")
A66: 62 | B66: 502 input.pdf | C66: 46113 | D66: 46142 | E66: 46118 | F66: 46118 | G66: DIGITA-MUMBAI/ NEFT-HDFCH00913518284-CORPAK | I66: Receipt | J66: 0 | K66: 38524 | L66: 38524 | M66: 185613 | N66: Recurring Transaction | O66: Yes | P66: DIGITA-MUMBAI/ NEFT-HDFCH#-CORPAK | Q66: 0 | R66: 1 | S66: 0 | T66: 0 | U66: 0 | V66: 0 | W66: 0 | X66: 0 | Y66: 0 | Z66: 0 | AA66: 46118 | AB66: =HYPERLINK("#'Transactions'!A63", "View Source Row")
A67: 63 | B67: 502 input.pdf | C67: 46113 | D67: 46142 | E67: 46118 | F67: 46118 | G67: DIGITA-MUMBAI/ NEFT-NKGSH26096901712-GEBI PRODUCTS PRIVATE LIMITE | I67: Receipt | J67: 0 | K67: 15001 | L67: 15001 | M67: 200614 | N67: Recurring Transaction | O67: Yes | P67: GEBI PRODUCTS PRIVATE LIMITE | Q67: 0 | R67: 1 | S67: 0 | T67: 0 | U67: 0 | V67: 0 | W67: 0 | X67: 0 | Y67: 0 | Z67: 0 | AA67: 46118 | AB67: =HYPERLINK("#'Transactions'!A64", "View Source Row")
A68: 64 | B68: 502 input.pdf | C68: 46113 | D68: 46142 | E68: 46118 | F68: 46118 | G68: EBANK:WIB/1502 EBANK:WIB/1502790855/Edfs | I68: Payment | J68: 198114 | K68: 0 | L68: 198114 | M68: 2500 | N68: High Transaction; Recurring Transaction | O68: Yes | P68: EBANKWIB | Q68: 0 | R68: 1 | S68: 0 | T68: 0 | U68: 1 | V68: 0 | W68: 0 | X68: 0 | Y68: 0 | Z68: 0 | AA68: 46118 | AB68: =HYPERLINK("#'Transactions'!A65", "View Source Row")
A69: 65 | B69: 502 input.pdf | C69: 46113 | D69: 46142 | E69: 46118 | F69: 46118 | G69: DIGITA-MUMBAI/ NEFT-HDFCH00915259780-MOHANJI BHARAT WELFARE FOUND | I69: Receipt | J69: 0 | K69: 18448 | L69: 18448 | M69: 20948 | N69: Recurring Transaction | O69: Yes | P69: MOHANJI BHARAT WELFARE FOUND | Q69: 0 | R69: 1 | S69: 0 | T69: 0 | U69: 0 | V69: 0 | W69: 0 | X69: 0 | Y69: 0 | Z69: 0 | AA69: 46118 | AB69: =HYPERLINK("#'Transactions'!A66", "View Source Row")
A70: 66 | B70: 502 input.pdf | C70: 46113 | D70: 46142 | E70: 46119 | F70: 46119 | G70: DIGITA-MUMBAI/ NEFT-YESAP60974165954-PhonePe Limited | I70: Receipt | J70: 0 | K70: 260044.42 | L70: 260044.42 | M70: 280992.42 | N70: High Transaction; Recurring Transaction | O70: Yes | P70: PHONEPE LIMITED | Q70: 0 | R70: 1 | S70: 0 | T70: 0 | U70: 1 | V70: 0 | W70: 0 | X70: 0 | Y70: 0 | Z70: 0 | AA70: 46119 | AB70: =HYPERLINK("#'Transactions'!A67", "View Source Row")
A71: 67 | B71: 502 input.pdf | C71: 46113 | D71: 46142 | E71: 46119 | F71: 46119 | G71: DIGITA-MUMBAI/ NEFT-AXNPN09743969962-PHONEPE LIMITED-PAYMENT AGGR | I71: Receipt | J71: 0 | K71: 55000.65 | L71: 55000.65 | M71: 335993.07 | N71: Recurring Transaction | O71: Yes | P71: PHONEPE LIMITED | Q71: 0 | R71: 1 | S71: 0 | T71: 0 | U71: 0 | V71: 0 | W71: 0 | X71: 0 | Y71: 0 | Z71: 0 | AA71: 46119 | AB71: =HYPERLINK("#'Transactions'!A68", "View Source Row")
A72: 68 | B72: 502 input.pdf | C72: 46113 | D72: 46142 | E72: 46119 | F72: 46119 | G72: EBANK:WIB/1502 EBANK:WIB/1502821939/Edfs | I72: Payment | J72: 330493.07 | K72: 0 | L72: 330493.07 | M72: 5500 | N72: High Transaction; Recurring Transaction | O72: Yes | P72: EBANKWIB | Q72: 0 | R72: 1 | S72: 0 | T72: 0 | U72: 1 | V72: 0 | W72: 0 | X72: 0 | Y72: 0 | Z72: 0 | AA72: 46119 | AB72: =HYPERLINK("#'Transactions'!A69", "View Source Row")
A73: 69 | B73: 502 input.pdf | C73: 46113 | D73: 46142 | E73: 46119 | F73: 46119 | G73: UPI/8639137766 13776666 UPI/863913776666/06:48:44/UPI/surajdhanotra1@ibl/ | I73: Receipt | J73: 0 | K73: 9000 | L73: 9000 | M73: 14500 | N73: UPI; Recurring Transaction | O73: Yes | P73: SURAJDHANOTRAIBL | Q73: 0 | R73: 1 | S73: 0 | T73: 0 | U73: 0 | V73: 1 | W73: 0 | X73: 0 | Y73: 0 | Z73: 0 | AA73: 46119 | AB73: =HYPERLINK("#'Transactions'!A70", "View Source Row")
A74: 70 | B74: 502 input.pdf | C74: 46113 | D74: 46142 | E74: 46119 | F74: 46119 | G74: DIGITA-MUMBAI/ NEFT-AXISCN1303901852-ONE MOBIKWIK SYSTEMS LIMITED | I74: Receipt | J74: 0 | K74: 23072 | L74: 23072 | M74: 37572 | N74: Recurring Transaction | O74: Yes | P74: ONE MOBIKWIK SYSTEMS LIMITED | Q74: 0 | R74: 1 | S74: 0 | T74: 0 | U74: 0 | V74: 0 | W74: 0 | X74: 0 | Y74: 0 | Z74: 0 | AA74: 46119 | AB74: =HYPERLINK("#'Transactions'!A71", "View Source Row")
A75: 71 | B75: 502 input.pdf | C75: 46113 | D75: 46142 | E75: 46119 | F75: 46119 | G75: DIGITA-MUMBAI/ NEFT-AXISCN1303985526-PINE LABS PRIVATE LIMITED-NO | I75: Receipt | J75: 0 | K75: 25110 | L75: 25110 | M75: 62682 | N75: Recurring Transaction | O75: Yes | P75: PINE LABS PRIVATE LIMITED | Q75: 0 | R75: 1 | S75: 0 | T75: 0 | U75: 0 | V75: 0 | W75: 0 | X75: 0 | Y75: 0 | Z75: 0 | AA75: 46119 | AB75: =HYPERLINK("#'Transactions'!A72", "View Source Row")
A76: 72 | B76: 502 input.pdf | C76: 46113 | D76: 46142 | E76: 46119 | F76: 46119 | G76: Charges for Charges for PORD Customer Payment :003566909942 | I76: Payment | J76: 2.65 | K76: 0 | L76: 2.65 | M76: 62679.35 | N76: Recurring Transaction | O76: Yes | P76: CHARGES FOR CHARGES FOR PORD CUSTOMER PA | Q76: 0 | R76: 1 | S76: 0 | T76: 0 | U76: 0 | V76: 0 | W76: 0 | X76: 0 | Y76: 0 | Z76: 0 | AA76: 46119 | AB76: =HYPERLINK("#'Transactions'!A73", "View Source Row")
